Workbook

Sheet Leeswijzer
A1: Financieel Vastgoedkompas · relationeel datamodel
A2: CONCEPT v0.1 · 2 oktober 2026 · KplusV · nog niet vastgesteld door het kernteam
A4: LET OP: dummy-data | B4: Deze werkmap is gevuld met DUMMY-gegevens als onderlegger voor een website-prototype. Wat hier staat is niet gecontroleerd en niet vastgesteld, en mag niet als inhoud van het Kompas worden gepubliceerd. Elk record dat is toegevoegd heeft in notes_internal de tekst DUMMY. Bij bestaande records staat 'DUMMY-aanvulling' met de velden die zijn aangevuld. Tabblad Dummy_overzicht telt per tabel.
A5: Wat is echt | B5: De 77 instrumenten (naam, omschrijving, bron, beheerder, eigenaartype, status) komen uit catalogus v0.1 van KplusV. Idem de hiaten- en dekkingsanalyse. De waardelijsten komen uit de modelbeschrijving. Alle koppelingen, classificaties en tekst die daarbovenop zijn gezet zijn dummy: rollen, fasen en beslismomenten per instrument, openstelling, voorwaarden, relaties, kennisproducten, validatie, feedback.
A6: Wat is verzonnen | B6: Alle beslismomenten, informatiebehoeften, handelingsperspectieven, knelpunten, informatieoverdracht, functietitels en kennisproducten. Idem alle datums van openstelling, controles en wijzigingen, en alle URL's naar example.org. Bedragen bij effecten zijn bewust leeg gelaten.
A7: Tabbladen vooraan | B7: Tabellen: overzicht van alle 65 tabellen met aantal records. Dummy_overzicht: per tabel hoeveel records echt zijn en hoeveel dummy. Velden: datadictionary met vulgraad. Keuzelijsten: toegestane waarden. Afwijkingen: gaten in de originele modelbeschrijving (de tabel beslismoment is hier met dummy gevuld, de gaten zelf zijn niet opgelost).
A8: Tabeltabbladen | B8: Rij 1 bevat de veldnamen precies zoals in het model. Verwijzingen (velden op _id) bevatten de leesbare code of naam van het doelrecord, bijvoorbeeld ROL-003 of I-001; entity_id bevat de UUID. Houd de muis op een kolomkop voor type, verplichting en toelichting.
A9: Voor de websitebouwer | B9: Naast deze werkmap staat dezelfde inhoud als JSON (kompas_dummy_data.json): per tabel een lijst records, met verwijzingen als leesbare sleutel. De hoofdroute voor navigatie: opgave > procesfase > beslismoment > rol, informatiebehoefte, financiële vraag, handelingsperspectief > instrument via instrument_beslismoment. Filters: rol, eigenaartype, objecttype, financiële vraag, financiële route, werkingsgebied, openstelling.
A10: Kleur kolomkop | B10: Donkerviolet = verplicht veld. Lichtviolet = optioneel veld. Grijs = standaard beheerveld.
A11: Datums en ja/nee | B11: Datums als jjjj-mm-dd. Booleans als ja of nee.
A12: Bron | B12: Modelbeschrijving 'Concreet datamodel Financieel Vastgoedkompas' en Financieel_Vastgoedkompas_instrumentendatabase_v0.1.xlsx (versie 4 september 2026).

Sheet Dummy_overzicht
A1: Dummy-overzicht
A2: Per tabel: aantal records, waarvan echt (uit catalogus v0.1 of waardelijst) en waarvan DUMMY. Dummy-records dragen DUMMY in notes_internal.
A4: Nr | B4: Tabel | C4: Domein | D4: Records | E4: Echt / voorstel | F4: DUMMY | G4: Aandeel DUMMY
A5: 1 | B5: opgave | C5: A. Navigatie | D5: 10 | E5: 0 | F5: 10 | G5: =IF(D5=0,0,F5/D5) -> 1
A6: 2 | B6: procesniveau | C6: A. Navigatie | D6: 4 | E6: 0 | F6: 4 | G6: =IF(D6=0,0,F6/D6) -> 1
A7: 3 | B7: procesfase | C7: A. Navigatie | D7: 12 | E7: 0 | F7: 12 | G7: =IF(D7=0,0,F7/D7) -> 1
A8: 4 | B8: procesfase_relatie | C8: A. Navigatie | D8: 16 | E8: 0 | F8: 16 | G8: =IF(D8=0,0,F8/D8) -> 1
A9: 5 | B9: beslismoment | C9: A. Navigatie | D9: 16 | E9: 0 | F9: 16 | G9: =IF(D9=0,0,F9/D9) -> 1
A10: 6 | B10: besluittype | C10: A. Navigatie | D10: 14 | E10: 14 | F10: 0 | G10: =IF(D10=0,0,F10/D10) -> 0
A11: 7 | B11: rol | C11: A. Navigatie | D11: 22 | E11: 0 | F11: 22 | G11: =IF(D11=0,0,F11/D11) -> 1
A12: 8 | B12: rolcluster | C12: A. Navigatie | D12: 9 | E12: 9 | F12: 0 | G12: =IF(D12=0,0,F12/D12) -> 0
A13: 9 | B13: functie_alias | C13: A. Navigatie | D13: 18 | E13: 0 | F13: 18 | G13: =IF(D13=0,0,F13/D13) -> 1
A14: 10 | B14: eigenaartype | C14: A. Navigatie | D14: 10 | E14: 10 | F14: 0 | G14: =IF(D14=0,0,F14/D14) -> 0
A15: 11 | B15: objecttype | C15: A. Navigatie | D15: 21 | E15: 21 | F15: 0 | G15: =IF(D15=0,0,F15/D15) -> 0
A16: 12 | B16: financiele_vraag | C16: B. Besluitondersteuning | D16: 12 | E16: 0 | F16: 12 | G16: =IF(D16=0,0,F16/D16) -> 1
... A69: 65 | B69: gebruikersfeedback | C69: D. Beheer en validatie | D69: 8 | E69: 0 | F69: 8 | G69: =IF(D69=0,0,F69/D69) -> 1
B70: Totaal | D70: =SUM(D5:D69) -> 2325 | E70: =SUM(E5:E69) -> 278 | F70: =SUM(F5:F69) -> 2047

Sheet Tabellen
A1: Overzicht tabellen
A2: Aantal records telt automatisch mee. Fase volgt §18 van de modelbeschrijving; 'niet ingedeeld' = daar niet genoemd.
A4: Nr | B4: Tabel (tabblad) | C4: Sectie | D4: Domein | E4: Soort | F4: Fase §18 | G4: Velden | H4: Verplichte velden | I4: Records | J4: Omschrijving
A5: 1 | B5: opgave | C5: 4.1 | D5: A. Navigatie | E5: entiteit | F5: 2 | G5: 20 | H5: 12 | I5: =COUNTA(opgave!$A$2:$A$2000) -> 10 | J5: Situatie, aanleiding of doel waarmee een gebruiker het Kompas binnenkomt.
A6: 2 | B6: procesniveau | C6: 4.2 | D6: A. Navigatie | E6: keuzelijsttabel | F6: 1 | G6: 14 | H6: 11 | I6: =COUNTA(procesniveau!$A$2:$A$2000) -> 4 | J6: Niveau waarop een proces speelt: portefeuille, programma, object of project.
A7: 3 | B7: procesfase | C7: 4.3 | D7: A. Navigatie | E7: entiteit | F7: 1 | G7: 21 | H7: 14 | I7: =COUNTA(procesfase!$A$2:$A$2000) -> 12 | J7: Fase binnen een procesniveau (voorstel: P1-P5 en O1-O7).
A8: 4 | B8: procesfase_relatie | C8: 4.4 | D8: A. Navigatie | E8: koppeltabel | F8: niet ingedeeld | G8: 16 | H8: 11 | I8: =COUNTA(procesfase_relatie!$A$2:$A$2000) -> 16 | J8: Verbindt fases aan elkaar zonder één lineair pad af te dwingen.
A9: 5 | B9: beslismoment | C9: 4.5 | D9: A. Navigatie | E9: entiteit | F9: 1 | G9: 27 | H9: 18 | I9: =COUNTA(beslismoment!$A$2:$A$2000) -> 16 | J9: Centrale navigatie-entiteit: het moment waarop een besluit wordt voorbereid of genomen.
A10: 6 | B10: besluittype | C10: 4.6 | D10: A. Navigatie | E10: keuzelijsttabel | F10: niet ingedeeld | G10: 14 | H10: 10 | I10: =COUNTA(besluittype!$A$2:$A$2000) -> 14 | J10: Type besluit.
A11: 7 | B11: rol | C11: 4.7 | D11: A. Navigatie | E11: entiteit | F11: 1 | G11: 21 | H11: 16 | I11: =COUNTA(rol!$A$2:$A$2000) -> 22 | J11: Generieke rol, los van lokale functietitels.
A12: 8 | B12: rolcluster | C12: 4.8 | D12: A. Navigatie | E12: keuzelijsttabel | F12: niet ingedeeld | G12: 14 | H12: 10 | I12: =COUNTA(rolcluster!$A$2:$A$2000) -> 9 | J12: Cluster van rollen.
A13: 9 | B13: functie_alias | C13: 4.9 | D13: A. Navigatie | E13: entiteit | F13: niet ingedeeld | G13: 15 | H13: 10 | I13: =COUNTA(functie_alias!$A$2:$A$2000) -> 18 | J13: Koppelt gemeentelijke functietitels aan generieke rollen.
A14: 10 | B14: eigenaartype | C14: 4.10 | D14: A. Navigatie | E14: keuzelijsttabel | F14: 1 | G14: 15 | H14: 11 | I14: =COUNTA(eigenaartype!$A$2:$A$2000) -> 10 | J14: Type vastgoedeigenaar.
A15: 11 | B15: objecttype | C15: 4.11 | D15: A. Navigatie | E15: keuzelijsttabel | F15: 1 | G15: 15 | H15: 10 | I15: =COUNTA(objecttype!$A$2:$A$2000) -> 21 | J15: Hiërarchische indeling van vastgoedobjecten.
A16: 12 | B16: financiele_vraag | C16: 5.1 | D16: B. Besluitondersteuning | E16: entiteit | F16: 1 | G16: 17 | H16: 12 | I16: =COUNTA(financiele_vraag!$A$2:$A$2000) -> 12 | J16: Financiële vraag die op een beslismoment speelt.
A17: 13 | B17: financieel_thema | C17: 5.2 | D17: B. Besluitondersteuning | E17: keuzelijsttabel | F17: 1 | G17: 15 | H17: 10 | I17: =COUNTA(financieel_thema!$A$2:$A$2000) -> 19 | J17: Financieel thema, hiërarchisch.
A18: 14 | B18: informatiebehoefte | C18: 5.3 | D18: B. Besluitondersteuning | E18: entiteit | F18: 2 | G18: 21 | H18: 13 | I18: =COUNTA(informatiebehoefte!$A$2:$A$2000) -> 15 | J18: Informatie die een rol op een beslismoment nodig heeft.
A19: 15 | B19: informatietype | C19: 5.4 | D19: B. Besluitondersteuning | E19: keuzelijsttabel | F19: niet ingedeeld | G19: 14 | H19: 10 | I19: =COUNTA(informatietype!$A$2:$A$2000) -> 18 | J19: Type informatie.
A20: 16 | B20: beslisproduct | C20: 5.5 | D20: B. Besluitondersteuning | E20: entiteit | F20: 2 | G20: 16 | H20: 11 | I20: =COUNTA(beslisproduct!$A$2:$A$2000) -> 15 | J20: Output waarmee een beslissing wordt voorbereid of onderbouwd.
A21: 17 | B21: handelingsperspectief | C21: 5.6 | D21: B. Besluitondersteuning | E21: entiteit | F21: 2 | G21: 18 | H21: 12 | I21: =COUNTA(handelingsperspectief!$A$2:$A$2000) -> 10 | J21: Concrete aanbevolen actie ('handelen boven informeren').
A22: 18 | B22: knelpunt | C22: 5.7 | D22: B. Besluitondersteuning | E22: entiteit | F22: niet ingedeeld | G22: 18 | H22: 13 | I22: =COUNTA(knelpunt!$A$2:$A$2000) -> 8 | J22: Risico of knelpunt in besluitvorming of informatieoverdracht.
A23: 19 | B23: informatieoverdracht | C23: 5.8 | D23: B. Besluitondersteuning | E23: entiteit | F23: 2 | G23: 20 | H23: 12 | I23: =COUNTA(informatieoverdracht!$A$2:$A$2000) -> 11 | J23: Welke rol welke informatie aan welke andere rol moet leveren op een beslismoment.
A24: 20 | B24: instrument | C24: 6.1 | D24: C. Instrumentenbibliotheek | E24: entiteit | F24: 1 | G24: 32 | H24: 18 | I24: =COUNTA(instrument!$A$2:$A$2000) -> 77 | J24: Instrument uit de catalogus.
A25: 21 | B25: instrumenttype | C25: 6.2 | D25: C. Instrumentenbibliotheek | E25: keuzelijsttabel | F25: 1 | G25: 15 | H25: 11 | I25: =COUNTA(instrumenttype!$A$2:$A$2000) -> 30 | J25: Type instrument, gegroepeerd in hoofdgroepen.
A26: 22 | B26: digitale_vorm | C26: 6.3 | D26: C. Instrumentenbibliotheek | E26: keuzelijsttabel | F26: niet ingedeeld | G26: 13 | H26: 9 | I26: =COUNTA(digitale_vorm!$A$2:$A$2000) -> 14 | J26: Digitale verschijningsvorm van een instrument.
A27: 23 | B27: organisatie | C27: 6.4 | D27: C. Instrumentenbibliotheek | E27: entiteit | F27: 1 | G27: 18 | H27: 9 | I27: =COUNTA(organisatie!$A$2:$A$2000) -> 56 | J27: Organisatie (bronhouder, verstrekker, beheerder enzovoort).
A28: 24 | B28: organisatietype | C28: 6.5 | D28: C. Instrumentenbibliotheek | E28: keuzelijsttabel | F28: niet ingedeeld | G28: 14 | H28: 10 | I28: =COUNTA(organisatietype!$A$2:$A$2000) -> 15 | J28: Type organisatie.
A29: 25 | B29: instrument_organisatie | C29: 6.6 | D29: C. Instrumentenbibliotheek | E29: koppeltabel | F29: niet ingedeeld | G29: 16 | H29: 10 | I29: =COUNTA(instrument_organisatie!$A$2:$A$2000) -> 77 | J29: Rol van een organisatie bij een instrument.
A30: 26 | B30: bron | C30: 6.7 | D30: C. Instrumentenbibliotheek | E30: entiteit | F30: 1 | G30: 24 | H30: 13 | I30: =COUNTA(bron!$A$2:$A$2000) -> 76 | J30: Bron waarop inhoud is gebaseerd.
A31: 27 | B31: brontype | C31: 6.8 | D31: C. Instrumentenbibliotheek | E31: keuzelijsttabel | F31: niet ingedeeld | G31: 14 | H31: 10 | I31: =COUNTA(brontype!$A$2:$A$2000) -> 14 | J31: Type bron.
A32: 28 | B32: instrument_bron | C32: 6.9 | D32: C. Instrumentenbibliotheek | E32: koppeltabel | F32: 1 | G32: 15 | H32: 11 | I32: =COUNTA(instrument_bron!$A$2:$A$2000) -> 77 | J32: Bronnen per instrument.
A33: 29 | B33: instrument_rol | C33: 7.1 | D33: C. Instrumentenbibliotheek | E33: koppeltabel | F33: 1 | G33: 16 | H33: 11 | I33: =COUNTA(instrument_rol!$A$2:$A$2000) -> 183 | J33: Voor welke rollen een instrument relevant is.
A34: 30 | B34: instrument_procesfase | C34: 7.2 | D34: C. Instrumentenbibliotheek | E34: koppeltabel | F34: 1 | G34: 15 | H34: 11 | I34: =COUNTA(instrument_procesfase!$A$2:$A$2000) -> 79 | J34: In welke procesfasen een instrument bruikbaar is.
A35: 31 | B35: instrument_beslismoment | C35: 7.3 | D35: C. Instrumentenbibliotheek | E35: koppeltabel | F35: 1 | G35: 17 | H35: 13 | I35: =COUNTA(instrument_beslismoment!$A$2:$A$2000) -> 79 | J35: Belangrijkste koppeltabel van de bronnenlaag: welk instrument welk beslismoment ondersteunt.
A36: 32 | B36: instrument_opgave | C36: 7.4 | D36: C. Instrumentenbibliotheek | E36: koppeltabel | F36: niet ingedeeld | G36: 14 | H36: 10 | I36: =COUNTA(instrument_opgave!$A$2:$A$2000) -> 154 | J36: Instrumenten per opgave.
A37: 33 | B37: instrument_financiele_vraag | C37: 7.5 | D37: C. Instrumentenbibliotheek | E37: koppeltabel | F37: 1 | G37: 15 | H37: 10 | I37: =COUNTA(instrument_financiele_vraag!$A$2:$A$2000) -> 150 | J37: Welke financiële vragen een instrument beantwoordt.
A38: 34 | B38: instrument_eigenaartype | C38: 7.6 | D38: C. Instrumentenbibliotheek | E38: koppeltabel | F38: 1 | G38: 15 | H38: 11 | I38: =COUNTA(instrument_eigenaartype!$A$2:$A$2000) -> 121 | J38: Toepasbaarheid per eigenaartype.
A39: 35 | B39: instrument_objecttype | C39: 7.7 | D39: C. Instrumentenbibliotheek | E39: koppeltabel | F39: 1 | G39: 15 | H39: 11 | I39: =COUNTA(instrument_objecttype!$A$2:$A$2000) -> 95 | J39: Toepasbaarheid per objecttype.
A40: 36 | B40: financiele_route | C40: 8.1 | D40: C. Instrumentenbibliotheek | E40: entiteit | F40: niet ingedeeld | G40: 18 | H40: 12 | I40: =COUNTA(financiele_route!$A$2:$A$2000) -> 17 | J40: Financiële oplossingsrichting.
A41: 37 | B41: instrument_financiele_route | C41: 8.2 | D41: C. Instrumentenbibliotheek | E41: koppeltabel | F41: niet ingedeeld | G41: 16 | H41: 10 | I41: =COUNTA(instrument_financiele_route!$A$2:$A$2000) -> 77 | J41: Instrumenten per financiële route.
A42: 38 | B42: effecttype | C42: 8.3 | D42: C. Instrumentenbibliotheek | E42: keuzelijsttabel | F42: 3 | G42: 14 | H42: 10 | I42: =COUNTA(effecttype!$A$2:$A$2000) -> 14 | J42: Type (financieel) effect van een instrument.
A43: 39 | B43: instrument_effect | C43: 8.4 | D43: C. Instrumentenbibliotheek | E43: koppeltabel | F43: 3 | G43: 21 | H43: 9 | I43: =COUNTA(instrument_effect!$A$2:$A$2000) -> 77 | J43: Effecten per instrument. Numerieke waarden alleen als ze expliciet uit een betrouwbare bron komen.
A44: 40 | B44: voorwaardetype | C44: 9.1 | D44: C. Instrumentenbibliotheek | E44: keuzelijsttabel | F44: 3 | G44: 14 | H44: 10 | I44: =COUNTA(voorwaardetype!$A$2:$A$2000) -> 19 | J44: Type toepassingsvoorwaarde.
A45: 41 | B45: instrument_voorwaarde | C45: 9.2 | D45: C. Instrumentenbibliotheek | E45: entiteit | F45: 3 | G45: 22 | H45: 12 | I45: =COUNTA(instrument_voorwaarde!$A$2:$A$2000) -> 82 | J45: Gestructureerde toepassingsvoorwaarde per instrument (basis voor vragenboom of persoonlijke adviseur).
A46: 42 | B46: werkingsgebied | C46: 10.1 | D46: C. Instrumentenbibliotheek | E46: keuzelijsttabel | F46: 3 | G46: 14 | H46: 9 | I46: =COUNTA(werkingsgebied!$A$2:$A$2000) -> 11 | J46: Geografisch werkingsgebied, hiërarchisch.
A47: 43 | B47: instrument_werkingsgebied | C47: 10.2 | D47: C. Instrumentenbibliotheek | E47: koppeltabel | F47: niet ingedeeld | G47: 14 | H47: 10 | I47: =COUNTA(instrument_werkingsgebied!$A$2:$A$2000) -> 83 | J47: Werkingsgebied per instrument.
A48: 44 | B48: openstelling | C48: 10.3 | D48: C. Instrumentenbibliotheek | E48: entiteit | F48: 3 | G48: 21 | H48: 10 | I48: =COUNTA(openstelling!$A$2:$A$2000) -> 32 | J48: Openstellingsperiode van een instrument.
A49: 45 | B49: pc_moment | C49: 10.4 | D49: C. Instrumentenbibliotheek | E49: keuzelijsttabel | F49: niet ingedeeld | G49: 16 | H49: 11 | I49: =COUNTA(pc_moment!$A$2:$A$2000) -> 13 | J49: P&C- of kalendermoment.
A50: 46 | B50: beslismoment_rol | C50: 11.1 | D50: B. Besluitondersteuning | E50: koppeltabel | F50: 2 | G50: 16 | H50: 10 | I50: =COUNTA(beslismoment_rol!$A$2:$A$2000) -> 64 | J50: Betrokkenheid van rollen bij een beslismoment.
A51: 47 | B51: beslismoment_informatiebehoefte | C51: 11.2 | D51: B. Besluitondersteuning | E51: koppeltabel | F51: 2 | G51: 17 | H51: 11 | I51: =COUNTA(beslismoment_informatiebehoefte!$A$2:$A$2000) -> 45 | J51: Informatiebehoeften per beslismoment (optioneel per rol).
A52: 48 | B52: beslismoment_financiele_vraag | C52: 11.3 | D52: B. Besluitondersteuning | E52: koppeltabel | F52: 2 | G52: 14 | H52: 10 | I52: =COUNTA(beslismoment_financiele_vraag!$A$2:$A$2000) -> 31 | J52: Financiële vragen per beslismoment.
A53: 49 | B53: beslismoment_beslisproduct | C53: 11.4 | D53: B. Besluitondersteuning | E53: koppeltabel | F53: 2 | G53: 15 | H53: 11 | I53: =COUNTA(beslismoment_beslisproduct!$A$2:$A$2000) -> 24 | J53: Beslisproducten per beslismoment.
A54: 50 | B54: beslismoment_handelingsperspectief | C54: 11.5 | D54: B. Besluitondersteuning | E54: koppeltabel | F54: 2 | G54: 15 | H54: 10 | I54: =COUNTA(beslismoment_handelingspersp!$A$2:$A$2000) -> 21 | J54: Handelingsperspectieven per beslismoment (optioneel per rol).
A55: 51 | B55: beslismoment_knelpunt | C55: 11.6 | D55: B. Besluitondersteuning | E55: koppeltabel | F55: niet ingedeeld | G55: 15 | H55: 9 | I55: =COUNTA(beslismoment_knelpunt!$A$2:$A$2000) -> 22 | J55: Knelpunten per beslismoment (optioneel per rol).
A56: 52 | B56: instrument_relatie | C56: 12.1 | D56: C. Instrumentenbibliotheek | E56: koppeltabel | F56: 3 | G56: 16 | H56: 11 | I56: =COUNTA(instrument_relatie!$A$2:$A$2000) -> 17 | J56: Relatie tussen twee instrumenten.
A57: 53 | B57: instrument_relatietype | C57: 12.2 | D57: C. Instrumentenbibliotheek | E57: keuzelijsttabel | F57: niet ingedeeld | G57: 14 | H57: 10 | I57: =COUNTA(instrument_relatietype!$A$2:$A$2000) -> 15 | J57: Type relatie tussen instrumenten.
A58: 54 | B58: kennisproduct | C58: 13.1 | D58: C. Instrumentenbibliotheek | E58: entiteit | F58: niet ingedeeld | G58: 20 | H58: 12 | I58: =COUNTA(kennisproduct!$A$2:$A$2000) -> 6 | J58: VMV-product of extern kennisproduct.
A59: 55 | B59: kennisproduct_instrument | C59: 13.2 | D59: C. Instrumentenbibliotheek | E59: koppeltabel | F59: niet ingedeeld | G59: 14 | H59: 10 | I59: =COUNTA(kennisproduct_instrument!$A$2:$A$2000) -> 12 | J59: Relatie kennisproduct - instrument.
A60: 56 | B60: kennisproduct_beslismoment | C60: 13.3 | D60: C. Instrumentenbibliotheek | E60: koppeltabel | F60: niet ingedeeld | G60: 14 | H60: 10 | I60: =COUNTA(kennisproduct_beslismoment!$A$2:$A$2000) -> 8 | J60: Relatie kennisproduct - beslismoment.
A61: 57 | B61: validation_status | C61: 14.1 | D61: D. Beheer en validatie | E61: keuzelijsttabel | F61: 1 | G61: 14 | H61: 10 | I61: =COUNTA(validation_status!$A$2:$A$2000) -> 9 | J61: Validatiestatus van inhoud.
A62: 58 | B62: publicatiestatus | C62: 14.2 | D62: D. Beheer en validatie | E62: keuzelijsttabel | F62: niet ingedeeld | G62: 14 | H62: 10 | I62: =COUNTA(publicatiestatus!$A$2:$A$2000) -> 7 | J62: Publicatiestatus.
A63: 59 | B63: inhoudelijke_status | C63: 14.3 | D63: D. Beheer en validatie | E63: keuzelijsttabel | F63: niet ingedeeld | G63: 14 | H63: 10 | I63: =COUNTA(inhoudelijke_status!$A$2:$A$2000) -> 8 | J63: Inhoudelijke status (actualiteit).
A64: 60 | B64: validatie | C64: 14.4 | D64: D. Beheer en validatie | E64: entiteit | F64: 3 | G64: 21 | H64: 13 | I64: =COUNTA(validatie!$A$2:$A$2000) -> 8 | J64: Uitgevoerde validatie van een willekeurig inhoudelijk record.
A65: 61 | B65: wijzigingslog | C65: 14.5 | D65: D. Beheer en validatie | E65: entiteit | F65: 3 | G65: 11 | H65: 7 | I65: =COUNTA(wijzigingslog!$A$2:$A$2000) -> 6 | J65: Wijzigingshistorie per record en veld.
A66: 62 | B66: reviewplanning | C66: 14.6 | D66: D. Beheer en validatie | E66: entiteit | F66: 3 | G66: 19 | H66: 11 | I66: =COUNTA(reviewplanning!$A$2:$A$2000) -> 10 | J66: Planning van periodieke controle per record.
A67: 63 | B67: kennisanalyse | C67: 15.1 | D67: D. Beheer en validatie | E67: entiteit | F67: 3 | G67: 26 | H67: 13 | I67: =COUNTA(kennisanalyse!$A$2:$A$2000) -> 16 | J67: Geconstateerde witte vlek, overlap of doublure.
A68: 64 | B68: ontwikkelactie | C68: 15.2 | D68: D. Beheer en validatie | E68: entiteit | F68: niet ingedeeld | G68: 19 | H68: 12 | I68: =COUNTA(ontwikkelactie!$A$2:$A$2000) -> 6 | J68: Actie op de ontwikkelagenda.
A69: 65 | B69: gebruikersfeedback | C69: 16.1 | D69: D. Beheer en validatie | E69: entiteit | F69: 3 | G69: 22 | H69: 12 | I69: =COUNTA(gebruikersfeedback!$A$2:$A$2000) -> 8 | J69: Feedback van gebruikers op een record of op het Kompas.
B70: Totaal | G70: =SUM(G5:G69) -> 1099 | H70: =SUM(H5:H69) -> 719 | I70: =SUM(I5:I69) -> 2325

Sheet Velden
A1: Datadictionary
A2: Eén regel per veld. 'Gevuld' en 'Leeg, verplicht' tellen automatisch mee met de tabeltabbladen.
A4: Tabel | B4: Veld | C4: Type | D4: Verplicht | E4: Sleutel | F4: Verwijst naar | G4: Keuzelijst | H4: Toelichting | I4: Gevuld | J4: Leeg, verplicht
A5: opgave | B5: opgave_id | C5: UUID | D5: ja | E5: PK | H5: Primaire sleutel | I5: =COUNTA(opgave!A$2:A$2000) -> 10 | J5: =IF(D5="ja",COUNTA(opgave!$A$2:$A$2000)-I5,"") -> 0
A6: opgave | B6: opgave_code | C6: varchar(20) | D6: ja | H6: Unieke functionele code | I6: =COUNTA(opgave!B$2:B$2000) -> 10 | J6: =IF(D6="ja",COUNTA(opgave!$A$2:$A$2000)-I6,"") -> 0
A7: opgave | B7: naam | C7: varchar(200) | D7: ja | H7: Korte naam | I7: =COUNTA(opgave!C$2:C$2000) -> 10 | J7: =IF(D7="ja",COUNTA(opgave!$A$2:$A$2000)-I7,"") -> 0
A8: opgave | B8: korte_omschrijving | C8: varchar(500) | D8: ja | H8: Tekst voor navigatie | I8: =COUNTA(opgave!D$2:D$2000) -> 10 | J8: =IF(D8="ja",COUNTA(opgave!$A$2:$A$2000)-I8,"") -> 0
A9: opgave | B9: uitgebreide_omschrijving | C9: text | D9: nee | H9: Nadere inhoud | I9: =COUNTA(opgave!E$2:E$2000) -> 0 | J9: =IF(D9="ja",COUNTA(opgave!$A$2:$A$2000)-I9,"")
A10: opgave | B10: aanleiding | C10: text | D10: nee | H10: Trigger of probleem | I10: =COUNTA(opgave!F$2:F$2000) -> 0 | J10: =IF(D10="ja",COUNTA(opgave!$A$2:$A$2000)-I10,"")
A11: opgave | B11: gewenst_resultaat | C11: text | D11: nee | H11: Beoogde uitkomst | I11: =COUNTA(opgave!G$2:G$2000) -> 10 | J11: =IF(D11="ja",COUNTA(opgave!$A$2:$A$2000)-I11,"")
A12: opgave | B12: niveau_default | C12: varchar(30) | D12: nee | G12: portefeuille; programma; object; project | H12: Portefeuille, programma, object, project | I12: =COUNTA(opgave!H$2:H$2000) -> 10 | J12: =IF(D12="ja",COUNTA(opgave!$A$2:$A$2000)-I12,"")
A13: opgave | B13: primaire_doelgroep | C13: varchar(100) | D13: nee | H13: Samenvattend | I13: =COUNTA(opgave!I$2:I$2000) -> 0 | J13: =IF(D13="ja",COUNTA(opgave!$A$2:$A$2000)-I13,"")
A14: opgave | B14: sort_order | C14: integer | D14: ja | H14: Volgorde in interface | I14: =COUNTA(opgave!J$2:J$2000) -> 10 | J14: =IF(D14="ja",COUNTA(opgave!$A$2:$A$2000)-I14,"") -> 0
A15: opgave | B15: is_public | C15: boolean | D15: ja | G15: ja; nee | H15: Publiceerbaar | I15: =COUNTA(opgave!K$2:K$2000) -> 10 | J15: =IF(D15="ja",COUNTA(opgave!$A$2:$A$2000)-I15,"") -> 0
A16: opgave | B16: created_at | C16: datetime | D16: ja | H16: Datum en tijd van aanmaak | I16: =COUNTA(opgave!L$2:L$2000) -> 10 | J16: =IF(D16="ja",COUNTA(opgave!$A$2:$A$2000)-I16,"") -> 0
A17: opgave | B17: created_by | C17: varchar(255) | D17: ja | H17: Maker | I17: =COUNTA(opgave!M$2:M$2000) -> 10 | J17: =IF(D17="ja",COUNTA(opgave!$A$2:$A$2000)-I17,"") -> 0
A18: opgave | B18: updated_at | C18: datetime | D18: ja | H18: Laatste wijziging | I18: =COUNTA(opgave!N$2:N$2000) -> 10 | J18: =IF(D18="ja",COUNTA(opgave!$A$2:$A$2000)-I18,"") -> 0
A19: opgave | B19: updated_by | C19: varchar(255) | D19: ja | H19: Laatste bewerker | I19: =COUNTA(opgave!O$2:O$2000) -> 10 | J19: =IF(D19="ja",COUNTA(opgave!$A$2:$A$2000)-I19,"") -> 0
A20: opgave | B20: record_status | C20: varchar(30) | D20: ja | G20: actief; concept; gearchiveerd | H20: Actief, concept, gearchiveerd | I20: =COUNTA(opgave!P$2:P$2000) -> 10 | J20: =IF(D20="ja",COUNTA(opgave!$A$2:$A$2000)-I20,"") -> 0
A21: opgave | B21: version_number | C21: integer | D21: ja | H21: Versienummer van record | I21: =COUNTA(opgave!Q$2:Q$2000) -> 10 | J21: =IF(D21="ja",COUNTA(opgave!$A$2:$A$2000)-I21,"") -> 0
A22: opgave | B22: valid_from | C22: date | D22: nee | H22: Geldig vanaf | I22: =COUNTA(opgave!R$2:R$2000) -> 0 | J22: =IF(D22="ja",COUNTA(opgave!$A$2:$A$2000)-I22,"")
A23: opgave | B23: valid_until | C23: date | D23: nee | H23: Geldig tot | I23: =COUNTA(opgave!S$2:S$2000) -> 0 | J23: =IF(D23="ja",COUNTA(opgave!$A$2:$A$2000)-I23,"")
A24: opgave | B24: notes_internal | C24: text | D24: nee | H24: Interne beheerinformatie | I24: =COUNTA(opgave!T$2:T$2000) -> 10 | J24: =IF(D24="ja",COUNTA(opgave!$A$2:$A$2000)-I24,"")
A25: procesniveau | B25: procesniveau_id | C25: UUID | D25: ja | E25: PK | H25: Primaire sleutel | I25: =COUNTA(procesniveau!A$2:A$2000) -> 4 | J25: =IF(D25="ja",COUNTA(procesniveau!$A$2:$A$2000)-I25,"") -> 0
A26: procesniveau | B26: code | C26: varchar(10) | D26: ja | H26: PORT, PROG, OBJ, PROJ | I26: =COUNTA(procesniveau!B$2:B$2000) -> 4 | J26: =IF(D26="ja",COUNTA(procesniveau!$A$2:$A$2000)-I26,"") -> 0
A27: procesniveau | B27: naam | C27: varchar(100) | D27: ja | H27: Naam niveau | I27: =COUNTA(procesniveau!C$2:C$2000) -> 4 | J27: =IF(D27="ja",COUNTA(procesniveau!$A$2:$A$2000)-I27,"") -> 0
A28: procesniveau | B28: omschrijving | C28: text | D28: ja | H28: Afbakening | I28: =COUNTA(procesniveau!D$2:D$2000) -> 4 | J28: =IF(D28="ja",COUNTA(procesniveau!$A$2:$A$2000)-I28,"") -> 0
A29: procesniveau | B29: sort_order | C29: integer | D29: ja | H29: Volgorde | I29: =COUNTA(procesniveau!E$2:E$2000) -> 4 | J29: =IF(D29="ja",COUNTA(procesniveau!$A$2:$A$2000)-I29,"") -> 0
A30: procesniveau | B30: created_at | C30: datetime | D30: ja | H30: Datum en tijd van aanmaak | I30: =COUNTA(procesniveau!F$2:F$2000) -> 4 | J30: =IF(D30="ja",COUNTA(procesniveau!$A$2:$A$2000)-I30,"") -> 0
A31: procesniveau | B31: created_by | C31: varchar(255) | D31: ja | H31: Maker | I31: =COUNTA(procesniveau!G$2:G$2000) -> 4 | J31: =IF(D31="ja",COUNTA(procesniveau!$A$2:$A$2000)-I31,"") -> 0
A32: procesniveau | B32: updated_at | C32: datetime | D32: ja | H32: Laatste wijziging | I32: =COUNTA(procesniveau!H$2:H$2000) -> 4 | J32: =IF(D32="ja",COUNTA(procesniveau!$A$2:$A$2000)-I32,"") -> 0
A33: procesniveau | B33: updated_by | C33: varchar(255) | D33: ja | H33: Laatste bewerker | I33: =COUNTA(procesniveau!I$2:I$2000) -> 4 | J33: =IF(D33="ja",COUNTA(procesniveau!$A$2:$A$2000)-I33,"") -> 0
A34: procesniveau | B34: record_status | C34: varchar(30) | D34: ja | G34: actief; concept; gearchiveerd | H34: Actief, concept, gearchiveerd | I34: =COUNTA(procesniveau!J$2:J$2000) -> 4 | J34: =IF(D34="ja",COUNTA(procesniveau!$A$2:$A$2000)-I34,"") -> 0
A35: procesniveau | B35: version_number | C35: integer | D35: ja | H35: Versienummer van record | I35: =COUNTA(procesniveau!K$2:K$2000) -> 4 | J35: =IF(D35="ja",COUNTA(procesniveau!$A$2:$A$2000)-I35,"") -> 0
A36: procesniveau | B36: valid_from | C36: date | D36: nee | H36: Geldig vanaf | I36: =COUNTA(procesniveau!L$2:L$2000) -> 0 | J36: =IF(D36="ja",COUNTA(procesniveau!$A$2:$A$2000)-I36,"")
A37: procesniveau | B37: valid_until | C37: date | D37: nee | H37: Geldig tot | I37: =COUNTA(procesniveau!M$2:M$2000) -> 0 | J37: =IF(D37="ja",COUNTA(procesniveau!$A$2:$A$2000)-I37,"")
A38: procesniveau | B38: notes_internal | C38: text | D38: nee | H38: Interne beheerinformatie | I38: =COUNTA(procesniveau!N$2:N$2000) -> 4 | J38: =IF(D38="ja",COUNTA(procesniveau!$A$2:$A$2000)-I38,"")
A39: procesfase | B39: procesfase_id | C39: UUID | D39: ja | E39: PK | H39: Primaire sleutel | I39: =COUNTA(procesfase!A$2:A$2000) -> 12 | J39: =IF(D39="ja",COUNTA(procesfase!$A$2:$A$2000)-I39,"") -> 0
A40: procesfase | B40: procesniveau_id | C40: UUID, FK | D40: ja | E40: FK | F40: procesniveau.code | H40: Verwijzing naar procesniveau | I40: =COUNTA(procesfase!B$2:B$2000) -> 12 | J40: =IF(D40="ja",COUNTA(procesfase!$A$2:$A$2000)-I40,"") -> 0
A41: procesfase | B41: fase_code | C41: varchar(20) | D41: ja | H41: Bijvoorbeeld P3 of O4 | I41: =COUNTA(procesfase!C$2:C$2000) -> 12 | J41: =IF(D41="ja",COUNTA(procesfase!$A$2:$A$2000)-I41,"") -> 0
A42: procesfase | B42: naam | C42: varchar(200) | D42: ja | H42: Naam fase | I42: =COUNTA(procesfase!D$2:D$2000) -> 12 | J42: =IF(D42="ja",COUNTA(procesfase!$A$2:$A$2000)-I42,"") -> 0
A43: procesfase | B43: centrale_vraag | C43: text | D43: ja | H43: Vraag die in deze fase centraal staat | I43: =COUNTA(procesfase!E$2:E$2000) -> 12 | J43: =IF(D43="ja",COUNTA(procesfase!$A$2:$A$2000)-I43,"") -> 0
A44: procesfase | B44: omschrijving | C44: text | D44: nee | H44: Inhoud van de fase | I44: =COUNTA(procesfase!F$2:F$2000) -> 12 | J44: =IF(D44="ja",COUNTA(procesfase!$A$2:$A$2000)-I44,"")
A45: procesfase | B45: startcriterium | C45: text | D45: nee | H45: Wanneer begint de fase? | I45: =COUNTA(procesfase!G$2:G$2000) -> 12 | J45: =IF(D45="ja",COUNTA(procesfase!$A$2:$A$2000)-I45,"")
A46: procesfase | B46: eindcriterium | C46: text | D46: nee | H46: Wanneer is zij afgerond? | I46: =COUNTA(procesfase!H$2:H$2000) -> 12 | J46: =IF(D46="ja",COUNTA(procesfase!$A$2:$A$2000)-I46,"")
A47: procesfase | B47: standaard_resultaat | C47: text | D47: nee | H47: Verwachte output | I47: =COUNTA(procesfase!I$2:I$2000) -> 12 | J47: =IF(D47="ja",COUNTA(procesfase!$A$2:$A$2000)-I47,"")
A48: procesfase | B48: sort_order | C48: integer | D48: ja | H48: Volgorde binnen niveau | I48: =COUNTA(procesfase!J$2:J$2000) -> 12 | J48: =IF(D48="ja",COUNTA(procesfase!$A$2:$A$2000)-I48,"") -> 0
A49: procesfase | B49: is_work_hypothesis | C49: boolean | D49: ja | G49: ja; nee | H49: Nog te valideren | I49: =COUNTA(procesfase!K$2:K$2000) -> 12 | J49: =IF(D49="ja",COUNTA(procesfase!$A$2:$A$2000)-I49,"") -> 0
A50: procesfase | B50: validation_status_id | C50: UUID, FK | D50: ja | E50: FK | F50: validation_status.code | H50: Status inhoudelijke validatie | I50: =COUNTA(procesfase!L$2:L$2000) -> 12 | J50: =IF(D50="ja",COUNTA(procesfase!$A$2:$A$2000)-I50,"") -> 0
A51: procesfase | B51: created_at | C51: datetime | D51: ja | H51: Datum en tijd van aanmaak | I51: =COUNTA(procesfase!M$2:M$2000) -> 12 | J51: =IF(D51="ja",COUNTA(procesfase!$A$2:$A$2000)-I51,"") -> 0
A52: procesfase | B52: created_by | C52: varchar(255) | D52: ja | H52: Maker | I52: =COUNTA(procesfase!N$2:N$2000) -> 12 | J52: =IF(D52="ja",COUNTA(procesfase!$A$2:$A$2000)-I52,"") -> 0
A53: procesfase | B53: updated_at | C53: datetime | D53: ja | H53: Laatste wijziging | I53: =COUNTA(procesfase!O$2:O$2000) -> 12 | J53: =IF(D53="ja",COUNTA(procesfase!$A$2:$A$2000)-I53,"") -> 0
A54: procesfase | B54: updated_by | C54: varchar(255) | D54: ja | H54: Laatste bewerker | I54: =COUNTA(procesfase!P$2:P$2000) -> 12 | J54: =IF(D54="ja",COUNTA(procesfase!$A$2:$A$2000)-I54,"") -> 0
A55: procesfase | B55: record_status | C55: varchar(30) | D55: ja | G55: actief; concept; gearchiveerd | H55: Actief, concept, gearchiveerd | I55: =COUNTA(procesfase!Q$2:Q$2000) -> 12 | J55: =IF(D55="ja",COUNTA(procesfase!$A$2:$A$2000)-I55,"") -> 0
A56: procesfase | B56: version_number | C56: integer | D56: ja | H56: Versienummer van record | I56: =COUNTA(procesfase!R$2:R$2000) -> 12 | J56: =IF(D56="ja",COUNTA(procesfase!$A$2:$A$2000)-I56,"") -> 0
A57: procesfase | B57: valid_from | C57: date | D57: nee | H57: Geldig vanaf | I57: =COUNTA(procesfase!S$2:S$2000) -> 0 | J57: =IF(D57="ja",COUNTA(procesfase!$A$2:$A$2000)-I57,"")
A58: procesfase | B58: valid_until | C58: date | D58: nee | H58: Geldig tot | I58: =COUNTA(procesfase!T$2:T$2000) -> 0 | J58: =IF(D58="ja",COUNTA(procesfase!$A$2:$A$2000)-I58,"")
A59: procesfase | B59: notes_internal | C59: text | D59: nee | H59: Interne beheerinformatie | I59: =COUNTA(procesfase!U$2:U$2000) -> 12 | J59: =IF(D59="ja",COUNTA(procesfase!$A$2:$A$2000)-I59,"")
A60: procesfase_relatie | B60: procesfase_relatie_id | C60: UUID | D60: ja | E60: PK | I60: =COUNTA(procesfase_relatie!A$2:A$2000) -> 16 | J60: =IF(D60="ja",COUNTA(procesfase_relatie!$A$2:$A$2000)-I60,"") -> 0
A61: procesfase_relatie | B61: van_procesfase_id | C61: UUID, FK | D61: ja | E61: FK | F61: procesfase.fase_code | I61: =COUNTA(procesfase_relatie!B$2:B$2000) -> 16 | J61: =IF(D61="ja",COUNTA(procesfase_relatie!$A$2:$A$2000)-I61,"") -> 0
A62: procesfase_relatie | B62: naar_procesfase_id | C62: UUID, FK | D62: ja | E62: FK | F62: procesfase.fase_code | I62: =COUNTA(procesfase_relatie!C$2:C$2000) -> 16 | J62: =IF(D62="ja",COUNTA(procesfase_relatie!$A$2:$A$2000)-I62,"") -> 0
A63: procesfase_relatie | B63: relatietype | C63: varchar(30) | D63: ja | G63: volgt op; kan volgen op; keert terug naar; leidt parallel tot; activeert; herijkt | I63: =COUNTA(procesfase_relatie!D$2:D$2000) -> 16 | J63: =IF(D63="ja",COUNTA(procesfase_relatie!$A$2:$A$2000)-I63,"") -> 0
A64: procesfase_relatie | B64: voorwaarde | C64: text | D64: nee | I64: =COUNTA(procesfase_relatie!E$2:E$2000) -> 2 | J64: =IF(D64="ja",COUNTA(procesfase_relatie!$A$2:$A$2000)-I64,"")
A65: procesfase_relatie | B65: is_default_route | C65: boolean | D65: ja | G65: ja; nee | I65: =COUNTA(procesfase_relatie!F$2:F$2000) -> 16 | J65: =IF(D65="ja",COUNTA(procesfase_relatie!$A$2:$A$2000)-I65,"") -> 0
A66: procesfase_relatie | B66: sort_order | C66: integer | D66: nee | I66: =COUNTA(procesfase_relatie!G$2:G$2000) -> 16 | J66: =IF(D66="ja",COUNTA(procesfase_relatie!$A$2:$A$2000)-I66,"")
A67: procesfase_relatie | B67: created_at | C67: datetime | D67: ja | H67: Datum en tijd van aanmaak | I67: =COUNTA(procesfase_relatie!H$2:H$2000) -> 16 | J67: =IF(D67="ja",COUNTA(procesfase_relatie!$A$2:$A$2000)-I67,"") -> 0
A68: procesfase_relatie | B68: created_by | C68: varchar(255) | D68: ja | H68: Maker | I68: =COUNTA(procesfase_relatie!I$2:I$2000) -> 16 | J68: =IF(D68="ja",COUNTA(procesfase_relatie!$A$2:$A$2000)-I68,"") -> 0
A69: procesfase_relatie | B69: updated_at | C69: datetime | D69: ja | H69: Laatste wijziging | I69: =COUNTA(procesfase_relatie!J$2:J$2000) -> 16 | J69: =IF(D69="ja",COUNTA(procesfase_relatie!$A$2:$A$2000)-I69,"") -> 0
A70: procesfase_relatie | B70: updated_by | C70: varchar(255) | D70: ja | H70: Laatste bewerker | I70: =COUNTA(procesfase_relatie!K$2:K$2000) -> 16 | J70: =IF(D70="ja",COUNTA(procesfase_relatie!$A$2:$A$2000)-I70,"") -> 0
A71: procesfase_relatie | B71: record_status | C71: varchar(30) | D71: ja | G71: actief; concept; gearchiveerd | H71: Actief, concept, gearchiveerd | I71: =COUNTA(procesfase_relatie!L$2:L$2000) -> 16 | J71: =IF(D71="ja",COUNTA(procesfase_relatie!$A$2:$A$2000)-I71,"") -> 0
A72: procesfase_relatie | B72: version_number | C72: integer | D72: ja | H72: Versienummer van record | I72: =COUNTA(procesfase_relatie!M$2:M$2000) -> 16 | J72: =IF(D72="ja",COUNTA(procesfase_relatie!$A$2:$A$2000)-I72,"") -> 0
A73: procesfase_relatie | B73: valid_from | C73: date | D73: nee | H73: Geldig vanaf | I73: =COUNTA(procesfase_relatie!N$2:N$2000) -> 0 | J73: =IF(D73="ja",COUNTA(procesfase_relatie!$A$2:$A$2000)-I73,"")
A74: procesfase_relatie | B74: valid_until | C74: date | D74: nee | H74: Geldig tot | I74: =COUNTA(procesfase_relatie!O$2:O$2000) -> 0 | J74: =IF(D74="ja",COUNTA(procesfase_relatie!$A$2:$A$2000)-I74,"")
A75: procesfase_relatie | B75: notes_internal | C75: text | D75: nee | H75: Interne beheerinformatie | I75: =COUNTA(procesfase_relatie!P$2:P$2000) -> 16 | J75: =IF(D75="ja",COUNTA(procesfase_relatie!$A$2:$A$2000)-I75,"")
A76: beslismoment | B76: beslismoment_id | C76: UUID | D76: ja | E76: PK | H76: Primaire sleutel | I76: =COUNTA(beslismoment!A$2:A$2000) -> 16 | J76: =IF(D76="ja",COUNTA(beslismoment!$A$2:$A$2000)-I76,"") -> 0
A77: beslismoment | B77: beslismoment_code | C77: varchar(30) | D77: ja | H77: Bijvoorbeeld BM-O4-01 | I77: =COUNTA(beslismoment!B$2:B$2000) -> 16 | J77: =IF(D77="ja",COUNTA(beslismoment!$A$2:$A$2000)-I77,"") -> 0
A78: beslismoment | B78: procesfase_id | C78: UUID, FK | D78: ja | E78: FK | F78: procesfase.fase_code | H78: Hoofdfase | I78: =COUNTA(beslismoment!C$2:C$2000) -> 16 | J78: =IF(D78="ja",COUNTA(beslismoment!$A$2:$A$2000)-I78,"") -> 0
A79: beslismoment | B79: naam | C79: varchar(200) | D79: ja | H79: Herkenbare naam | I79: =COUNTA(beslismoment!D$2:D$2000) -> 16 | J79: =IF(D79="ja",COUNTA(beslismoment!$A$2:$A$2000)-I79,"") -> 0
A80: beslismoment | B80: centrale_vraag | C80: text | D80: ja | H80: Vraag die moet worden beantwoord | I80: =COUNTA(beslismoment!E$2:E$2000) -> 16 | J80: =IF(D80="ja",COUNTA(beslismoment!$A$2:$A$2000)-I80,"") -> 0
A81: beslismoment | B81: omschrijving | C81: text | D81: nee | H81: Context | I81: =COUNTA(beslismoment!F$2:F$2000) -> 16 | J81: =IF(D81="ja",COUNTA(beslismoment!$A$2:$A$2000)-I81,"")
A82: beslismoment | B82: besluittype_id | C82: UUID, FK | D82: ja | E82: FK | F82: besluittype.code | H82: Type besluit | I82: =COUNTA(beslismoment!G$2:G$2000) -> 16 | J82: =IF(D82="ja",COUNTA(beslismoment!$A$2:$A$2000)-I82,"") -> 0
A83: beslismoment | B83: formaliteitsniveau | C83: varchar(30) | D83: ja | G83: informeel; ambtelijk; bestuurlijk; formeel | H83: Informeel, ambtelijk, bestuurlijk, formeel | I83: =COUNTA(beslismoment!H$2:H$2000) -> 16 | J83: =IF(D83="ja",COUNTA(beslismoment!$A$2:$A$2000)-I83,"") -> 0
A84: beslismoment | B84: voorbereidend_of_definitief | C84: varchar(30) | D84: ja | G84: voorbereidend; richtinggevend; definitief | H84: Voorbereidend, richtinggevend, definitief | I84: =COUNTA(beslismoment!I$2:I$2000) -> 16 | J84: =IF(D84="ja",COUNTA(beslismoment!$A$2:$A$2000)-I84,"") -> 0
A85: beslismoment | B85: verwacht_besluit | C85: text | D85: nee | H85: Wat wordt besloten? | I85: =COUNTA(beslismoment!J$2:J$2000) -> 16 | J85: =IF(D85="ja",COUNTA(beslismoment!$A$2:$A$2000)-I85,"")
A86: beslismoment | B86: benodigde_input_samenvatting | C86: text | D86: nee | H86: Globale informatiebehoefte | I86: =COUNTA(beslismoment!K$2:K$2000) -> 16 | J86: =IF(D86="ja",COUNTA(beslismoment!$A$2:$A$2000)-I86,"")
A87: beslismoment | B87: verwachte_output | C87: text | D87: nee | H87: Beslisnota, opdracht, krediet enzovoort | I87: =COUNTA(beslismoment!L$2:L$2000) -> 16 | J87: =IF(D87="ja",COUNTA(beslismoment!$A$2:$A$2000)-I87,"")
A88: beslismoment | B88: volgende_stap | C88: text | D88: nee | H88: Mogelijk vervolg | I88: =COUNTA(beslismoment!M$2:M$2000) -> 16 | J88: =IF(D88="ja",COUNTA(beslismoment!$A$2:$A$2000)-I88,"")
A89: beslismoment | B89: mandaat_lokaal_bepaald | C89: boolean | D89: ja | G89: ja; nee | H89: Lokale variatie | I89: =COUNTA(beslismoment!N$2:N$2000) -> 16 | J89: =IF(D89="ja",COUNTA(beslismoment!$A$2:$A$2000)-I89,"") -> 0
A90: beslismoment | B90: pc_moment_id | C90: UUID, FK | D90: nee | E90: FK | F90: pc_moment.code | H90: P&C- of kalendermoment | I90: =COUNTA(beslismoment!O$2:O$2000) -> 11 | J90: =IF(D90="ja",COUNTA(beslismoment!$A$2:$A$2000)-I90,"")
A91: beslismoment | B91: is_generic | C91: boolean | D91: ja | G91: ja; nee | H91: Generiek herkenbaar | I91: =COUNTA(beslismoment!P$2:P$2000) -> 16 | J91: =IF(D91="ja",COUNTA(beslismoment!$A$2:$A$2000)-I91,"") -> 0
A92: beslismoment | B92: is_work_hypothesis | C92: boolean | D92: ja | G92: ja; nee | H92: Nog te toetsen | I92: =COUNTA(beslismoment!Q$2:Q$2000) -> 16 | J92: =IF(D92="ja",COUNTA(beslismoment!$A$2:$A$2000)-I92,"") -> 0
A93: beslismoment | B93: validation_status_id | C93: UUID, FK | D93: ja | E93: FK | F93: validation_status.code | H93: Validatiestatus | I93: =COUNTA(beslismoment!R$2:R$2000) -> 16 | J93: =IF(D93="ja",COUNTA(beslismoment!$A$2:$A$2000)-I93,"") -> 0
A94: beslismoment | B94: created_at | C94: datetime | D94: ja | H94: Datum en tijd van aanmaak | I94: =COUNTA(beslismoment!S$2:S$2000) -> 16 | J94: =IF(D94="ja",COUNTA(beslismoment!$A$2:$A$2000)-I94,"") -> 0
A95: beslismoment | B95: created_by | C95: varchar(255) | D95: ja | H95: Maker | I95: =COUNTA(beslismoment!T$2:T$2000) -> 16 | J95: =IF(D95="ja",COUNTA(beslismoment!$A$2:$A$2000)-I95,"") -> 0
A96: beslismoment | B96: updated_at | C96: datetime | D96: ja | H96: Laatste wijziging | I96: =COUNTA(beslismoment!U$2:U$2000) -> 16 | J96: =IF(D96="ja",COUNTA(beslismoment!$A$2:$A$2000)-I96,"") -> 0
A97: beslismoment | B97: updated_by | C97: varchar(255) | D97: ja | H97: Laatste bewerker | I97: =COUNTA(beslismoment!V$2:V$2000) -> 16 | J97: =IF(D97="ja",COUNTA(beslismoment!$A$2:$A$2000)-I97,"") -> 0
A98: beslismoment | B98: record_status | C98: varchar(30) | D98: ja | G98: actief; concept; gearchiveerd | H98: Actief, concept, gearchiveerd | I98: =COUNTA(beslismoment!W$2:W$2000) -> 16 | J98: =IF(D98="ja",COUNTA(beslismoment!$A$2:$A$2000)-I98,"") -> 0
A99: beslismoment | B99: version_number | C99: integer | D99: ja | H99: Versienummer van record | I99: =COUNTA(beslismoment!X$2:X$2000) -> 16 | J99: =IF(D99="ja",COUNTA(beslismoment!$A$2:$A$2000)-I99,"") -> 0
A100: beslismoment | B100: valid_from | C100: date | D100: nee | H100: Geldig vanaf | I100: =COUNTA(beslismoment!Y$2:Y$2000) -> 0 | J100: =IF(D100="ja",COUNTA(beslismoment!$A$2:$A$2000)-I100,"")
A101: beslismoment | B101: valid_until | C101: date | D101: nee | H101: Geldig tot | I101: =COUNTA(beslismoment!Z$2:Z$2000) -> 0 | J101: =IF(D101="ja",COUNTA(beslismoment!$A$2:$A$2000)-I101,"")
...

Sheet Keuzelijsten
A1: Keuzelijsten
A2: Eén kolom per keuzeveld. Nieuwe waarde: onderaan de kolom toevoegen, dan klopt de dropdown direct.
A4: (alle tabellen).record_status | B4: opgave.niveau_default | C4: procesfase_relatie.relatietype | D4: beslismoment.formaliteitsniveau | E4: beslismoment.voorbereidend_of_definitief | F4: rol.informatie_detailniveau | G4: knelpunt.knelpunttype | H4: instrument.zelfstandig_bruikbaar | I4: instrument.complexiteitsniveau | J4: instrument.doorlooptijd_categorie | K4: instrument.relevantie_v1 | L4: instrument_organisatie.relatierol | M4: instrument_bron.bronrol | N4: instrument_rol.rol_bij_gebruik | O4: instrument_beslismoment.ondersteuningsfunctie | P4: instrument_financiele_vraag.antwoordniveau | Q4: instrument_eigenaartype.toepasbaarheid | R4: instrument_voorwaarde.operator | S4: werkingsgebied.gebiedstype | T4: openstelling.openstelling_status | U4: beslismoment_rol.betrokkenheidstype | V4: beslismoment_rol.raci_type | W4: beslismoment_beslisproduct.productrol | X4: kennisproduct.relatie_met_kompas | Y4: validatie.validatiemethode | Z4: kennisanalyse.analysetype | AA4: gebruikersfeedback.feedbacktype
A5: actief | B5: portefeuille | C5: volgt op | D5: informeel | E5: voorbereidend | F5: strategisch | G5: ontbrekende informatie | H5: ja | I5: basis | J5: direct | K5: hoog | L5: eigenaar | M5: officiële bron | N5: gebruiker | O5: informeren | P5: eerste oriëntatie | Q5: direct toepasbaar | R5: gelijk aan | S5: Europees | T5: open | U5: initieert | V5: R | W5: input | X5: inhoud opnemen | Y5: broncontrole | Z5: witte vlek | AA5: inhoud onjuist
A6: concept | B6: programma | C6: kan volgen op | D6: ambtelijk | E6: richtinggevend | F6: tactisch | G6: onduidelijke verantwoordelijkheid | H6: deels | I6: gemiddeld | J6: dagen | K6: middel | L6: beheerder | M6: gebruiksinstructie | N6: adviseur | O6: analyseren | P6: indicatief inzicht | Q6: mogelijk toepasbaar | R6: niet gelijk aan | S6: landelijk | T6: gesloten | U6: bereidt voor | V6: A | W6: onderbouwing | X6: naar verwijzen | Y6: deskundigenreview | Z6: beperkte dekking | AA6: informatie verouderd
A7: gearchiveerd | B7: object | C7: keert terug naar | D7: bestuurlijk | E7: definitief | F7: operationeel | G7: overdrachtsprobleem | H7: nee | I7: specialistisch | J7: weken | K7: laag | L7: uitvoerder | M7: onderbouwing | N7: beslisser | O7: rekenen | P7: volledige onderbouwing | Q7: alleen via samenwerking | R7: groter dan | S7: provincie | T7: verwacht | U7: levert input | V7: C | W7: besluitdocument | X7: onderlegger | Y7: interview | Z7: mogelijke doublure | AA7: instrument ontbreekt
B8: project | C8: leidt parallel tot | D8: formeel | G8: ontbrekend instrument | H8: onbekend | J8: maanden | L8: verstrekker | M8: praktijktoepassing | N8: leverancier van input | O8: vergelijken | P8: specialistische onderbouwing | Q8: alleen via andere juridische entiteit | R8: kleiner dan | S8: regio | T8: doorlopend | U8: adviseert | V8: I | W8: output | X8: mogelijke toekomstige koppeling | Y8: gebruikerssessie | Z8: inhoudelijke overlap | AA8: niet begrijpelijk
C9: activeert | G9: onvoldoende capaciteit | L9: ontwikkelaar | M9: validatie | N9: toetser | O9: prioriteren | P9: verwijzing naar expertise | Q9: niet toepasbaar | R9: minimaal | S9: gemeente | T9: uitgeput | U9: toetst | W9: overdrachtsproduct | X9: buiten scope | Y9: casusvalidatie | Z9: regionale versnippering | AA9: route niet herkenbaar
C10: herijkt | G10: kennisprobleem | L10: inhoudelijk verantwoordelijke | M10: actualiteitscontrole | N10: beheerder | O10: toetsen | Q10: nog te controleren | R10: maximaal | S10: lokaal fonds | T10: beëindigd | U10: besluit | W10: monitoring | Y10: kernteam | Z10: sectorspecifieke variatie | AA10: onvoldoende handelingsperspectief
G11: lokaal procesverschil | L11: actualisatieverantwoordelijke | M11: achtergrondinformatie | N11: ontvanger van output | O11: financieren | R11: bevat | T11: onbekend | U11: voert uit | Y11: redactionele controle | Z11: verouderde informatie | AA11: koppeling onjuist
G12: mandaatprobleem | L12: kennispartner | O12: bekostigen | R12: geldt voor | U12: monitort | Y12: technische controle | Z12: onduidelijke bronhouder | AA12: positief praktijkvoorbeeld
G13: timing P&C-cyclus | L13: distributeur | O13: onderbouwen | R13: geldt niet voor | U13: wordt geïnformeerd | Z13: ontbrekend handelingsperspectief | AA13: verbetersuggestie
G14: onvoldoende dekking | O14: besluiten voorbereiden | R14: vereist | Z14: ontbrekende bestuurlijke vertaling
G15: fiscale of juridische onzekerheid | O15: contracteren | R15: optioneel | Z15: ontbrekende praktische toepassing
O16: monitoren
O17: verantwoorden
O18: herijken

Sheet Afwijkingen
A1: Afwijkingen en gaten in de modelbeschrijving
A2: Gaten in de modelbeschrijving, gemeld en niet opgelost; ongewijzigd t.o.v. de lege werkmap. Kolom 'Verwerking' verwijst naar de lege versie.
A4: Nr | B4: Onderwerp | C4: Bevinding | D4: Verwerking in deze werkmap | E4: Beslissing nodig van
A5: 1 | B5: opgave_beslismoment ontbreekt | C5: Het ER-model (§17) noemt de koppeltabel OPGAVE_BESLISMOMENT, maar die is nergens uitgewerkt. Een opgave is daardoor alleen aan instrument (instrument_opgave) en gebruikersfeedback gekoppeld, niet aan procesniveau, fase of beslismoment. De hoofdrelatie uit §2 (opgave -> procesniveau -> ... -> beslismoment) is zo niet af te leiden. | D5: Niet opgenomen. | E5: Kernteam
A6: 2 | B6: Hoofdrelatie §2 niet volledig gedekt | C6: De keten informatiebehoefte -> financiële vraag -> handelingsperspectief -> instrument heeft geen eigen relaties. Deze vier hangen elk alleen aan beslismoment (en deels aan rol). Welk instrument bij welk handelingsperspectief hoort, is niet vast te leggen. | D6: Geen extra koppeltabellen toegevoegd. | E6: Kernteam
A7: 3 | B7: procesniveau - beslismoment | C7: §17 toont PROCESNIVEAU 1-n BESLISMOMENT, maar beslismoment heeft alleen procesfase_id. Het niveau is alleen via de fase af te leiden. | D7: Tabel conform §4.5. | E7: Datamodelleur
A8: 4 | B8: Fasen alleen voor twee van vier niveaus | C8: procesniveau kent vier records (PORT, PROG, OBJ, PROJ), de voorgestelde fasen zijn alleen 'portefeuillefasen' (P) en 'objectfasen' (O). PROG en PROJ hebben geen fasen. | D8: P-fasen gekoppeld aan PORT, O-fasen aan OBJ. | E8: Kernteam (beslispunt 1 en 2)
A9: 5 | B9: Verplichte instrumentvelden §19 zonder plek | C9: §19 verplicht per instrument 'Primair procesniveau' en 'Benodigde expertise'. Het model kent geen relatie instrument-procesniveau en geen veld voor benodigde expertise (alleen als voorwaardetype 'vereiste expertise'). 'Laatste controledatum' bestaat alleen in openstelling en reviewplanning. | D9: Geen velden toegevoegd. | E9: Datamodelleur
A10: 6 | B10: Fasering §18 dekt niet alle tabellen | C10: §18 deelt 42 tabellen in; 23 uitgewerkte tabellen staan in geen enkele fase: procesfase_relatie, besluittype, rolcluster, functie_alias, informatietype, knelpunt, digitale_vorm, organisatietype, instrument_organisatie, brontype, instrument_opgave, financiele_route, instrument_financiele_route, instrument_werkingsgebied, pc_moment, beslismoment_knelpunt, instrument_relatietype, kennisproduct, kennisproduct_instrument, kennisproduct_beslismoment, publicatiestatus, inhoudelijke_status, ontwikkelactie. Daaronder keuzelijsttabellen waar verplichte velden uit fase 1 naar verwijzen (besluittype, rolcluster, organisatietype, brontype, publicatiestatus, inhoudelijke_status). | D10: Alle tabellen opgenomen; in kolom Fase gemarkeerd als 'niet ingedeeld'. | E10: Kernteam
A11: 7 | B11: Fase 1 versus verplichte velden §19 | C11: §19 verplicht bronhouder en werkingsgebied in versie 1.0, maar instrument_organisatie en instrument_werkingsgebied zijn niet ingedeeld en werkingsgebied staat in fase 3. | D11: Tabellen opgenomen en gevuld vanuit de catalogus. | E11: Kernteam
A12: 8 | B12: Tabellen zonder veldbeschrijving | C12: organisatietype, brontype, instrument_relatietype, publicatiestatus en inhoudelijke_status hebben in de tekst alleen waarden, geen velden. | D12: Aanname: sleutel, code, naam, omschrijving, sort_order plus beheervelden, naar het patroon van de andere keuzelijsttabellen. Dit is de enige structurele aanvulling. | E12: Datamodelleur
A13: 9 | B13: Keuzevelden zonder waardenlijst | C13: Voor 42 velden met een beperkte waardenset geeft de tekst geen waarden, waaronder alle velden relevantie, prioriteit, impact, status en entity_type. Zie kolom Keuzelijst op tabblad Velden. | D13: Geen dropdown; vrij invulbaar. Bij de migratie zijn deze velden leeg gelaten. | E13: Kernteam
A14: 10 | B14: Toepasbaarheid bij objecttype | C14: De waarden voor toepasbaarheid staan alleen onder §7.6 (eigenaartype). §7.7 (objecttype) heeft hetzelfde veld zonder lijst. | D14: Aanname: dezelfde lijst gebruikt. | E14: Datamodelleur
A15: 11 | B15: Verwijzingen via entity_type/entity_id | C15: validatie, wijzigingslog, reviewplanning en gebruikersfeedback verwijzen naar 'een' record via entity_type en entity_id. Een database kan dat niet als verwijzing afdwingen, en de toegestane waarden voor entity_type zijn niet gegeven. | D15: Conform tekst; geen dropdown. | E15: Datamodelleur
A16: 12 | B16: Naamgeving sleutels | C16: Niet alle sleutels volgen het patroon tabelnaam_id: beslismoment_informatiebehoefte heeft beslismoment_informatie_id, gebruikersfeedback heeft feedback_id, instrument_relatie verwijst met relatietype_id naar instrument_relatietype. validation_status is Engels, de rest Nederlands. | D16: Namen letterlijk overgenomen. | E16: Datamodelleur
... A24: 20 | B24: Catalogus v0.1: rollen | C24: De catalogus kent zeven rollen, waarvan twee eigenaartypen zijn en twee samengesteld (Vastgoedexpert/PM, Financieel medewerker/controller). Alleen 'Wethouder' past eenduidig; 8 rolkoppelingen zijn overgenomen, 129 niet. | D24: Zie Migratie_rest. | E24: Kernteam (beslispunt 4)

Sheet opgave
A1: opgave_id | B1: opgave_code | C1: naam | D1: korte_omschrijving | E1: uitgebreide_omschrijving | F1: aanleiding | G1: gewenst_resultaat | H1: niveau_default | I1: primaire_doelgroep | J1: sort_order | K1: is_public | L1: created_at | M1: created_by | N1: updated_at | O1: updated_by | P1: record_status | Q1: version_number | R1: valid_from | S1: valid_until | T1: notes_internal
A2: edb80e5b-7c99-518b-b3a3-759d248a8884 | B2: OPG-001 | C2: verduurzamingsopgave bepalen | D2: Bepaal hoe groot de verduurzamingsopgave van het vastgoed is | G2: Dummy: een onderbouwd antwoord op: verduurzamingsopgave bepalen. | H2: portefeuille | J2: 1 | K2: ja | L2: 2026-10-02 | M2: startwaardelijst datamodel | N2: 2026-10-02 | O2: startwaardelijst datamodel | P2: concept | Q2: 1 | T2: DUMMY-aanvulling: gewenst_resultaat, is_public, korte_omschrijving, niveau_default
A3: b81ebeab-5b54-59b4-891d-f4025c6913d0 | B3: OPG-002 | C3: portefeuille prioriteren | D3: Rangschik de objecten en kies wat eerst komt | G3: Dummy: een onderbouwd antwoord op: portefeuille prioriteren. | H3: portefeuille | J3: 2 | K3: ja | L3: 2026-10-02 | M3: startwaardelijst datamodel | N3: 2026-10-02 | O3: startwaardelijst datamodel | P3: concept | Q3: 1 | T3: DUMMY-aanvulling: gewenst_resultaat, is_public, korte_omschrijving, niveau_default
A4: d905a0f8-2cd6-5974-98fb-476e0c50784d | B4: OPG-003 | C4: uitvoeringsprogramma opstellen | D4: Maak een uitvoeringsprogramma binnen het budget | G4: Dummy: een onderbouwd antwoord op: uitvoeringsprogramma opstellen. | H4: programma | J4: 3 | K4: ja | L4: 2026-10-02 | M4: startwaardelijst datamodel | N4: 2026-10-02 | O4: startwaardelijst datamodel | P4: concept | Q4: 1 | T4: DUMMY-aanvulling: gewenst_resultaat, is_public, korte_omschrijving, niveau_default
A5: fd32baca-8921-552c-ad52-bb3e45699f95 | B5: OPG-004 | C5: object verduurzamen | D5: Pak een gebouw aan en verduurzaam het | G5: Dummy: een onderbouwd antwoord op: object verduurzamen. | H5: object | J5: 4 | K5: ja | L5: 2026-10-02 | M5: startwaardelijst datamodel | N5: 2026-10-02 | O5: startwaardelijst datamodel | P5: concept | Q5: 1 | T5: DUMMY-aanvulling: gewenst_resultaat, is_public, korte_omschrijving, niveau_default
A6: 42faaa98-a334-5a17-a076-7e4adb9060ad | B6: OPG-005 | C6: accommodatie vernieuwen | D6: Vernieuw een accommodatie | G6: Dummy: een onderbouwd antwoord op: accommodatie vernieuwen. | H6: object | J6: 5 | K6: ja | L6: 2026-10-02 | M6: startwaardelijst datamodel | N6: 2026-10-02 | O6: startwaardelijst datamodel | P6: concept | Q6: 1 | T6: DUMMY-aanvulling: gewenst_resultaat, is_public, korte_omschrijving, niveau_default
A7: 81f58067-24f9-57d4-9965-81cd84523e78 | B7: OPG-006 | C7: investering voorbereiden | D7: Bereid een investering voor | G7: Dummy: een onderbouwd antwoord op: investering voorbereiden. | H7: object | J7: 6 | K7: ja | L7: 2026-10-02 | M7: startwaardelijst datamodel | N7: 2026-10-02 | O7: startwaardelijst datamodel | P7: concept | Q7: 1 | T7: DUMMY-aanvulling: gewenst_resultaat, is_public, korte_omschrijving, niveau_default
A8: cfd5d161-bf93-5067-94e8-3f68474da126 | B8: OPG-007 | C8: financiering of dekking organiseren | D8: Organiseer financiering of dekking | G8: Dummy: een onderbouwd antwoord op: financiering of dekking organiseren. | H8: object | J8: 7 | K8: ja | L8: 2026-10-02 | M8: startwaardelijst datamodel | N8: 2026-10-02 | O8: startwaardelijst datamodel | P8: concept | Q8: 1 | T8: DUMMY-aanvulling: gewenst_resultaat, is_public, korte_omschrijving, niveau_default
A9: 4ebb3bc7-232d-5a64-bb0d-54fd09a52ee4 | B9: OPG-008 | C9: exploitatie verbeteren | D9: Verbeter de exploitatie van een gebouw | G9: Dummy: een onderbouwd antwoord op: exploitatie verbeteren. | H9: object | J9: 8 | K9: ja | L9: 2026-10-02 | M9: startwaardelijst datamodel | N9: 2026-10-02 | O9: startwaardelijst datamodel | P9: concept | Q9: 1 | T9: DUMMY-aanvulling: gewenst_resultaat, is_public, korte_omschrijving, niveau_default
A10: d7f5569c-48f8-5414-a819-7c1bce611e56 | B10: OPG-009 | C10: prestaties monitoren | D10: Volg de prestaties van het vastgoed | G10: Dummy: een onderbouwd antwoord op: prestaties monitoren. | H10: portefeuille | J10: 9 | K10: ja | L10: 2026-10-02 | M10: startwaardelijst datamodel | N10: 2026-10-02 | O10: startwaardelijst datamodel | P10: concept | Q10: 1 | T10: DUMMY-aanvulling: gewenst_resultaat, is_public, korte_omschrijving, niveau_default
A11: 7a0bcf2c-029c-5f0b-af97-854948b9e324 | B11: OPG-010 | C11: strategie herijken | D11: Herijk de vastgoedstrategie | G11: Dummy: een onderbouwd antwoord op: strategie herijken. | H11: portefeuille | J11: 10 | K11: ja | L11: 2026-10-02 | M11: startwaardelijst datamodel | N11: 2026-10-02 | O11: startwaardelijst datamodel | P11: concept | Q11: 1 | T11: DUMMY-aanvulling: gewenst_resultaat, is_public, korte_omschrijving, niveau_default

Sheet procesniveau
A1: procesniveau_id | B1: code | C1: naam | D1: omschrijving | E1: sort_order | F1: created_at | G1: created_by | H1: updated_at | I1: updated_by | J1: record_status | K1: version_number | L1: valid_from | M1: valid_until | N1: notes_internal
A2: 6e830033-beab-52ff-af50-47b90185a425 | B2: PORT | C2: Portefeuille | D2: Alle objecten van de organisatie samen: strategie, prioritering en meerjarig budget. | E2: 1 | F2: 2026-10-02 | G2: startwaardelijst datamodel | H2: 2026-10-02 | I2: startwaardelijst datamodel | J2: concept | K2: 1 | N2: DUMMY-aanvulling: omschrijving
A3: ce6ba184-fd57-5f93-966f-25855310460f | B3: PROG | C3: Programma | D3: Een samenhangende set projecten met gezamenlijke doelen, planning en budget. | E3: 2 | F3: 2026-10-02 | G3: startwaardelijst datamodel | H3: 2026-10-02 | I3: startwaardelijst datamodel | J3: concept | K3: 1 | N3: DUMMY-aanvulling: omschrijving
A4: a271a421-b3e3-5ea3-9e2b-b3caaeffe7c9 | B4: OBJ | C4: Object | D4: Eén gebouw of accommodatie, van initiatief tot exploitatie. | E4: 3 | F4: 2026-10-02 | G4: startwaardelijst datamodel | H4: 2026-10-02 | I4: startwaardelijst datamodel | J4: concept | K4: 1 | N4: DUMMY-aanvulling: omschrijving
A5: d62e9efa-e217-50c8-9844-9454ec7dc140 | B5: PROJ | C5: Project | D5: Een afgebakende ingreep aan een object, zoals een verduurzamingsproject. | E5: 4 | F5: 2026-10-02 | G5: startwaardelijst datamodel | H5: 2026-10-02 | I5: startwaardelijst datamodel | J5: concept | K5: 1 | N5: DUMMY-aanvulling: omschrijving

Sheet procesfase
A1: procesfase_id | B1: procesniveau_id | C1: fase_code | D1: naam | E1: centrale_vraag | F1: omschrijving | G1: startcriterium | H1: eindcriterium | I1: standaard_resultaat | J1: sort_order | K1: is_work_hypothesis | L1: validation_status_id | M1: created_at | N1: created_by | O1: updated_at | P1: updated_by | Q1: record_status | R1: version_number | S1: valid_from | T1: valid_until | U1: notes_internal
A2: 1f3bb4ac-0700-56fc-bb41-1902287c72e8 | B2: PORT | C2: P1 | D2: Richting en kaders | E2: Welke ambitie en financiële kaders gelden voor ons vastgoed? | F2: Bestuurlijke richting en kaders voor het vastgoedbeleid. | G2: Aanleiding: nieuw college of nieuwe opgave. | H2: Kaders zijn vastgesteld. | I2: Vastgestelde ambitie en kaders | J2: 1 | K2: ja | L2: VS-02 | M2: 2026-10-02 | N2: startwaardelijst datamodel | O2: 2026-10-02 | P2: startwaardelijst datamodel | Q2: concept | R2: 1 | U2: DUMMY-aanvulling: centrale_vraag, eindcriterium, omschrijving, standaard_resultaat, startcriterium, validation_status_id
A3: 0730b6b8-6f18-59d6-a261-68951875f3d4 | B3: PORT | C3: P2 | D3: Inzicht en analyse | E3: Wat is de stand van de portefeuille en wat kost niets doen? | F3: Inzicht in staat, kosten en prestaties van alle objecten. | G3: Kaders zijn vastgesteld. | H3: Nulmeting is geaccordeerd. | I3: Portefeuilleanalyse met nulmeting | J3: 2 | K3: ja | L3: VS-02 | M3: 2026-10-02 | N3: startwaardelijst datamodel | O3: 2026-10-02 | P3: startwaardelijst datamodel | Q3: concept | R3: 1 | U3: DUMMY-aanvulling: centrale_vraag, eindcriterium, omschrijving, standaard_resultaat, startcriterium, validation_status_id
A4: c3370122-9e82-51c0-ae4a-56dff990586c | B4: PORT | C4: P3 | D4: Portefeuillestrategie en programmering | E4: Welke prioriteiten en welk programma passen binnen de middelen? | F4: Prioriteren van objecten en programmeren in de tijd binnen het budget. | G4: Nulmeting is geaccordeerd. | H4: Programma met dekking is vastgesteld. | I4: Prioriteitenlijst en meerjarenprogramma | J4: 3 | K4: ja | L4: VS-02 | M4: 2026-10-02 | N4: startwaardelijst datamodel | O4: 2026-10-02 | P4: startwaardelijst datamodel | Q4: concept | R4: 1 | U4: DUMMY-aanvulling: centrale_vraag, eindcriterium, omschrijving, standaard_resultaat, startcriterium, validation_status_id
A5: b3319dde-7f4a-5fa3-8bbc-1b150950feaf | B5: PORT | C5: P4 | D5: Uitvoering portefeuille | E5: Hoe wordt het programma uitgevoerd en gefinancierd? | F5: Uitvoering van de jaarschijven en inzet van financiering. | G5: Programma is vastgesteld. | H5: Jaarschijf is afgerond. | I5: Uitgevoerde jaarschijf | J5: 4 | K5: ja | L5: VS-02 | M5: 2026-10-02 | N5: startwaardelijst datamodel | O5: 2026-10-02 | P5: startwaardelijst datamodel | Q5: concept | R5: 1 | U5: DUMMY-aanvulling: centrale_vraag, eindcriterium, omschrijving, standaard_resultaat, startcriterium, validation_status_id
A6: 039fc579-3c78-5be0-8918-16e085a42591 | B6: PORT | C6: P5 | D6: Monitoren en herijken | E6: Halen we de doelen en moet de strategie worden herijkt? | F6: Volgen van voortgang en prestaties, bijsturen en herijken. | G6: Eerste jaarschijf is afgerond. | H6: Herijking is vastgesteld. | I6: Monitoringsrapportage en herijkingsvoorstel | J6: 5 | K6: ja | L6: VS-02 | M6: 2026-10-02 | N6: startwaardelijst datamodel | O6: 2026-10-02 | P6: startwaardelijst datamodel | Q6: concept | R6: 1 | U6: DUMMY-aanvulling: centrale_vraag, eindcriterium, omschrijving, standaard_resultaat, startcriterium, validation_status_id
A7: c9cee471-85c8-5e09-bea3-9d8bfdf23178 | B7: OBJ | C7: O1 | D7: Trigger en initiatief | E7: Is er aanleiding om dit object aan te pakken? | F7: Trigger en initiatief voor een object. | G7: Er is een aanleiding of opdracht. | H7: Projectopdracht verkenning is verstrekt. | I7: Projectopdracht verkenning | J7: 1 | K7: ja | L7: VS-02 | M7: 2026-10-02 | N7: startwaardelijst datamodel | O7: 2026-10-02 | P7: startwaardelijst datamodel | Q7: concept | R7: 1 | U7: DUMMY-aanvulling: centrale_vraag, eindcriterium, omschrijving, standaard_resultaat, startcriterium, validation_status_id
A8: 90e47428-c6bb-5ee9-aee2-433b0d46f925 | B8: OBJ | C8: O2 | D8: Verkenning en haalbaarheid | E8: Is het haalbaar en welke varianten zijn er? | F8: Verkenning van varianten en haalbaarheid. | G8: Projectopdracht is verstrekt. | H8: Varianten zijn beoordeeld. | I8: Scenariovergelijking | J8: 2 | K8: ja | L8: VS-02 | M8: 2026-10-02 | N8: startwaardelijst datamodel | O8: 2026-10-02 | P8: startwaardelijst datamodel | Q8: concept | R8: 1 | U8: DUMMY-aanvulling: centrale_vraag, eindcriterium, omschrijving, standaard_resultaat, startcriterium, validation_status_id
A9: bd67a801-9c90-510a-bf78-31663f607f42 | B9: OBJ | C9: O3 | D9: Definitie en voorkeurskeuze | E9: Welke variant heeft de voorkeur en wat is het budget? | F9: Definitie van het project en keuze van de voorkeursvariant. | G9: Varianten zijn beoordeeld. | H9: Voorkeursbesluit is genomen. | I9: Voorkeursbesluit en budget | J9: 3 | K9: ja | L9: VS-02 | M9: 2026-10-02 | N9: startwaardelijst datamodel | O9: 2026-10-02 | P9: startwaardelijst datamodel | Q9: concept | R9: 1 | U9: DUMMY-aanvulling: centrale_vraag, eindcriterium, omschrijving, standaard_resultaat, startcriterium, validation_status_id
A10: 83dfd909-b86c-5b6b-9aca-48c3ddcc5de2 | B10: OBJ | C10: O4 | D10: Ontwerp en investeringsbesluit | E10: Is de investering onderbouwd en gedekt zodat het besluit genomen kan worden? | F10: Ontwerp, financiële onderbouwing en investeringsbesluit. | G10: Voorkeursbesluit is genomen. | H10: Krediet is beschikbaar gesteld. | I10: Investeringsvoorstel en krediet | J10: 4 | K10: ja | L10: VS-02 | M10: 2026-10-02 | N10: startwaardelijst datamodel | O10: 2026-10-02 | P10: startwaardelijst datamodel | Q10: concept | R10: 1 | U10: DUMMY-aanvulling: centrale_vraag, eindcriterium, omschrijving, standaard_resultaat, startcriterium, validation_status_id
A11: dc6aaf7b-7621-52eb-a006-e152df1bde2b | B11: OBJ | C11: O5 | D11: Contractering en realisatie | E11: Hoe wordt gecontracteerd en wat kost de realisatie? | F11: Aanbesteding, contractering en realisatie. | G11: Krediet is beschikbaar gesteld. | H11: Project is gerealiseerd. | I11: Contract en gerealiseerd project | J11: 5 | K11: ja | L11: VS-02 | M11: 2026-10-02 | N11: startwaardelijst datamodel | O11: 2026-10-02 | P11: startwaardelijst datamodel | Q11: concept | R11: 1 | U11: DUMMY-aanvulling: centrale_vraag, eindcriterium, omschrijving, standaard_resultaat, startcriterium, validation_status_id
A12: 7dcb0b2f-1cf3-5032-a045-ec438705e570 | B12: OBJ | C12: O6 | D12: Oplevering en ingebruikname | E12: Is het opgeleverd conform afspraken en wat zijn de beheerkosten? | F12: Oplevering, acceptatie en ingebruikname. | G12: Realisatie is gereed. | H12: Object is in gebruik genomen. | I12: Opleverdossier | J12: 6 | K12: ja | L12: VS-02 | M12: 2026-10-02 | N12: startwaardelijst datamodel | O12: 2026-10-02 | P12: startwaardelijst datamodel | Q12: concept | R12: 1 | U12: DUMMY-aanvulling: centrale_vraag, eindcriterium, omschrijving, standaard_resultaat, startcriterium, validation_status_id
A13: 27a18e93-6a34-5e33-aed2-bb296bc9fec5 | B13: OBJ | C13: O7 | D13: Exploitatie, beheer en evaluatie | E13: Presteert het object zoals bedoeld en wat leren we? | F13: Exploitatie, beheer en evaluatie. | G13: Object is in gebruik. | H13: Evaluatie is afgerond. | I13: Evaluatie en prestatiegegevens | J13: 7 | K13: ja | L13: VS-02 | M13: 2026-10-02 | N13: startwaardelijst datamodel | O13: 2026-10-02 | P13: startwaardelijst datamodel | Q13: concept | R13: 1 | U13: DUMMY-aanvulling: centrale_vraag, eindcriterium, omschrijving, standaard_resultaat, startcriterium, validation_status_id

Sheet procesfase_relatie
A1: procesfase_relatie_id | B1: van_procesfase_id | C1: naar_procesfase_id | D1: relatietype | E1: voorwaarde | F1: is_default_route | G1: sort_order | H1: created_at | I1: created_by | J1: updated_at | K1: updated_by | L1: record_status | M1: version_number | N1: valid_from | O1: valid_until | P1: notes_internal
A2: 1371438d-0004-5bb2-88bd-72c29e14a8b1 | B2: P1 | C2: P2 | D2: volgt op | F2: ja | G2: 1 | H2: 2026-10-03 | I2: dummy-generator | J2: 2026-10-03 | K2: dummy-generator | L2: concept | M2: 1 | P2: DUMMY
A3: 8a4852a9-eb1b-5c87-b731-840b39a01862 | B3: P2 | C3: P3 | D3: volgt op | F3: ja | G3: 2 | H3: 2026-10-03 | I3: dummy-generator | J3: 2026-10-03 | K3: dummy-generator | L3: concept | M3: 1 | P3: DUMMY
A4: c93db876-841c-5932-b776-d876505b91f4 | B4: P3 | C4: P4 | D4: volgt op | F4: ja | G4: 3 | H4: 2026-10-03 | I4: dummy-generator | J4: 2026-10-03 | K4: dummy-generator | L4: concept | M4: 1 | P4: DUMMY
A5: fd68bec1-107d-532d-91a4-d34285923952 | B5: P4 | C5: P5 | D5: volgt op | F5: ja | G5: 4 | H5: 2026-10-03 | I5: dummy-generator | J5: 2026-10-03 | K5: dummy-generator | L5: concept | M5: 1 | P5: DUMMY
A6: 6d18511e-9738-50d8-a4cd-b276d4cde4ca | B6: P5 | C6: P3 | D6: herijkt | F6: nee | G6: 5 | H6: 2026-10-03 | I6: dummy-generator | J6: 2026-10-03 | K6: dummy-generator | L6: concept | M6: 1 | P6: DUMMY
A7: 1bdb4df5-f8bf-5152-bc21-b4b64d2bf214 | B7: P5 | C7: P1 | D7: keert terug naar | F7: nee | G7: 6 | H7: 2026-10-03 | I7: dummy-generator | J7: 2026-10-03 | K7: dummy-generator | L7: concept | M7: 1 | P7: DUMMY
A8: 367da0c6-c5cc-51fa-acf9-3b0f468989a7 | B8: P3 | C8: O1 | D8: activeert | E8: Dummy: alleen als het object in het programma is opgenomen | F8: nee | G8: 7 | H8: 2026-10-03 | I8: dummy-generator | J8: 2026-10-03 | K8: dummy-generator | L8: concept | M8: 1 | P8: DUMMY
A9: ce89a7d5-4eae-5724-a3e8-713cf90d1a0d | B9: P4 | C9: O1 | D9: activeert | E9: Dummy: alleen als het object in het programma is opgenomen | F9: nee | G9: 8 | H9: 2026-10-03 | I9: dummy-generator | J9: 2026-10-03 | K9: dummy-generator | L9: concept | M9: 1 | P9: DUMMY
A10: b0c806bd-8eda-5eeb-9b6b-462d6e477634 | B10: O1 | C10: O2 | D10: volgt op | F10: ja | G10: 9 | H10: 2026-10-03 | I10: dummy-generator | J10: 2026-10-03 | K10: dummy-generator | L10: concept | M10: 1 | P10: DUMMY
A11: 65268cea-3ce2-5fd5-a598-0fc7d92127d0 | B11: O2 | C11: O3 | D11: volgt op | F11: ja | G11: 10 | H11: 2026-10-03 | I11: dummy-generator | J11: 2026-10-03 | K11: dummy-generator | L11: concept | M11: 1 | P11: DUMMY
A12: c73360a4-fb18-5b27-b228-1092ffdcfdea | B12: O3 | C12: O4 | D12: volgt op | F12: ja | G12: 11 | H12: 2026-10-03 | I12: dummy-generator | J12: 2026-10-03 | K12: dummy-generator | L12: concept | M12: 1 | P12: DUMMY
A13: b18d1a4e-2645-568c-8cb7-3758831044dc | B13: O4 | C13: O5 | D13: volgt op | F13: ja | G13: 12 | H13: 2026-10-03 | I13: dummy-generator | J13: 2026-10-03 | K13: dummy-generator | L13: concept | M13: 1 | P13: DUMMY
A14: a9458a2e-2bff-56fb-8dc3-66813d99f978 | B14: O5 | C14: O6 | D14: volgt op | F14: ja | G14: 13 | H14: 2026-10-03 | I14: dummy-generator | J14: 2026-10-03 | K14: dummy-generator | L14: concept | M14: 1 | P14: DUMMY
A15: bcc79bbd-962d-5e59-9fdc-9eb1e688de4c | B15: O6 | C15: O7 | D15: volgt op | F15: ja | G15: 14 | H15: 2026-10-03 | I15: dummy-generator | J15: 2026-10-03 | K15: dummy-generator | L15: concept | M15: 1 | P15: DUMMY
A16: 6c942830-bfc9-528a-a079-4b507daed2c7 | B16: O4 | C16: O3 | D16: keert terug naar | F16: nee | G16: 15 | H16: 2026-10-03 | I16: dummy-generator | J16: 2026-10-03 | K16: dummy-generator | L16: concept | M16: 1 | P16: DUMMY
A17: e733d728-fc1b-58b5-90a5-a1744ccbea5c | B17: O7 | C17: P5 | D17: leidt parallel tot | F17: nee | G17: 16 | H17: 2026-10-03 | I17: dummy-generator | J17: 2026-10-03 | K17: dummy-generator | L17: concept | M17: 1 | P17: DUMMY

Sheet beslismoment
A1: beslismoment_id | B1: beslismoment_code | C1: procesfase_id | D1: naam | E1: centrale_vraag | F1: omschrijving | G1: besluittype_id | H1: formaliteitsniveau | I1: voorbereidend_of_definitief | J1: verwacht_besluit | K1: benodigde_input_samenvatting | L1: verwachte_output | M1: volgende_stap | N1: mandaat_lokaal_bepaald | O1: pc_moment_id | P1: is_generic | Q1: is_work_hypothesis | R1: validation_status_id | S1: created_at | T1: created_by | U1: updated_at | V1: updated_by | W1: record_status | X1: version_number | Y1: valid_from | Z1: valid_until | AA1: notes_internal
A2: 6156f938-eb57-5d0a-aca9-92688e9bcaab | B2: BM-P1-01 | C2: P1 | D2: Ambitie en financiële kaders vaststellen | E2: Welke ambitie en financiële kaders gelden voor ons vastgoed? | F2: Dummy: vaststellen van ambitie en kaders. | G2: BT-03 | H2: bestuurlijk | I2: richtinggevend | J2: Vaststellen van ambitie en kaders | K2: Beleidskaders, ambities, financiële ruimte | L2: Raadsvoorstel kaders vastgoed | M2: Inzicht en analyse opstarten | N2: ja | O2: PC-01 | P2: ja | Q2: ja | R2: VS-02 | S2: 2026-10-03 | T2: dummy-generator | U2: 2026-10-03 | V2: dummy-generator | W2: concept | X2: 1 | AA2: DUMMY
A3: 98f00286-5111-5f2a-9044-b3254bc5b88d | B3: BM-P2-01 | C3: P2 | D3: Opgave en nulmeting accorderen | E3: Wat is de stand van de portefeuille en wat kost niets doen? | F3: Dummy: accorderen van de nulmeting. | G3: BT-01 | H3: ambtelijk | I3: voorbereidend | J3: Accorderen van de nulmeting | K3: Portefeuilledata, onderhoudsstaat, energielabels | L3: Portefeuilleanalyse met nulmeting | M3: Prioriteiten stellen | N3: nee | O3: PC-10 | P3: ja | Q3: ja | R3: VS-02 | S3: 2026-10-03 | T3: dummy-generator | U3: 2026-10-03 | V3: dummy-generator | W3: concept | X3: 1 | AA3: DUMMY
A4: e82f7080-2cfc-5f28-9944-8f427118fd8d | B4: BM-P3-01 | C4: P3 | D4: Prioriteiten stellen | E4: Welke objecten pakken we eerst aan en op basis waarvan? | F4: Dummy: vaststellen van de prioriteitenlijst. | G4: BT-04 | H4: ambtelijk | I4: richtinggevend | J4: Vaststellen van de prioriteitenlijst | K4: Nulmeting, afwegingscriteria, maatschappelijke waarde | L4: Prioriteitenlijst | M4: Meerjarenprogramma opstellen | N4: nee | O4: PC-10 | P4: ja | Q4: ja | R4: VS-02 | S4: 2026-10-03 | T4: dummy-generator | U4: 2026-10-03 | V4: dummy-generator | W4: concept | X4: 1 | AA4: DUMMY
A5: 51475306-097e-5cb8-bef7-0519fbd30abd | B5: BM-P3-02 | C5: P3 | D5: Meerjarenprogramma en dekking vaststellen | E5: Welk programma past binnen de beschikbare middelen en hoe is het gedekt? | F5: Dummy: vaststellen van programma en dekking. | G5: BT-05 | H5: bestuurlijk | I5: definitief | J5: Vaststellen van programma en dekking | K5: Begrotingsruimte, boekwaarde, ramingen | L5: Collegevoorstel programma | M5: Jaarschijf vrijgeven | N5: ja | O5: PC-02 | P5: ja | Q5: ja | R5: VS-02 | S5: 2026-10-03 | T5: dummy-generator | U5: 2026-10-03 | V5: dummy-generator | W5: concept | X5: 1 | AA5: DUMMY
A6: cafef713-5fb3-5519-a769-8b45ceedf668 | B6: BM-P4-01 | C6: P4 | D6: Jaarschijf en uitvoeringsbudget vrijgeven | E6: Welk budget geven we dit jaar vrij en hoe financieren we het? | F6: Dummy: vrijgeven van jaarschijf. | G6: BT-08 | H6: bestuurlijk | I6: definitief | J6: Vrijgeven van jaarschijf | K6: Programma, ramingen, subsidiemogelijkheden | L6: Kredietaanvraag jaarschijf | M6: Uitvoering starten | N6: ja | O6: PC-04 | P6: ja | Q6: ja | R6: VS-02 | S6: 2026-10-03 | T6: dummy-generator | U6: 2026-10-03 | V6: dummy-generator | W6: concept | X6: 1 | AA6: DUMMY
A7: 8ae20795-1191-5505-8e12-d9d75fdc5689 | B7: BM-P5-01 | C7: P5 | D7: Voortgang en prestaties beoordelen | E7: Halen we de doelen en blijft het binnen budget? | F7: Dummy: bijsturen van het programma. | G7: BT-12 | H7: ambtelijk | I7: voorbereidend | J7: Bijsturen van het programma | K7: Voortgangs- en prestatiegegevens | L7: Monitoringsrapportage | M7: Strategie herijken | N7: nee | O7: PC-06 | P7: ja | Q7: ja | R7: VS-02 | S7: 2026-10-03 | T7: dummy-generator | U7: 2026-10-03 | V7: dummy-generator | W7: concept | X7: 1 | AA7: DUMMY
A8: 16f6beb3-d778-5595-a11b-2f796ba15a47 | B8: BM-P5-02 | C8: P5 | D8: Strategie herijken | E8: Moeten ambitie, kaders of programma worden aangepast? | F8: Dummy: herijken van strategie. | G8: BT-13 | H8: bestuurlijk | I8: definitief | J8: Herijken van strategie | K8: Monitoringsrapportage, beleidskaders | L8: Herijkingsvoorstel | M8: Nieuwe kaders vaststellen | N8: ja | O8: PC-01 | P8: ja | Q8: ja | R8: VS-02 | S8: 2026-10-03 | T8: dummy-generator | U8: 2026-10-03 | V8: dummy-generator | W8: concept | X8: 1 | AA8: DUMMY
A9: 6fa07aba-e44a-57f3-8dcc-f08cb18e7af6 | B9: BM-O1-01 | C9: O1 | D9: Initiatief starten | E9: Is er aanleiding om dit object aan te pakken? | F9: Dummy: starten van verkenning. | G9: BT-01 | H9: ambtelijk | I9: voorbereidend | J9: Starten van verkenning | K9: Onderhoudsstaat, gebruikerswensen | L9: Projectopdracht verkenning | M9: Haalbaarheid onderzoeken | N9: nee | O9: PC-11 | P9: ja | Q9: ja | R9: VS-02 | S9: 2026-10-03 | T9: dummy-generator | U9: 2026-10-03 | V9: dummy-generator | W9: concept | X9: 1 | AA9: DUMMY
A10: 89a2c493-046c-5938-87f3-635fbac99248 | B10: BM-O2-01 | C10: O2 | D10: Haalbaarheid en varianten beoordelen | E10: Is het haalbaar en welke varianten zijn er? | F10: Dummy: beoordelen van varianten. | G10: BT-06 | H10: ambtelijk | I10: voorbereidend | J10: Beoordelen van varianten | K10: Ramingen, exploitatie, juridische afspraken | L10: Scenariovergelijking | M10: Voorkeursvariant kiezen | N10: nee | P10: ja | Q10: ja | R10: VS-02 | S10: 2026-10-03 | T10: dummy-generator | U10: 2026-10-03 | V10: dummy-generator | W10: concept | X10: 1 | AA10: DUMMY
A11: e58bb9c6-4ed0-540b-ae41-7a7971ec2ed8 | B11: BM-O3-01 | C11: O3 | D11: Voorkeursvariant kiezen | E11: Welke variant heeft de voorkeur en wat is het budget? | F11: Dummy: kiezen van voorkeursvariant. | G11: BT-02 | H11: bestuurlijk | I11: richtinggevend | J11: Kiezen van voorkeursvariant | K11: Scenariovergelijking, maatschappelijk effect | L11: Voorkeursbesluit | M11: Ontwerp en financiële beoordeling | N11: ja | P11: ja | Q11: ja | R11: VS-02 | S11: 2026-10-03 | T11: dummy-generator | U11: 2026-10-03 | V11: dummy-generator | W11: concept | X11: 1 | AA11: DUMMY
A12: 6988526b-d463-523d-afaf-955c812cc5db | B12: BM-O4-01 | C12: O4 | D12: Voorkeursvariant financieel beoordelen | E12: Welke variant is over de levensduur het meest betaalbaar? | F12: Dummy: financiële toets van de voorkeursvariant. | G12: BT-06 | H12: ambtelijk | I12: voorbereidend | J12: Financiële toets van de voorkeursvariant | K12: Ramingen, TCO, boekwaarde, fiscale positie, risico's | L12: Investeringsvoorstel | M12: Investeringsbesluit voorbereiden | N12: nee | P12: ja | Q12: ja | R12: VS-02 | S12: 2026-10-03 | T12: dummy-generator | U12: 2026-10-03 | V12: dummy-generator | W12: concept | X12: 1 | AA12: DUMMY
A13: 49658117-4a7a-5431-a76a-d0409513ed1b | B13: BM-O4-02 | C13: O4 | D13: Investeringsbesluit nemen | E13: Nemen we het investeringsbesluit en onder welke voorwaarden? | F13: Dummy: nemen van investeringsbesluit. | G13: BT-07 | H13: bestuurlijk | I13: definitief | J13: Nemen van investeringsbesluit | K13: Investeringsvoorstel, bestuurlijke beslisinformatie | L13: Collegevoorstel en raadsvoorstel | M13: Krediet en dekking regelen | N13: ja | O13: PC-05 | P13: ja | Q13: ja | R13: VS-02 | S13: 2026-10-03 | T13: dummy-generator | U13: 2026-10-03 | V13: dummy-generator | W13: concept | X13: 1 | AA13: DUMMY
A14: c7eb949e-1c44-52b7-95d9-5726d80bec34 | B14: BM-O4-03 | C14: O4 | D14: Krediet en dekking regelen | E14: Is het krediet beschikbaar en is de dekking geregeld? | F14: Dummy: beschikbaar stellen van krediet. | G14: BT-08 | H14: formeel | I14: definitief | J14: Beschikbaar stellen van krediet | K14: Begrotingsruimte, subsidiebeschikkingen, leningaanbod | L14: Kredietaanvraag | M14: Aanbesteden | N14: ja | O14: PC-04 | P14: ja | Q14: ja | R14: VS-02 | S14: 2026-10-03 | T14: dummy-generator | U14: 2026-10-03 | V14: dummy-generator | W14: concept | X14: 1 | AA14: DUMMY
A15: db17631f-2449-54e2-b4d7-ebfc8c45ca12 | B15: BM-O5-01 | C15: O5 | D15: Opdracht verlenen aan uitvoerder | E15: Aan wie verlenen we de opdracht en tegen welke kosten? | F15: Dummy: gunnen van opdracht. | G15: BT-10 | H15: formeel | I15: definitief | J15: Gunnen van opdracht | K15: Raming, aanbestedingsstrategie, juridische afspraken | L15: Gunningsbesluit | M15: Realisatie bewaken | N15: nee | P15: ja | Q15: ja | R15: VS-02 | S15: 2026-10-03 | T15: dummy-generator | U15: 2026-10-03 | V15: dummy-generator | W15: concept | X15: 1 | AA15: DUMMY
A16: 1331e508-d2d5-57a0-b71a-339da74d3b20 | B16: BM-O6-01 | C16: O6 | D16: Oplevering accepteren | E16: Is het opgeleverd conform afspraken en wat zijn de beheerkosten? | F16: Dummy: accepteren van oplevering. | G16: BT-11 | H16: ambtelijk | I16: definitief | J16: Accepteren van oplevering | K16: Technische staat, exploitatiegegevens | L16: Opleverdossier | M16: In gebruik nemen | N16: nee | P16: ja | Q16: ja | R16: VS-02 | S16: 2026-10-03 | T16: dummy-generator | U16: 2026-10-03 | V16: dummy-generator | W16: concept | X16: 1 | AA16: DUMMY
A17: 2e2c89d9-0a51-5230-9d92-c0de821b80a1 | B17: BM-O7-01 | C17: O7 | D17: Exploitatie en prestaties evalueren | E17: Presteert het object zoals bedoeld en wat leren we? | F17: Dummy: evalueren en bijsturen. | G17: BT-12 | H17: ambtelijk | I17: richtinggevend | J17: Evalueren en bijsturen | K17: Verbruik, exploitatie, voortgang, gebruik | L17: Evaluatie en monitoringsrapportage | M17: Terugkoppelen naar portefeuille | N17: nee | O17: PC-07 | P17: ja | Q17: ja | R17: VS-02 | S17: 2026-10-03 | T17: dummy-generator | U17: 2026-10-03 | V17: dummy-generator | W17: concept | X17: 1 | AA17: DUMMY

Sheet besluittype
A1: besluittype_id | B1: code | C1: naam | D1: omschrijving | E1: sort_order | F1: created_at | G1: created_by | H1: updated_at | I1: updated_by | J1: record_status | K1: version_number | L1: valid_from | M1: valid_until | N1: notes_internal
A2: e5d229a1-26b1-58fc-8f15-f48996c7c9ef | B2: BT-01 | C2: verkennend | E2: 1 | F2: 2026-10-02 | G2: startwaardelijst datamodel | H2: 2026-10-02 | I2: startwaardelijst datamodel | J2: concept | K2: 1
A3: a6589a86-6c2d-5d1f-ac92-7157cb398233 | B3: BT-02 | C3: richtinggevend | E3: 2 | F3: 2026-10-02 | G3: startwaardelijst datamodel | H3: 2026-10-02 | I3: startwaardelijst datamodel | J3: concept | K3: 1
A4: a5c66e9a-5ac6-5c1a-84f0-d2f8fa665d89 | B4: BT-03 | C4: kaderstellend | E4: 3 | F4: 2026-10-02 | G4: startwaardelijst datamodel | H4: 2026-10-02 | I4: startwaardelijst datamodel | J4: concept | K4: 1
A5: f11e278c-42f9-5067-a1ad-4946e767a6a9 | B5: BT-04 | C5: prioriterend | E5: 4 | F5: 2026-10-02 | G5: startwaardelijst datamodel | H5: 2026-10-02 | I5: startwaardelijst datamodel | J5: concept | K5: 1
A6: 6e065eab-74fb-50c5-adb0-f173920b38a2 | B6: BT-05 | C6: programmerend | E6: 5 | F6: 2026-10-02 | G6: startwaardelijst datamodel | H6: 2026-10-02 | I6: startwaardelijst datamodel | J6: concept | K6: 1
A7: c1204c95-2f13-529f-bfaa-98af8667dca6 | B7: BT-06 | C7: financieel toetsend | E7: 6 | F7: 2026-10-02 | G7: startwaardelijst datamodel | H7: 2026-10-02 | I7: startwaardelijst datamodel | J7: concept | K7: 1
A8: 13b42bbe-207e-5dba-8de6-67238edf4976 | B8: BT-07 | C8: investeringsbesluit | E8: 7 | F8: 2026-10-02 | G8: startwaardelijst datamodel | H8: 2026-10-02 | I8: startwaardelijst datamodel | J8: concept | K8: 1
A9: cd348d5e-85cf-56a7-a8b7-314f894d7d4f | B9: BT-08 | C9: kredietbesluit | E9: 8 | F9: 2026-10-02 | G9: startwaardelijst datamodel | H9: 2026-10-02 | I9: startwaardelijst datamodel | J9: concept | K9: 1
A10: 312bae80-63f0-5bb7-ad11-b4980413b9e7 | B10: BT-09 | C10: uitvoeringsbesluit | E10: 9 | F10: 2026-10-02 | G10: startwaardelijst datamodel | H10: 2026-10-02 | I10: startwaardelijst datamodel | J10: concept | K10: 1
A11: 2bd3d1b3-653d-5198-ac0d-01a01dab41b2 | B11: BT-10 | C11: contractbesluit | E11: 10 | F11: 2026-10-02 | G11: startwaardelijst datamodel | H11: 2026-10-02 | I11: startwaardelijst datamodel | J11: concept | K11: 1
A12: a6a030b1-fcc9-59f2-9a0b-c838cad042c2 | B12: BT-11 | C12: acceptatiebesluit | E12: 11 | F12: 2026-10-02 | G12: startwaardelijst datamodel | H12: 2026-10-02 | I12: startwaardelijst datamodel | J12: concept | K12: 1
A13: ce985b68-3037-5156-b829-118d3e4c60fe | B13: BT-12 | C13: bijsturingsbesluit | E13: 12 | F13: 2026-10-02 | G13: startwaardelijst datamodel | H13: 2026-10-02 | I13: startwaardelijst datamodel | J13: concept | K13: 1
... A15: cbec7d03-a1ff-5339-b5bc-59643ead2463 | B15: BT-14 | C15: beëindigingsbesluit | E15: 14 | F15: 2026-10-02 | G15: startwaardelijst datamodel | H15: 2026-10-02 | I15: startwaardelijst datamodel | J15: concept | K15: 1

Sheet rol
A1: rol_id | B1: rol_code | C1: naam | D1: rolcluster_id | E1: omschrijving | F1: primaire_verantwoordelijkheid | G1: typisch_perspectief | H1: informatie_detailniveau | I1: primaire_gebruiker_v1 | J1: externe_rol | K1: is_work_hypothesis | L1: validation_status_id | M1: created_at | N1: created_by | O1: updated_at | P1: updated_by | Q1: record_status | R1: version_number | S1: valid_from | T1: valid_until | U1: notes_internal
A2: 5cb94d0d-d9c3-58ae-9787-fa878d7c8443 | B2: ROL-001 | C2: beleidsopdrachtgever | D2: RC-04 | E2: Dummy: de rol beleidsopdrachtgever in vastgoedbesluitvorming. | F2: Dummy: verantwoordelijk voor het aandeel van de beleidsopdrachtgever in het besluit. | H2: strategisch | I2: nee | J2: nee | K2: ja | L2: VS-02 | M2: 2026-10-02 | N2: startwaardelijst datamodel | O2: 2026-10-02 | P2: startwaardelijst datamodel | Q2: concept | R2: 1 | U2: DUMMY-aanvulling: externe_rol, informatie_detailniveau, omschrijving, primaire_gebruiker_v1, primaire_verantwoordelijkheid, rolcluster_id, validation_status_id
A3: c4d89414-041c-5a14-a5d7-d80c1293318b | B3: ROL-002 | C3: portefeuilleregisseur | D3: RC-01 | E3: Dummy: de rol portefeuilleregisseur in vastgoedbesluitvorming. | F3: Dummy: verantwoordelijk voor het aandeel van de portefeuilleregisseur in het besluit. | H3: strategisch | I3: ja | J3: nee | K3: ja | L3: VS-02 | M3: 2026-10-02 | N3: startwaardelijst datamodel | O3: 2026-10-02 | P3: startwaardelijst datamodel | Q3: concept | R3: 1 | U3: DUMMY-aanvulling: externe_rol, informatie_detailniveau, omschrijving, primaire_gebruiker_v1, primaire_verantwoordelijkheid, rolcluster_id, validation_status_id
A4: 78fde774-e707-585a-9717-02694381c956 | B4: ROL-003 | C4: vastgoedmanager | D4: RC-01 | E4: Dummy: de rol vastgoedmanager in vastgoedbesluitvorming. | F4: Dummy: verantwoordelijk voor het aandeel van de vastgoedmanager in het besluit. | H4: tactisch | I4: ja | J4: nee | K4: ja | L4: VS-02 | M4: 2026-10-02 | N4: startwaardelijst datamodel | O4: 2026-10-02 | P4: startwaardelijst datamodel | Q4: concept | R4: 1 | U4: DUMMY-aanvulling: externe_rol, informatie_detailniveau, omschrijving, primaire_gebruiker_v1, primaire_verantwoordelijkheid, rolcluster_id, validation_status_id
A5: a75f1ece-f3e5-5633-9b37-3537f763539b | B5: ROL-004 | C5: assetmanager | D5: RC-01 | E5: Dummy: de rol assetmanager in vastgoedbesluitvorming. | F5: Dummy: verantwoordelijk voor het aandeel van de assetmanager in het besluit. | H5: tactisch | I5: ja | J5: nee | K5: ja | L5: VS-02 | M5: 2026-10-02 | N5: startwaardelijst datamodel | O5: 2026-10-02 | P5: startwaardelijst datamodel | Q5: concept | R5: 1 | U5: DUMMY-aanvulling: externe_rol, informatie_detailniveau, omschrijving, primaire_gebruiker_v1, primaire_verantwoordelijkheid, rolcluster_id, validation_status_id
A6: cc3e6744-260b-5c55-86fd-8935039c6e55 | B6: ROL-005 | C6: projectverantwoordelijke | D6: RC-01 | E6: Dummy: de rol projectverantwoordelijke in vastgoedbesluitvorming. | F6: Dummy: verantwoordelijk voor het aandeel van de projectverantwoordelijke in het besluit. | H6: operationeel | I6: ja | J6: nee | K6: ja | L6: VS-02 | M6: 2026-10-02 | N6: startwaardelijst datamodel | O6: 2026-10-02 | P6: startwaardelijst datamodel | Q6: concept | R6: 1 | U6: DUMMY-aanvulling: externe_rol, informatie_detailniveau, omschrijving, primaire_gebruiker_v1, primaire_verantwoordelijkheid, rolcluster_id, validation_status_id
A7: 926c6640-e74d-58e3-b7c4-aa4de3c82eae | B7: ROL-006 | C7: beheerder | D7: RC-05 | E7: Dummy: de rol beheerder in vastgoedbesluitvorming. | F7: Dummy: verantwoordelijk voor het aandeel van de beheerder in het besluit. | H7: operationeel | I7: nee | J7: nee | K7: ja | L7: VS-02 | M7: 2026-10-02 | N7: startwaardelijst datamodel | O7: 2026-10-02 | P7: startwaardelijst datamodel | Q7: concept | R7: 1 | U7: DUMMY-aanvulling: externe_rol, informatie_detailniveau, omschrijving, primaire_gebruiker_v1, primaire_verantwoordelijkheid, rolcluster_id, validation_status_id
A8: ea258ed3-d0f1-5306-93e0-6c7d58cb6230 | B8: ROL-007 | C8: exploitant | D8: RC-05 | E8: Dummy: de rol exploitant in vastgoedbesluitvorming. | F8: Dummy: verantwoordelijk voor het aandeel van de exploitant in het besluit. | H8: operationeel | I8: nee | J8: nee | K8: ja | L8: VS-02 | M8: 2026-10-02 | N8: startwaardelijst datamodel | O8: 2026-10-02 | P8: startwaardelijst datamodel | Q8: concept | R8: 1 | U8: DUMMY-aanvulling: externe_rol, informatie_detailniveau, omschrijving, primaire_gebruiker_v1, primaire_verantwoordelijkheid, rolcluster_id, validation_status_id
A9: 06ac82e4-0414-5d3f-b8ed-11b07cd17e56 | B9: ROL-008 | C9: beleidsadviseur | D9: RC-03 | E9: Dummy: de rol beleidsadviseur in vastgoedbesluitvorming. | F9: Dummy: verantwoordelijk voor het aandeel van de beleidsadviseur in het besluit. | H9: tactisch | I9: ja | J9: nee | K9: ja | L9: VS-02 | M9: 2026-10-02 | N9: startwaardelijst datamodel | O9: 2026-10-02 | P9: startwaardelijst datamodel | Q9: concept | R9: 1 | U9: DUMMY-aanvulling: externe_rol, informatie_detailniveau, omschrijving, primaire_gebruiker_v1, primaire_verantwoordelijkheid, rolcluster_id, validation_status_id
A10: 6f8b2ba2-f64c-57b3-9b63-fe9b4a05a21d | B10: ROL-009 | C10: strategisch adviseur | D10: RC-03 | E10: Dummy: de rol strategisch adviseur in vastgoedbesluitvorming. | F10: Dummy: verantwoordelijk voor het aandeel van de strategisch adviseur in het besluit. | H10: strategisch | I10: nee | J10: nee | K10: ja | L10: VS-02 | M10: 2026-10-02 | N10: startwaardelijst datamodel | O10: 2026-10-02 | P10: startwaardelijst datamodel | Q10: concept | R10: 1 | U10: DUMMY-aanvulling: externe_rol, informatie_detailniveau, omschrijving, primaire_gebruiker_v1, primaire_verantwoordelijkheid, rolcluster_id, validation_status_id
A11: 0c3ca78c-b51f-5fdb-8126-f05d6d9d0e56 | B11: ROL-010 | C11: programmamanager | D11: RC-03 | E11: Dummy: de rol programmamanager in vastgoedbesluitvorming. | F11: Dummy: verantwoordelijk voor het aandeel van de programmamanager in het besluit. | H11: tactisch | I11: nee | J11: nee | K11: ja | L11: VS-02 | M11: 2026-10-02 | N11: startwaardelijst datamodel | O11: 2026-10-02 | P11: startwaardelijst datamodel | Q11: concept | R11: 1 | U11: DUMMY-aanvulling: externe_rol, informatie_detailniveau, omschrijving, primaire_gebruiker_v1, primaire_verantwoordelijkheid, rolcluster_id, validation_status_id
A12: 2e734299-91ac-5f36-ae56-8042318bcd8c | B12: ROL-011 | C12: financieel adviseur | D12: RC-02 | E12: Dummy: de rol financieel adviseur in vastgoedbesluitvorming. | F12: Dummy: verantwoordelijk voor het aandeel van de financieel adviseur in het besluit. | H12: tactisch | I12: ja | J12: nee | K12: ja | L12: VS-02 | M12: 2026-10-02 | N12: startwaardelijst datamodel | O12: 2026-10-02 | P12: startwaardelijst datamodel | Q12: concept | R12: 1 | U12: DUMMY-aanvulling: externe_rol, informatie_detailniveau, omschrijving, primaire_gebruiker_v1, primaire_verantwoordelijkheid, rolcluster_id, validation_status_id
A13: fb39ef16-74a0-5129-8359-b224431707f6 | B13: ROL-012 | C13: controller | D13: RC-02 | E13: Dummy: de rol controller in vastgoedbesluitvorming. | F13: Dummy: verantwoordelijk voor het aandeel van de controller in het besluit. | H13: tactisch | I13: ja | J13: nee | K13: ja | L13: VS-02 | M13: 2026-10-02 | N13: startwaardelijst datamodel | O13: 2026-10-02 | P13: startwaardelijst datamodel | Q13: concept | R13: 1 | U13: DUMMY-aanvulling: externe_rol, informatie_detailniveau, omschrijving, primaire_gebruiker_v1, primaire_verantwoordelijkheid, rolcluster_id, validation_status_id
... A23: 8a2c2eb1-f023-5c28-b84f-027594af6442 | B23: ROL-022 | C23: kennispartner | D23: RC-09 | E23: Dummy: de rol kennispartner in vastgoedbesluitvorming. | F23: Dummy: verantwoordelijk voor het aandeel van de kennispartner in het besluit. | H23: tactisch | I23: nee | J23: ja | K23: ja | L23: VS-02 | M23: 2026-10-02 | N23: startwaardelijst datamodel | O23: 2026-10-02 | P23: startwaardelijst datamodel | Q23: concept | R23: 1 | U23: DUMMY-aanvulling: externe_rol, informatie_detailniveau, omschrijving, primaire_gebruiker_v1, primaire_verantwoordelijkheid, rolcluster_id, validation_status_id

Sheet rolcluster
A1: rolcluster_id | B1: code | C1: naam | D1: omschrijving | E1: sort_order | F1: created_at | G1: created_by | H1: updated_at | I1: updated_by | J1: record_status | K1: version_number | L1: valid_from | M1: valid_until | N1: notes_internal
A2: fed0b311-e32d-5d87-a5fa-c7fc31b281e3 | B2: RC-01 | C2: vastgoed | E2: 1 | F2: 2026-10-02 | G2: startwaardelijst datamodel | H2: 2026-10-02 | I2: startwaardelijst datamodel | J2: concept | K2: 1
A3: 2f357169-a0ed-5344-93c2-6c1888fcb0e2 | B3: RC-02 | C3: financiën en control | E3: 2 | F3: 2026-10-02 | G3: startwaardelijst datamodel | H3: 2026-10-02 | I3: startwaardelijst datamodel | J3: concept | K3: 1
A4: e16560bc-a3da-5c5f-9270-bff12c54670f | B4: RC-03 | C4: beleid | E4: 3 | F4: 2026-10-02 | G4: startwaardelijst datamodel | H4: 2026-10-02 | I4: startwaardelijst datamodel | J4: concept | K4: 1
A5: e1541d9b-3f83-5295-addc-ca6ae16c8ebd | B5: RC-04 | C5: bestuur | E5: 4 | F5: 2026-10-02 | G5: startwaardelijst datamodel | H5: 2026-10-02 | I5: startwaardelijst datamodel | J5: concept | K5: 1
A6: 9fb9ef4c-67ba-5131-b20d-ca03bcad039a | B6: RC-05 | C6: beheer en exploitatie | E6: 5 | F6: 2026-10-02 | G6: startwaardelijst datamodel | H6: 2026-10-02 | I6: startwaardelijst datamodel | J6: concept | K6: 1
A7: 427327f3-64ce-5373-9664-e4cdc932ad57 | B7: RC-06 | C7: gebruiker en eigenaar | E7: 6 | F7: 2026-10-02 | G7: startwaardelijst datamodel | H7: 2026-10-02 | I7: startwaardelijst datamodel | J7: concept | K7: 1
A8: 21ddf6a9-4877-56c6-aae7-fec0da07a213 | B8: RC-07 | C8: juridisch en fiscaal | E8: 7 | F8: 2026-10-02 | G8: startwaardelijst datamodel | H8: 2026-10-02 | I8: startwaardelijst datamodel | J8: concept | K8: 1
A9: 7e55d5aa-947e-5a8f-ad4c-1aa9fe546ae4 | B9: RC-08 | C9: inkoop en contractering | E9: 8 | F9: 2026-10-02 | G9: startwaardelijst datamodel | H9: 2026-10-02 | I9: startwaardelijst datamodel | J9: concept | K9: 1
A10: 005da926-88a2-540e-aad5-59d75e656909 | B10: RC-09 | C10: markt en kennis | E10: 9 | F10: 2026-10-02 | G10: startwaardelijst datamodel | H10: 2026-10-02 | I10: startwaardelijst datamodel | J10: concept | K10: 1

Sheet functie_alias
A1: functie_alias_id | B1: rol_id | C1: functietitel | D1: organisatiecontext | E1: toelichting | F1: is_preferred_term | G1: created_at | H1: created_by | I1: updated_at | J1: updated_by | K1: record_status | L1: version_number | M1: valid_from | N1: valid_until | O1: notes_internal
A2: cc5e53e1-df17-5398-ab6d-4c60c676a7ec | B2: ROL-003 | C2: Vastgoedregisseur | D2: Dummy-gemeente | F2: ja | G2: 2026-10-03 | H2: dummy-generator | I2: 2026-10-03 | J2: dummy-generator | K2: concept | L2: 1 | O2: DUMMY
A3: af131c2f-8e05-5743-9353-c25af1f2542e | B3: ROL-003 | C3: Accountmanager vastgoed | D3: Dummy-gemeente | F3: nee | G3: 2026-10-03 | H3: dummy-generator | I3: 2026-10-03 | J3: dummy-generator | K3: concept | L3: 1 | O3: DUMMY
A4: d87c9fb5-cc9f-56e9-9375-5901498bf45a | B4: ROL-004 | C4: Assetmanager | D4: Dummy-gemeente | F4: ja | G4: 2026-10-03 | H4: dummy-generator | I4: 2026-10-03 | J4: dummy-generator | K4: concept | L4: 1 | O4: DUMMY
A5: 1b9ff2a1-ddd9-507f-ad53-0119bd0b3b54 | B5: ROL-004 | C5: Portefeuillemanager vastgoed | D5: Dummy-gemeente | F5: nee | G5: 2026-10-03 | H5: dummy-generator | I5: 2026-10-03 | J5: dummy-generator | K5: concept | L5: 1 | O5: DUMMY
A6: 609aca0c-c239-5c6a-83d7-4ea79b1f611f | B6: ROL-005 | C6: Projectleider vastgoed | D6: Dummy-gemeente | F6: ja | G6: 2026-10-03 | H6: dummy-generator | I6: 2026-10-03 | J6: dummy-generator | K6: concept | L6: 1 | O6: DUMMY
A7: 9e45ded6-e079-5bc3-9e51-c566f867a365 | B7: ROL-005 | C7: Projectmanager | D7: Dummy-gemeente | F7: nee | G7: 2026-10-03 | H7: dummy-generator | I7: 2026-10-03 | J7: dummy-generator | K7: concept | L7: 1 | O7: DUMMY
A8: 7317c829-b6e3-52d4-b64a-d8eabbf07022 | B8: ROL-006 | C8: Beheerder gebouwen | D8: Dummy-gemeente | F8: ja | G8: 2026-10-03 | H8: dummy-generator | I8: 2026-10-03 | J8: dummy-generator | K8: concept | L8: 1 | O8: DUMMY
A9: a1c30f2e-db3d-5b02-abe7-d7e4e3ca2221 | B9: ROL-006 | C9: Facilitair beheerder | D9: Dummy-gemeente | F9: nee | G9: 2026-10-03 | H9: dummy-generator | I9: 2026-10-03 | J9: dummy-generator | K9: concept | L9: 1 | O9: DUMMY
A10: e8387b0d-5079-5d1e-b79c-14c5954fb45a | B10: ROL-011 | C10: Financieel adviseur | D10: Dummy-gemeente | F10: ja | G10: 2026-10-03 | H10: dummy-generator | I10: 2026-10-03 | J10: dummy-generator | K10: concept | L10: 1 | O10: DUMMY
A11: 378b7bfc-6de8-5f26-b224-e207ce5f78b2 | B11: ROL-011 | C11: Business controller | D11: Dummy-gemeente | F11: nee | G11: 2026-10-03 | H11: dummy-generator | I11: 2026-10-03 | J11: dummy-generator | K11: concept | L11: 1 | O11: DUMMY
A12: 924cde10-6f45-5b39-b801-018eb3f4539f | B12: ROL-012 | C12: Concerncontroller | D12: Dummy-gemeente | F12: ja | G12: 2026-10-03 | H12: dummy-generator | I12: 2026-10-03 | J12: dummy-generator | K12: concept | L12: 1 | O12: DUMMY
A13: 5d9a785b-c7d0-54bc-8985-5689a39443b5 | B13: ROL-012 | C13: Afdelingscontroller | D13: Dummy-gemeente | F13: nee | G13: 2026-10-03 | H13: dummy-generator | I13: 2026-10-03 | J13: dummy-generator | K13: concept | L13: 1 | O13: DUMMY
... A19: 616b2ab4-e431-5d89-a839-92f50cd7430e | B19: ROL-010 | C19: Programmaleider verduurzaming | D19: Dummy-gemeente | F19: ja | G19: 2026-10-03 | H19: dummy-generator | I19: 2026-10-03 | J19: dummy-generator | K19: concept | L19: 1 | O19: DUMMY

Sheet eigenaartype
A1: eigenaartype_id | B1: code | C1: naam | D1: omschrijving | E1: primaire_scope_v1 | F1: sort_order | G1: created_at | H1: created_by | I1: updated_at | J1: updated_by | K1: record_status | L1: version_number | M1: valid_from | N1: valid_until | O1: notes_internal
A2: 078c79c9-e872-5cf9-86ca-86cee134ed0e | B2: ET-01 | C2: gemeente | E2: ja | F2: 1 | G2: 2026-10-02 | H2: startwaardelijst datamodel | I2: 2026-10-02 | J2: startwaardelijst datamodel | K2: concept | L2: 1
A3: 7880bbc3-8ca6-5a8b-ac49-7751b310e86d | B3: ET-02 | C3: eigenaar met gemeentelijke subsidierelatie | E3: nee | F3: 2 | G3: 2026-10-02 | H3: startwaardelijst datamodel | I3: 2026-10-02 | J3: startwaardelijst datamodel | K3: concept | L3: 1
A4: cd8a3340-e6a7-5923-8b74-82369ee823f1 | B4: ET-03 | C4: eigenaar zonder gemeentelijke subsidierelatie | E4: nee | F4: 3 | G4: 2026-10-02 | H4: startwaardelijst datamodel | I4: 2026-10-02 | J4: startwaardelijst datamodel | K4: concept | L4: 1
A5: 05920de7-e9a9-5532-ae36-58f28e15ec69 | B5: ET-04 | C5: schoolbestuur | E5: nee | F5: 4 | G5: 2026-10-02 | H5: startwaardelijst datamodel | I5: 2026-10-02 | J5: startwaardelijst datamodel | K5: concept | L5: 1
A6: b7773c08-7b62-506a-aaf9-098f38d327ab | B6: ET-05 | C6: zorginstelling | E6: nee | F6: 5 | G6: 2026-10-02 | H6: startwaardelijst datamodel | I6: 2026-10-02 | J6: startwaardelijst datamodel | K6: concept | L6: 1
A7: df6af6ff-fd4c-5b1a-b5c2-0a6b6e63983d | B7: ET-06 | C7: gemeenschappelijke regeling | E7: nee | F7: 6 | G7: 2026-10-02 | H7: startwaardelijst datamodel | I7: 2026-10-02 | J7: startwaardelijst datamodel | K7: concept | L7: 1
A8: 460cb315-5aad-5fd8-b74d-488d7a87ee6f | B8: ET-07 | C8: stichting | E8: nee | F8: 7 | G8: 2026-10-02 | H8: startwaardelijst datamodel | I8: 2026-10-02 | J8: startwaardelijst datamodel | K8: concept | L8: 1
A9: 3a4905cd-2dd8-5b16-ae70-6154444062d1 | B9: ET-08 | C9: vereniging | E9: nee | F9: 8 | G9: 2026-10-02 | H9: startwaardelijst datamodel | I9: 2026-10-02 | J9: startwaardelijst datamodel | K9: concept | L9: 1
A10: 80298eea-2dd0-598a-bd99-71de7ef4e58a | B10: ET-09 | C10: publiek-private entiteit | E10: nee | F10: 9 | G10: 2026-10-02 | H10: startwaardelijst datamodel | I10: 2026-10-02 | J10: startwaardelijst datamodel | K10: concept | L10: 1
A11: cbba3ce9-0d48-5e98-9680-997b1690e834 | B11: ET-10 | C11: overig | E11: nee | F11: 10 | G11: 2026-10-02 | H11: startwaardelijst datamodel | I11: 2026-10-02 | J11: startwaardelijst datamodel | K11: concept | L11: 1

Sheet objecttype
A1: objecttype_id | B1: objecttype_code | C1: naam | D1: parent_objecttype_id | E1: omschrijving | F1: sort_order | G1: created_at | H1: created_by | I1: updated_at | J1: updated_by | K1: record_status | L1: version_number | M1: valid_from | N1: valid_until | O1: notes_internal
A2: bb593c1e-8f69-5c36-85ff-1e2af5dd4915 | B2: OT-01 | C2: maatschappelijk vastgoed | F2: 1 | G2: 2026-10-02 | H2: startwaardelijst datamodel | I2: 2026-10-02 | J2: startwaardelijst datamodel | K2: concept | L2: 1
A3: 0cf2fa28-5439-5e96-ad44-1b8262df0ad2 | B3: OT-02 | C3: sportvastgoed | D3: OT-01 | F3: 2 | G3: 2026-10-02 | H3: startwaardelijst datamodel | I3: 2026-10-02 | J3: startwaardelijst datamodel | K3: concept | L3: 1
A4: a0868aaf-a2ad-52ec-82d9-355bc12de3ee | B4: OT-03 | C4: sporthal | D4: OT-02 | F4: 3 | G4: 2026-10-02 | H4: startwaardelijst datamodel | I4: 2026-10-02 | J4: startwaardelijst datamodel | K4: concept | L4: 1
A5: dca58d0b-825e-59b0-9d6c-f4b083ae03f9 | B5: OT-04 | C5: zwembad | D5: OT-02 | F5: 4 | G5: 2026-10-02 | H5: startwaardelijst datamodel | I5: 2026-10-02 | J5: startwaardelijst datamodel | K5: concept | L5: 1
A6: fd592021-5b5d-5d93-b59e-5a4d8ce9b966 | B6: OT-05 | C6: buitensportaccommodatie | D6: OT-02 | F6: 5 | G6: 2026-10-02 | H6: startwaardelijst datamodel | I6: 2026-10-02 | J6: startwaardelijst datamodel | K6: concept | L6: 1
A7: c8e8cf33-830a-559f-b6a5-291f1a77a320 | B7: OT-06 | C7: onderwijsvastgoed | D7: OT-01 | F7: 6 | G7: 2026-10-02 | H7: startwaardelijst datamodel | I7: 2026-10-02 | J7: startwaardelijst datamodel | K7: concept | L7: 1
A8: 2b4b81d5-8240-5c7e-afae-8925be43b0bc | B8: OT-07 | C8: basisschool | D8: OT-06 | F8: 7 | G8: 2026-10-02 | H8: startwaardelijst datamodel | I8: 2026-10-02 | J8: startwaardelijst datamodel | K8: concept | L8: 1
A9: 57a7ebd4-625b-5045-8929-becbe2b89b27 | B9: OT-08 | C9: voortgezet onderwijs | D9: OT-06 | F9: 8 | G9: 2026-10-02 | H9: startwaardelijst datamodel | I9: 2026-10-02 | J9: startwaardelijst datamodel | K9: concept | L9: 1
A10: 35ad4c44-208c-5982-8c6e-803b1db8979f | B10: OT-09 | C10: cultuurvastgoed | D10: OT-01 | F10: 9 | G10: 2026-10-02 | H10: startwaardelijst datamodel | I10: 2026-10-02 | J10: startwaardelijst datamodel | K10: concept | L10: 1
A11: 74ed2318-9704-5d82-91cb-31c03ff4ea27 | B11: OT-10 | C11: theater | D11: OT-09 | F11: 10 | G11: 2026-10-02 | H11: startwaardelijst datamodel | I11: 2026-10-02 | J11: startwaardelijst datamodel | K11: concept | L11: 1
A12: f6b11a85-4cce-55b8-8298-04d3c1f09c43 | B12: OT-11 | C12: museum | D12: OT-09 | F12: 11 | G12: 2026-10-02 | H12: startwaardelijst datamodel | I12: 2026-10-02 | J12: startwaardelijst datamodel | K12: concept | L12: 1
A13: c17db46f-95b7-5c4f-9091-32a671dbf086 | B13: OT-12 | C13: bibliotheek | D13: OT-09 | F13: 12 | G13: 2026-10-02 | H13: startwaardelijst datamodel | I13: 2026-10-02 | J13: startwaardelijst datamodel | K13: concept | L13: 1
A14: 3a6774e7-1410-5ee7-8f8d-6f701d8c4ca4 | B14: OT-13 | C14: welzijnsvastgoed | D14: OT-01 | F14: 13 | G14: 2026-10-02 | H14: startwaardelijst datamodel | I14: 2026-10-02 | J14: startwaardelijst datamodel | K14: concept | L14: 1
... A22: ad0061b1-4aa0-5f4a-8345-ece6c26c5313 | B22: OT-21 | C22: overig | D22: OT-01 | F22: 21 | G22: 2026-10-02 | H22: startwaardelijst datamodel | I22: 2026-10-02 | J22: startwaardelijst datamodel | K22: concept | L22: 1

Sheet financiele_vraag
A1: financiele_vraag_id | B1: vraag_code | C1: vraagtekst | D1: korte_naam | E1: financieel_thema_id | F1: omschrijving | G1: verwacht_antwoordtype | H1: sort_order | I1: created_at | J1: created_by | K1: updated_at | L1: updated_by | M1: record_status | N1: version_number | O1: valid_from | P1: valid_until | Q1: notes_internal
A2: 3386974c-aa28-56ac-bf93-bbc5bc7694fa | B2: FV-001 | C2: Wat kost niets doen? | D2: Kosten niets doen | E2: TH-02 | G2: bedrag | H2: 1 | I2: 2026-10-02 | J2: startwaardelijst datamodel | K2: 2026-10-02 | L2: startwaardelijst datamodel | M2: concept | N2: 1 | Q2: DUMMY-aanvulling: financieel_thema_id, korte_naam, verwacht_antwoordtype
A3: d9f6ca41-4b54-5819-896e-6b44a084c8bf | B3: FV-002 | C3: Wat is de totale investeringsbehoefte? | D3: Investeringsbehoefte | E3: TH-03 | G3: bedrag | H3: 2 | I3: 2026-10-02 | J3: startwaardelijst datamodel | K3: 2026-10-02 | L3: startwaardelijst datamodel | M3: concept | N3: 1 | Q3: DUMMY-aanvulling: financieel_thema_id, korte_naam, verwacht_antwoordtype
A4: 1a4217e4-4442-5265-b755-0fe8f80c8449 | B4: FV-003 | C4: Welke structurele lasten ontstaan? | D4: Structurele lasten | E4: TH-06 | G4: bedrag | H4: 3 | I4: 2026-10-02 | J4: startwaardelijst datamodel | K4: 2026-10-02 | L4: startwaardelijst datamodel | M4: concept | N4: 1 | Q4: DUMMY-aanvulling: financieel_thema_id, korte_naam, verwacht_antwoordtype
A5: 7ca525e4-2bfe-56d6-9f5e-64033df231f9 | B5: FV-004 | C5: Welke dekking is beschikbaar? | D5: Dekking | E5: TH-09 | G5: overzicht | H5: 4 | I5: 2026-10-02 | J5: startwaardelijst datamodel | K5: 2026-10-02 | L5: startwaardelijst datamodel | M5: concept | N5: 1 | Q5: DUMMY-aanvulling: financieel_thema_id, korte_naam, verwacht_antwoordtype
A6: 43b9b0e9-16b1-5cd5-821a-e4e2c5c391ba | B6: FV-005 | C6: Welke subsidies zijn beschikbaar? | D6: Subsidies | E6: TH-01 | G6: overzicht | H6: 5 | I6: 2026-10-02 | J6: startwaardelijst datamodel | K6: 2026-10-02 | L6: startwaardelijst datamodel | M6: concept | N6: 1 | Q6: DUMMY-aanvulling: financieel_thema_id, korte_naam, verwacht_antwoordtype
A7: fac9f842-8386-5651-899c-3efb296dcf82 | B7: FV-006 | C7: Hoe landt de investering in begroting en MIP? | D7: Begroting en MIP | E7: TH-04 | G7: overzicht | H7: 6 | I7: 2026-10-02 | J7: startwaardelijst datamodel | K7: 2026-10-02 | L7: startwaardelijst datamodel | M7: concept | N7: 1 | Q7: DUMMY-aanvulling: financieel_thema_id, korte_naam, verwacht_antwoordtype
A8: 4a97989c-e48f-5c0f-b05d-f2eb442c6a73 | B8: FV-007 | C8: Welke fiscale gevolgen zijn er? | D8: Fiscale gevolgen | E8: TH-08 | G8: overzicht | H8: 7 | I8: 2026-10-02 | J8: startwaardelijst datamodel | K8: 2026-10-02 | L8: startwaardelijst datamodel | M8: concept | N8: 1 | Q8: DUMMY-aanvulling: financieel_thema_id, korte_naam, verwacht_antwoordtype
A9: b17a8b26-548f-537f-87eb-d19b376870d4 | B9: FV-008 | C9: Welke risico’s moeten worden meegenomen? | D9: Risico's | E9: TH-17 | G9: overzicht | H9: 8 | I9: 2026-10-02 | J9: startwaardelijst datamodel | K9: 2026-10-02 | L9: startwaardelijst datamodel | M9: concept | N9: 1 | Q9: DUMMY-aanvulling: financieel_thema_id, korte_naam, verwacht_antwoordtype
A10: a7fbdd0c-e118-5074-9705-99e2c08e8aba | B10: FV-009 | C10: Welke scenario’s zijn financieel vergelijkbaar? | D10: Scenariovergelijking | E10: TH-17 | G10: overzicht | H10: 9 | I10: 2026-10-02 | J10: startwaardelijst datamodel | K10: 2026-10-02 | L10: startwaardelijst datamodel | M10: concept | N10: 1 | Q10: DUMMY-aanvulling: financieel_thema_id, korte_naam, verwacht_antwoordtype
A11: 132ae9ef-e910-5827-9682-3d42146cbaaa | B11: FV-010 | C11: Welke huur- of subsidieafspraken zijn nodig? | D11: Huur- en subsidieafspraken | E11: TH-07 | G11: overzicht | H11: 10 | I11: 2026-10-02 | J11: startwaardelijst datamodel | K11: 2026-10-02 | L11: startwaardelijst datamodel | M11: concept | N11: 1 | Q11: DUMMY-aanvulling: financieel_thema_id, korte_naam, verwacht_antwoordtype
A12: c4b284ef-df54-576e-8f29-b591a1481436 | B12: FV-011 | C12: Welke financieringsconstructie past? | D12: Financieringsconstructie | E12: TH-14 | G12: overzicht | H12: 11 | I12: 2026-10-02 | J12: startwaardelijst datamodel | K12: 2026-10-02 | L12: startwaardelijst datamodel | M12: concept | N12: 1 | Q12: DUMMY-aanvulling: financieel_thema_id, korte_naam, verwacht_antwoordtype
A13: a3a60b60-fa9b-594a-93c8-5194b4df1d65 | B13: FV-012 | C13: Hoe worden maatschappelijke effecten meegewogen? | D13: Maatschappelijke effecten | E13: TH-13 | G13: overzicht | H13: 12 | I13: 2026-10-02 | J13: startwaardelijst datamodel | K13: 2026-10-02 | L13: startwaardelijst datamodel | M13: concept | N13: 1 | Q13: DUMMY-aanvulling: financieel_thema_id, korte_naam, verwacht_antwoordtype

Sheet financieel_thema
A1: financieel_thema_id | B1: thema_code | C1: naam | D1: omschrijving | E1: parent_thema_id | F1: sort_order | G1: created_at | H1: created_by | I1: updated_at | J1: updated_by | K1: record_status | L1: version_number | M1: valid_from | N1: valid_until | O1: notes_internal
A2: c65f5d0f-5866-53f5-b249-68d83f4c4f77 | B2: TH-01 | C2: subsidies | F2: 1 | G2: 2026-10-02 | H2: startwaardelijst datamodel | I2: 2026-10-02 | J2: startwaardelijst datamodel | K2: concept | L2: 1
A3: 290083a1-0bd9-537a-9f5b-c44fe862ddd1 | B3: TH-02 | C3: TCO | F3: 2 | G3: 2026-10-02 | H3: startwaardelijst datamodel | I3: 2026-10-02 | J3: startwaardelijst datamodel | K3: concept | L3: 1
A4: 7ae6f15d-0003-5d19-9151-14c9ec9d7ab0 | B4: TH-03 | C4: investeringsopgave | F4: 3 | G4: 2026-10-02 | H4: startwaardelijst datamodel | I4: 2026-10-02 | J4: startwaardelijst datamodel | K4: concept | L4: 1
A5: 1eca9eab-098d-50d2-8baa-d8c96b9d58c6 | B5: TH-04 | C5: begroting | F5: 4 | G5: 2026-10-02 | H5: startwaardelijst datamodel | I5: 2026-10-02 | J5: startwaardelijst datamodel | K5: concept | L5: 1
A6: e0449d32-09b9-50be-a4af-c9c111f9d1b0 | B6: TH-05 | C6: MIP | E6: TH-04 | F6: 5 | G6: 2026-10-02 | H6: startwaardelijst datamodel | I6: 2026-10-02 | J6: startwaardelijst datamodel | K6: concept | L6: 1 | O6: DUMMY-aanvulling: parent_thema_id
A7: 9d83abb2-c1a8-5d8e-9773-1bb01eedb2b5 | B7: TH-06 | C7: exploitatie | F7: 6 | G7: 2026-10-02 | H7: startwaardelijst datamodel | I7: 2026-10-02 | J7: startwaardelijst datamodel | K7: concept | L7: 1
A8: 4633f308-1200-5ae5-bbe5-9d28f29abbf1 | B8: TH-07 | C8: kostprijsdekkende huur | E8: TH-06 | F8: 7 | G8: 2026-10-02 | H8: startwaardelijst datamodel | I8: 2026-10-02 | J8: startwaardelijst datamodel | K8: concept | L8: 1 | O8: DUMMY-aanvulling: parent_thema_id
A9: e1ad742d-7ef3-5e44-ac03-70110ec150d0 | B9: TH-08 | C9: BTW en fiscaliteit | F9: 8 | G9: 2026-10-02 | H9: startwaardelijst datamodel | I9: 2026-10-02 | J9: startwaardelijst datamodel | K9: concept | L9: 1
A10: 55604a17-c234-5a0c-bb2a-e06d5c028f49 | B10: TH-09 | C10: reserves | F10: 9 | G10: 2026-10-02 | H10: startwaardelijst datamodel | I10: 2026-10-02 | J10: startwaardelijst datamodel | K10: concept | L10: 1
A11: 34756948-4e30-56db-85f6-aa4a12a42a1a | B11: TH-10 | C11: voorzieningen | E11: TH-09 | F11: 10 | G11: 2026-10-02 | H11: startwaardelijst datamodel | I11: 2026-10-02 | J11: startwaardelijst datamodel | K11: concept | L11: 1 | O11: DUMMY-aanvulling: parent_thema_id
A12: b71abfe9-ae17-53c9-b7f8-fa5d984095a7 | B12: TH-11 | C12: afschrijving | E12: TH-04 | F12: 11 | G12: 2026-10-02 | H12: startwaardelijst datamodel | I12: 2026-10-02 | J12: startwaardelijst datamodel | K12: concept | L12: 1 | O12: DUMMY-aanvulling: parent_thema_id
A13: 98cbc02f-d8b5-571e-bc56-acbc5e81dde8 | B13: TH-12 | C13: circulaire restwaarde | F13: 12 | G13: 2026-10-02 | H13: startwaardelijst datamodel | I13: 2026-10-02 | J13: startwaardelijst datamodel | K13: concept | L13: 1
A14: 7414ab79-8980-53f2-aaeb-c620ed8f7ca7 | B14: TH-13 | C14: maatschappelijke kosten en baten | F14: 13 | G14: 2026-10-02 | H14: startwaardelijst datamodel | I14: 2026-10-02 | J14: startwaardelijst datamodel | K14: concept | L14: 1
A15: 5125fa67-e38d-5fc9-a8e5-bad9e2ca6fdc | B15: TH-14 | C15: financieringsconstructies | F15: 14 | G15: 2026-10-02 | H15: startwaardelijst datamodel | I15: 2026-10-02 | J15: startwaardelijst datamodel | K15: concept | L15: 1
A16: 582b5230-9708-5380-af6e-83606ac74dbc | B16: TH-15 | C16: leningen | E16: TH-14 | F16: 15 | G16: 2026-10-02 | H16: startwaardelijst datamodel | I16: 2026-10-02 | J16: startwaardelijst datamodel | K16: concept | L16: 1 | O16: DUMMY-aanvulling: parent_thema_id
A17: 3ce9196c-22fe-5742-87b4-bf16d2e6434c | B17: TH-16 | C17: borgstellingen en waarborgfondsen | E17: TH-14 | F17: 16 | G17: 2026-10-02 | H17: startwaardelijst datamodel | I17: 2026-10-02 | J17: startwaardelijst datamodel | K17: concept | L17: 1 | O17: DUMMY-aanvulling: parent_thema_id
A18: c665d8e6-87aa-5f60-a722-c2042d12816f | B18: TH-17 | C18: investeringsafweging | F18: 17 | G18: 2026-10-02 | H18: startwaardelijst datamodel | I18: 2026-10-02 | J18: startwaardelijst datamodel | K18: concept | L18: 1
A19: 87d8ebdf-26d1-5165-b2cc-5c840763391f | B19: TH-18 | C19: voorzieningenbeleid | E19: TH-10 | F19: 18 | G19: 2026-10-02 | H19: startwaardelijst datamodel | I19: 2026-10-02 | J19: startwaardelijst datamodel | K19: concept | L19: 1 | O19: DUMMY-aanvulling: parent_thema_id
A20: 94318e78-8bc1-5314-89ce-fcb4e7c6083d | B20: TH-19 | C20: monitoring en verantwoording | F20: 19 | G20: 2026-10-02 | H20: startwaardelijst datamodel | I20: 2026-10-02 | J20: startwaardelijst datamodel | K20: concept | L20: 1

Sheet informatiebehoefte
A1: informatiebehoefte_id | B1: informatie_code | C1: naam | D1: informatietype_id | E1: vraagstelling | F1: omschrijving | G1: vereist_detailniveau | H1: vormvoorkeur | I1: actualiteitseis | J1: kwaliteitseis | K1: verplicht_voor_besluit | L1: vaak_ontbrekend | M1: created_at | N1: created_by | O1: updated_at | P1: updated_by | Q1: record_status | R1: version_number | S1: valid_from | T1: valid_until | U1: notes_internal
A2: c426e4c2-8f2f-5cae-b57a-a85c790e25eb | B2: IB-01 | C2: Beleidskaders en ambities | D2: IT-02 | E2: Is beleidskaders en ambities beschikbaar, actueel en in een bruikbare vorm? | G2: portefeuille | H2: Excel of dashboard | I2: Maximaal 12 maanden oud | K2: ja | L2: nee | M2: 2026-10-03 | N2: dummy-generator | O2: 2026-10-03 | P2: dummy-generator | Q2: concept | R2: 1 | U2: DUMMY
A3: 69cfe2f0-7416-54cd-afed-8df20cb1b519 | B3: IB-02 | C3: Portefeuilleoverzicht met objecten | D3: IT-03 | E3: Is portefeuilleoverzicht met objecten beschikbaar, actueel en in een bruikbare vorm? | G3: portefeuille | H3: Excel of dashboard | I3: Maximaal 12 maanden oud | K3: ja | L3: nee | M3: 2026-10-03 | N3: dummy-generator | O3: 2026-10-03 | P3: dummy-generator | Q3: concept | R3: 1 | U3: DUMMY
A4: 113a43c1-1aa9-59eb-849b-80d9342eb5c7 | B4: IB-03 | C4: Technische staat en onderhoudsopgave per object | D4: IT-05 | E4: Is technische staat en onderhoudsopgave per object beschikbaar, actueel en in een bruikbare vorm? | G4: per object | H4: Excel of dashboard | I4: Maximaal 12 maanden oud | K4: ja | L4: ja | M4: 2026-10-03 | N4: dummy-generator | O4: 2026-10-03 | P4: dummy-generator | Q4: concept | R4: 1 | U4: DUMMY
A5: 407aefc8-401d-54af-a469-22ba1dc63319 | B5: IB-04 | C5: Meerjarenonderhoudsplanning (MJOP) | D5: IT-06 | E5: Is meerjarenonderhoudsplanning (MJOP) beschikbaar, actueel en in een bruikbare vorm? | G5: per object | H5: Excel of dashboard | I5: Maximaal 12 maanden oud | K5: ja | L5: ja | M5: 2026-10-03 | N5: dummy-generator | O5: 2026-10-03 | P5: dummy-generator | Q5: concept | R5: 1 | U5: DUMMY
A6: d6439a52-2a51-554e-bb14-946385063c80 | B6: IB-05 | C6: Energielabels en verbruiksgegevens | D6: IT-07 | E6: Is energielabels en verbruiksgegevens beschikbaar, actueel en in een bruikbare vorm? | G6: portefeuille | H6: Excel of dashboard | I6: Maximaal 12 maanden oud | K6: nee | L6: ja | M6: 2026-10-03 | N6: dummy-generator | O6: 2026-10-03 | P6: dummy-generator | Q6: concept | R6: 1 | U6: DUMMY
A7: e774ed8a-7657-54fc-ad5c-c07f5bd2182b | B7: IB-06 | C7: Investeringsramingen per variant | D7: IT-08 | E7: Is investeringsramingen per variant beschikbaar, actueel en in een bruikbare vorm? | G7: per object | H7: Excel of dashboard | I7: Maximaal 12 maanden oud | K7: ja | L7: nee | M7: 2026-10-03 | N7: dummy-generator | O7: 2026-10-03 | P7: dummy-generator | Q7: concept | R7: 1 | U7: DUMMY
A8: dc86d818-49f5-58b9-9452-a8b85c8aad1d | B8: IB-07 | C8: Exploitatiebegroting en huurinkomsten | D8: IT-09 | E8: Is exploitatiebegroting en huurinkomsten beschikbaar, actueel en in een bruikbare vorm? | G8: per object | H8: Excel of dashboard | I8: Maximaal 12 maanden oud | K8: ja | L8: ja | M8: 2026-10-03 | N8: dummy-generator | O8: 2026-10-03 | P8: dummy-generator | Q8: concept | R8: 1 | U8: DUMMY
A9: 221ef3bb-85f3-58a6-87ef-fd4e6a0041a4 | B9: IB-08 | C9: Beschikbare begrotings- en MIP-ruimte | D9: IT-10 | E9: Is beschikbare begrotings- en MIP-ruimte beschikbaar, actueel en in een bruikbare vorm? | G9: portefeuille | H9: Excel of dashboard | I9: Maximaal 12 maanden oud | K9: ja | L9: nee | M9: 2026-10-03 | N9: dummy-generator | O9: 2026-10-03 | P9: dummy-generator | Q9: concept | R9: 1 | U9: DUMMY
A10: d54beaa9-436c-57f6-9026-162f75105efe | B10: IB-09 | C10: Boekwaarde en afschrijvingstermijnen | D10: IT-11 | E10: Is boekwaarde en afschrijvingstermijnen beschikbaar, actueel en in een bruikbare vorm? | G10: portefeuille | H10: Excel of dashboard | I10: Maximaal 12 maanden oud | K10: ja | L10: nee | M10: 2026-10-03 | N10: dummy-generator | O10: 2026-10-03 | P10: dummy-generator | Q10: concept | R10: 1 | U10: DUMMY
A11: 62491782-ff70-5eab-a686-d5cf5277cb5d | B11: IB-10 | C11: BTW- en fiscale positie | D11: IT-12 | E11: Is bTW- en fiscale positie beschikbaar, actueel en in een bruikbare vorm? | G11: portefeuille | H11: Excel of dashboard | I11: Maximaal 12 maanden oud | K11: nee | L11: ja | M11: 2026-10-03 | N11: dummy-generator | O11: 2026-10-03 | P11: dummy-generator | Q11: concept | R11: 1 | U11: DUMMY
A12: 68e2d9bf-43b9-585f-8014-8cea232ef7a6 | B12: IB-11 | C12: Eigendoms-, huur- en subsidieafspraken | D12: IT-13 | E12: Is eigendoms-, huur- en subsidieafspraken beschikbaar, actueel en in een bruikbare vorm? | G12: portefeuille | H12: Excel of dashboard | I12: Maximaal 12 maanden oud | K12: ja | L12: nee | M12: 2026-10-03 | N12: dummy-generator | O12: 2026-10-03 | P12: dummy-generator | Q12: concept | R12: 1 | U12: DUMMY
A13: 9c52e1ad-5c08-5975-97c1-b3b714b74d5c | B13: IB-12 | C13: Risico's en onzekerheden per variant | D13: IT-14 | E13: Is risico's en onzekerheden per variant beschikbaar, actueel en in een bruikbare vorm? | G13: portefeuille | H13: Excel of dashboard | I13: Maximaal 12 maanden oud | K13: nee | L13: ja | M13: 2026-10-03 | N13: dummy-generator | O13: 2026-10-03 | P13: dummy-generator | Q13: concept | R13: 1 | U13: DUMMY
... A16: 877a2b26-7ef3-50e0-8a3b-972e68bc2334 | B16: IB-15 | C16: Voortgangs- en prestatiegegevens | D16: IT-17 | E16: Is voortgangs- en prestatiegegevens beschikbaar, actueel en in een bruikbare vorm? | G16: portefeuille | H16: Excel of dashboard | I16: Maximaal 12 maanden oud | K16: ja | L16: nee | M16: 2026-10-03 | N16: dummy-generator | O16: 2026-10-03 | P16: dummy-generator | Q16: concept | R16: 1 | U16: DUMMY

Sheet informatietype
A1: informatietype_id | B1: code | C1: naam | D1: omschrijving | E1: sort_order | F1: created_at | G1: created_by | H1: updated_at | I1: updated_by | J1: record_status | K1: version_number | L1: valid_from | M1: valid_until | N1: notes_internal
A2: 2e734fbb-1bd3-5749-8643-5312029c1559 | B2: IT-01 | C2: basiskennis | E2: 1 | F2: 2026-10-02 | G2: startwaardelijst datamodel | H2: 2026-10-02 | I2: startwaardelijst datamodel | J2: concept | K2: 1
A3: 1f36d831-4d6c-5bc5-b44e-fb7722098845 | B3: IT-02 | C3: beleidsinformatie | E3: 2 | F3: 2026-10-02 | G3: startwaardelijst datamodel | H3: 2026-10-02 | I3: startwaardelijst datamodel | J3: concept | K3: 1
A4: d81b30a5-1531-5510-a91c-89a67b055d13 | B4: IT-03 | C4: portefeuilledata | E4: 3 | F4: 2026-10-02 | G4: startwaardelijst datamodel | H4: 2026-10-02 | I4: startwaardelijst datamodel | J4: concept | K4: 1
A5: 06afb507-a9e5-5652-9e06-ca3950a55988 | B5: IT-04 | C5: objectdata | E5: 4 | F5: 2026-10-02 | G5: startwaardelijst datamodel | H5: 2026-10-02 | I5: startwaardelijst datamodel | J5: concept | K5: 1
A6: 704464f8-0341-5bb0-9912-0702f1d3e335 | B6: IT-05 | C6: technische informatie | E6: 5 | F6: 2026-10-02 | G6: startwaardelijst datamodel | H6: 2026-10-02 | I6: startwaardelijst datamodel | J6: concept | K6: 1
A7: ee764348-48c6-5d06-88be-24aa6b287f15 | B7: IT-06 | C7: onderhoudsinformatie | E7: 6 | F7: 2026-10-02 | G7: startwaardelijst datamodel | H7: 2026-10-02 | I7: startwaardelijst datamodel | J7: concept | K7: 1
A8: f48bc6b3-0a37-5e05-abf0-d1ff0ad57ecb | B8: IT-07 | C8: energie- en prestatiegegevens | E8: 7 | F8: 2026-10-02 | G8: startwaardelijst datamodel | H8: 2026-10-02 | I8: startwaardelijst datamodel | J8: concept | K8: 1
A9: 98c7aa97-82ea-5cdd-917b-56d40a20e1b4 | B9: IT-08 | C9: investeringskosten | E9: 8 | F9: 2026-10-02 | G9: startwaardelijst datamodel | H9: 2026-10-02 | I9: startwaardelijst datamodel | J9: concept | K9: 1
A10: 08866568-b381-5d1c-9c51-b54d22fe2304 | B10: IT-09 | C10: exploitatiegegevens | E10: 9 | F10: 2026-10-02 | G10: startwaardelijst datamodel | H10: 2026-10-02 | I10: startwaardelijst datamodel | J10: concept | K10: 1
A11: 0f1272d9-ebd4-56ae-b9a0-5eec21f652cb | B11: IT-10 | C11: begrotingsinformatie | E11: 10 | F11: 2026-10-02 | G11: startwaardelijst datamodel | H11: 2026-10-02 | I11: startwaardelijst datamodel | J11: concept | K11: 1
A12: b978c8ec-9dcf-5a85-9521-dfa1dd2b57a4 | B12: IT-11 | C12: boekhoudkundige informatie | E12: 11 | F12: 2026-10-02 | G12: startwaardelijst datamodel | H12: 2026-10-02 | I12: startwaardelijst datamodel | J12: concept | K12: 1
A13: 358d3dc4-e8a6-5930-8ea3-9564385e81bd | B13: IT-12 | C13: fiscale informatie | E13: 12 | F13: 2026-10-02 | G13: startwaardelijst datamodel | H13: 2026-10-02 | I13: startwaardelijst datamodel | J13: concept | K13: 1
... A19: fbe1ec78-8075-5d8b-a703-eff9354bbfe5 | B19: IT-18 | C19: verantwoordingsinformatie | E19: 18 | F19: 2026-10-02 | G19: startwaardelijst datamodel | H19: 2026-10-02 | I19: startwaardelijst datamodel | J19: concept | K19: 1

Sheet beslisproduct
A1: beslisproduct_id | B1: code | C1: naam | D1: omschrijving | E1: producttype | F1: is_formeel_document | G1: template_instrument_id | H1: created_at | I1: created_by | J1: updated_at | K1: updated_by | L1: record_status | M1: version_number | N1: valid_from | O1: valid_until | P1: notes_internal
A2: 7b6f49bb-e435-549f-a1c0-40d1497e1026 | B2: BP-01 | C2: portefeuilleanalyse | E2: analyse | F2: nee | G2: I-025 | H2: 2026-10-02 | I2: startwaardelijst datamodel | J2: 2026-10-02 | K2: startwaardelijst datamodel | L2: concept | M2: 1 | P2: DUMMY-aanvulling: is_formeel_document, producttype, template_instrument_id
A3: 9218c2c9-9a21-5ec4-ab33-ef6d01069893 | B3: BP-02 | C3: prioriteitenlijst | E3: analyse | F3: nee | H3: 2026-10-02 | I3: startwaardelijst datamodel | J3: 2026-10-02 | K3: startwaardelijst datamodel | L3: concept | M3: 1 | P3: DUMMY-aanvulling: is_formeel_document, producttype
A4: a49d11f9-9a55-5edc-a8e4-84974bda69c0 | B4: BP-03 | C4: scenariovergelijking | E4: analyse | F4: nee | G4: I-024 | H4: 2026-10-02 | I4: startwaardelijst datamodel | J4: 2026-10-02 | K4: startwaardelijst datamodel | L4: concept | M4: 1 | P4: DUMMY-aanvulling: is_formeel_document, producttype, template_instrument_id
A5: d2424690-1901-536d-a059-42f3dc9feeb5 | B5: BP-04 | C5: businesscase | E5: onderbouwing | F5: nee | G5: I-040 | H5: 2026-10-02 | I5: startwaardelijst datamodel | J5: 2026-10-02 | K5: startwaardelijst datamodel | L5: concept | M5: 1 | P5: DUMMY-aanvulling: is_formeel_document, producttype, template_instrument_id
A6: 5ce7020c-b609-5c41-8211-547aa620e2fe | B6: BP-05 | C6: investeringsvoorstel | E6: voorstel | F6: nee | H6: 2026-10-02 | I6: startwaardelijst datamodel | J6: 2026-10-02 | K6: startwaardelijst datamodel | L6: concept | M6: 1 | P6: DUMMY-aanvulling: is_formeel_document, producttype
A7: 2abdd2f5-8cec-56b1-b829-81805ae6e7ac | B7: BP-06 | C7: collegevoorstel | E7: besluitdocument | F7: ja | H7: 2026-10-02 | I7: startwaardelijst datamodel | J7: 2026-10-02 | K7: startwaardelijst datamodel | L7: concept | M7: 1 | P7: DUMMY-aanvulling: is_formeel_document, producttype
A8: 36b71e88-d66a-574b-971d-9360e1559a83 | B8: BP-07 | C8: raadsvoorstel | E8: besluitdocument | F8: ja | H8: 2026-10-02 | I8: startwaardelijst datamodel | J8: 2026-10-02 | K8: startwaardelijst datamodel | L8: concept | M8: 1 | P8: DUMMY-aanvulling: is_formeel_document, producttype
A9: ae123b2a-27ff-592f-9838-6d4ac70165b5 | B9: BP-08 | C9: kredietaanvraag | E9: besluitdocument | F9: ja | H9: 2026-10-02 | I9: startwaardelijst datamodel | J9: 2026-10-02 | K9: startwaardelijst datamodel | L9: concept | M9: 1 | P9: DUMMY-aanvulling: is_formeel_document, producttype
A10: 977b9844-4b4d-504d-8bc9-4065447f2d03 | B10: BP-09 | C10: projectopdracht | E10: opdracht | F10: ja | H10: 2026-10-02 | I10: startwaardelijst datamodel | J10: 2026-10-02 | K10: startwaardelijst datamodel | L10: concept | M10: 1 | P10: DUMMY-aanvulling: is_formeel_document, producttype
A11: 302f2512-d6c5-53fe-ab8b-83ab19eeece1 | B11: BP-10 | C11: exploitatiebegroting | E11: begroting | F11: nee | H11: 2026-10-02 | I11: startwaardelijst datamodel | J11: 2026-10-02 | K11: startwaardelijst datamodel | L11: concept | M11: 1 | P11: DUMMY-aanvulling: is_formeel_document, producttype
A12: a37b7cd3-2463-5558-8123-b02eb50bac76 | B12: BP-11 | C12: subsidieaanvraag | E12: aanvraag | F12: ja | H12: 2026-10-02 | I12: startwaardelijst datamodel | J12: 2026-10-02 | K12: startwaardelijst datamodel | L12: concept | M12: 1 | P12: DUMMY-aanvulling: is_formeel_document, producttype
A13: c4326e6e-58ba-5c57-b87d-a35bf98a973e | B13: BP-12 | C13: aanbestedingsstrategie | E13: strategie | F13: nee | H13: 2026-10-02 | I13: startwaardelijst datamodel | J13: 2026-10-02 | K13: startwaardelijst datamodel | L13: concept | M13: 1 | P13: DUMMY-aanvulling: is_formeel_document, producttype
A14: 95c6da25-ad1d-5096-8857-021194acf1db | B14: BP-13 | C14: opleverdossier | E14: dossier | F14: ja | H14: 2026-10-02 | I14: startwaardelijst datamodel | J14: 2026-10-02 | K14: startwaardelijst datamodel | L14: concept | M14: 1 | P14: DUMMY-aanvulling: is_formeel_document, producttype
A15: d98eb67a-ff6f-5a99-be15-8b9f0a53498d | B15: BP-14 | C15: monitoringsrapportage | E15: rapportage | F15: nee | G15: I-029 | H15: 2026-10-02 | I15: startwaardelijst datamodel | J15: 2026-10-02 | K15: startwaardelijst datamodel | L15: concept | M15: 1 | P15: DUMMY-aanvulling: is_formeel_document, producttype, template_instrument_id
A16: 3220ef3d-e7a8-58b4-8265-d9d78c0a382e | B16: BP-15 | C16: herijkingsvoorstel | E16: voorstel | F16: nee | H16: 2026-10-02 | I16: startwaardelijst datamodel | J16: 2026-10-02 | K16: startwaardelijst datamodel | L16: concept | M16: 1 | P16: DUMMY-aanvulling: is_formeel_document, producttype

Sheet handelingsperspectief
A1: handelingsperspectief_id | B1: code | C1: titel | D1: samenvatting | E1: beschrijving | F1: aanbevolen_actie | G1: verwacht_resultaat | H1: waarschuwing | I1: sort_order | J1: created_at | K1: created_by | L1: updated_at | M1: updated_by | N1: record_status | O1: version_number | P1: valid_from | Q1: valid_until | R1: notes_internal
A2: 4528d86c-8fba-5bf7-b849-ad0e392e65ff | B2: HP-01 | C2: Maak de kosten van niets doen zichtbaar | D2: Reken door wat uitstel kost aan onderhoud, energie en leegstand. | F2: Stel een nulmeting op met de kosten van niets doen per object. | G2: Een startpunt waar varianten mee worden vergeleken | H2: Gebruik actuele onderhoudsdata; verouderde data vertekent het beeld. | I2: 1 | J2: 2026-10-03 | K2: dummy-generator | L2: 2026-10-03 | M2: dummy-generator | N2: concept | O2: 1 | R2: DUMMY
A3: 6505fcb6-23d3-594f-92ac-02bf33e69423 | B3: HP-02 | C3: Stel prioriteiten met een vaste afwegingsmethode | D3: Kies vooraf de criteria waarmee objecten worden gerangschikt. | F3: Leg afwegingscriteria vast en pas ze toe op alle objecten. | G3: Een uitlegbare prioriteitenlijst | H3: Wijzig criteria niet achteraf om een uitkomst te sturen. | I3: 2 | J3: 2026-10-03 | K3: dummy-generator | L3: 2026-10-03 | M3: dummy-generator | N3: concept | O3: 1 | R3: DUMMY
A4: 0d0391d3-4667-5288-b9ea-3c32cf8aa086 | B4: HP-03 | C4: Reken varianten door op levensduurkosten | D4: Vergelijk varianten op totale kosten over de levensduur, niet alleen op investering. | F4: Maak een TCO-vergelijking van minimaal drie varianten. | G4: Een financieel vergelijkbare scenariovergelijking | H4: Neem onderhoud en energie mee in de exploitatie. | I4: 3 | J4: 2026-10-03 | K4: dummy-generator | L4: 2026-10-03 | M4: dummy-generator | N4: concept | O4: 1 | R4: DUMMY
A5: ec5208b3-97d2-5253-8675-626942112705 | B5: HP-04 | C5: Zoek dekking in subsidies en leningen vóór reservering | D5: Inventariseer wat extern beschikbaar is voordat eigen middelen worden gereserveerd. | F5: Controleer subsidies, fondsen en leningen die voor dit object gelden. | G5: Een dekkingsplan met externe middelen | H5: Let op stapelbaarheid en deadlines van rondes. | I5: 4 | J5: 2026-10-03 | K5: dummy-generator | L5: 2026-10-03 | M5: dummy-generator | N5: concept | O5: 1 | R5: DUMMY
A6: add457f6-7bb7-5347-b697-fd96abd9b252 | B6: HP-05 | C6: Leg structurele dekking van kapitaallasten vast | D6: Zorg dat de jaarlijkse lasten na de investering gedekt zijn. | F6: Regel dekking via begroting, huur of reserve voordat het krediet wordt aangevraagd. | G6: Een sluitende meerjarenbegroting | H6: Een financierbaar plan is niet automatisch begrotingshaalbaar. | I6: 5 | J6: 2026-10-03 | K6: dummy-generator | L6: 2026-10-03 | M6: dummy-generator | N6: concept | O6: 1 | R6: DUMMY
A7: 42b94ed9-40b6-5c22-be7b-087e044e669d | B7: HP-06 | C7: Controleer BTW- en fiscale gevolgen voor het besluit | D7: Fiscale gevolgen veranderen de businesscase. | F7: Laat een fiscaal adviseur de BTW-positie toetsen. | G7: Een fiscaal getoetste businesscase | H7: Late fiscale uitkomsten leiden tot herziening van het besluit. | I7: 6 | J7: 2026-10-03 | K7: dummy-generator | L7: 2026-10-03 | M7: dummy-generator | N7: concept | O7: 1 | R7: DUMMY
A8: 63e7f245-3d74-5feb-83e1-77c4f3926652 | B8: HP-07 | C8: Bundel kleine projecten tot een programma | D8: Schaalvoordeel bij inkoop en financiering. | F8: Groepeer vergelijkbare projecten en bepaal een gezamenlijke inkoopstrategie. | G8: Lagere kosten per project | H8: Bundelen vraagt eerst een gedeeld programma van eisen. | I8: 7 | J8: 2026-10-03 | K8: dummy-generator | L8: 2026-10-03 | M8: dummy-generator | N8: concept | O8: 1 | R8: DUMMY
A9: fae6e7cd-cb01-5232-a972-edfdbeb121fd | B9: HP-08 | C9: Organiseer huurafspraken met gebruikers | D9: Kosten en baten komen vaak bij verschillende partijen terecht. | F9: Maak afspraken over huur, onderhoud en energie met de gebruiker. | G9: Een sluitende verdeling van kosten en baten | H9: Split incentive: een positieve businesscase kan per partij negatief zijn. | I9: 8 | J9: 2026-10-03 | K9: dummy-generator | L9: 2026-10-03 | M9: dummy-generator | N9: concept | O9: 1 | R9: DUMMY
A10: 1c9cea93-9ba3-5584-acbe-3364df2eeae3 | B10: HP-09 | C10: Maak monitoring onderdeel van het besluit | D10: Leg vooraf vast hoe prestaties worden gevolgd. | F10: Voeg indicatoren en een meetmoment toe aan het besluit. | G10: Een besluit dat later toetsbaar is | H10: Zonder meetmoment verdwijnt monitoring uit beeld. | I10: 9 | J10: 2026-10-03 | K10: dummy-generator | L10: 2026-10-03 | M10: dummy-generator | N10: concept | O10: 1 | R10: DUMMY
A11: 23db3bc7-a89d-5bc5-8a8f-198dc493221f | B11: HP-10 | C11: Vraag ontzorging aan voor kleine eigenaren | D11: Kleine eigenaren missen vaak capaciteit. | F11: Verwijs naar een ontzorgingsprogramma of adviseur. | G11: Een uitvoerbaar plan voor kleine eigenaren | H11: Ontzorging is niet altijd gratis of landelijk beschikbaar. | I11: 10 | J11: 2026-10-03 | K11: dummy-generator | L11: 2026-10-03 | M11: dummy-generator | N11: concept | O11: 1 | R11: DUMMY

Sheet knelpunt
A1: knelpunt_id | B1: code | C1: naam | D1: omschrijving | E1: knelpunttype | F1: ernst | G1: frequentie | H1: bron_type | I1: is_validated | J1: created_at | K1: created_by | L1: updated_at | M1: updated_by | N1: record_status | O1: version_number | P1: valid_from | Q1: valid_until | R1: notes_internal
A2: 8ee518c2-b99b-5bb5-acf7-4fa4586b3c0e | B2: K-01 | C2: Onderhoudsdata ontbreekt of is verouderd | D2: Objectgegevens zijn niet actueel of niet digitaal beschikbaar. | E2: ontbrekende informatie | F2: hoog | G2: vaak | H2: interview | I2: nee | J2: 2026-10-03 | K2: dummy-generator | L2: 2026-10-03 | M2: dummy-generator | N2: concept | O2: 1 | R2: DUMMY
A3: f1f7f852-a1d2-5c91-8da9-cbb53f24eaf8 | B3: K-02 | C3: Onduidelijk wie eigenaar is van de businesscase | D3: Vastgoed, financiën en beleid wijzen naar elkaar. | E3: onduidelijke verantwoordelijkheid | F3: middel | G3: soms | H3: werksessie | I3: nee | J3: 2026-10-03 | K3: dummy-generator | L3: 2026-10-03 | M3: dummy-generator | N3: concept | O3: 1 | R3: DUMMY
A4: 505677e2-9bab-5324-9553-ec7d50f84294 | B4: K-03 | C4: Informatie loopt vast tussen vastgoed en financiën | D4: Ramingen en exploitatiedata komen laat of in een ander formaat. | E4: overdrachtsprobleem | F4: hoog | G4: vaak | H4: interview | I4: nee | J4: 2026-10-03 | K4: dummy-generator | L4: 2026-10-03 | M4: dummy-generator | N4: concept | O4: 1 | R4: DUMMY
A5: f13a04cc-e076-5412-b5c2-41e3666861d4 | B5: K-04 | C5: Geen instrument voor structurele dekking | D5: Er zijn subsidies en leningen maar weinig middelen voor kapitaallasten. | E5: ontbrekend instrument | F5: hoog | G5: vaak | H5: documentanalyse | I5: nee | J5: 2026-10-03 | K5: dummy-generator | L5: 2026-10-03 | M5: dummy-generator | N5: concept | O5: 1 | R5: DUMMY
A6: 8ee061b9-cf0e-5d3e-b928-e6155dad7b7b | B6: K-05 | C6: Te weinig capaciteit voor subsidieaanvragen | D6: Kleine eigenaren kunnen aanvragen niet bijhouden. | E6: onvoldoende capaciteit | F6: middel | G6: vaak | H6: interview | I6: nee | J6: 2026-10-03 | K6: dummy-generator | L6: 2026-10-03 | M6: dummy-generator | N6: concept | O6: 1 | R6: DUMMY
A7: b497cd72-feb0-5a85-8efd-2d2318722f6d | B7: K-06 | C7: Beslismoment valt buiten de P&C-cyclus | D7: Het besluit komt te laat voor kadernota of begroting. | E7: timing P&C-cyclus | F7: middel | G7: soms | H7: werksessie | I7: nee | J7: 2026-10-03 | K7: dummy-generator | L7: 2026-10-03 | M7: dummy-generator | N7: concept | O7: 1 | R7: DUMMY
A8: 477fcc7d-0ab9-5416-971c-8ac7e6688ac4 | B8: K-07 | C8: BTW-gevolgen pas laat bekend | D8: Fiscale toets vindt pas na het voorkeursbesluit plaats. | E8: fiscale of juridische onzekerheid | F8: middel | G8: soms | H8: interview | I8: nee | J8: 2026-10-03 | K8: dummy-generator | L8: 2026-10-03 | M8: dummy-generator | N8: concept | O8: 1 | R8: DUMMY
A9: 096e0851-6da5-591f-8a64-74bd0497c108 | B9: K-08 | C9: Lokaal mandaat verschilt per gemeente | D9: Wie waarover mag besluiten verschilt per gemeente. | E9: mandaatprobleem | F9: laag | G9: soms | H9: werksessie | I9: nee | J9: 2026-10-03 | K9: dummy-generator | L9: 2026-10-03 | M9: dummy-generator | N9: concept | O9: 1 | R9: DUMMY

Sheet informatieoverdracht
A1: informatieoverdracht_id | B1: beslismoment_id | C1: van_rol_id | D1: naar_rol_id | E1: informatiebehoefte_id | F1: beslisproduct_id | G1: moment_binnen_fase | H1: vereist_formaat | I1: kwaliteitseis | J1: overdrachtsrisico | K1: is_verplicht | L1: created_at | M1: created_by | N1: updated_at | O1: updated_by | P1: record_status | Q1: version_number | R1: valid_from | S1: valid_until | T1: notes_internal
A2: 89ff24fd-4560-5532-8d54-cc0c26f0fe16 | B2: BM-O4-01 | C2: ROL-003 | D2: ROL-011 | E2: IB-06 | F2: BP-05 | G2: Voor de ambtelijke toets | H2: Excel of PDF | I2: Actueel en gecontroleerd door afzender | J2: Data komt laat of in een ander formaat | K2: ja | L2: 2026-10-03 | M2: dummy-generator | N2: 2026-10-03 | O2: dummy-generator | P2: concept | Q2: 1 | T2: DUMMY
A3: 58c3269f-efca-5df5-9218-a0a36231731a | B3: BM-O4-01 | C3: ROL-011 | D3: ROL-012 | E3: IB-07 | F3: BP-03 | G3: Voor de ambtelijke toets | H3: Excel of PDF | I3: Actueel en gecontroleerd door afzender | J3: Data komt laat of in een ander formaat | K3: ja | L3: 2026-10-03 | M3: dummy-generator | N3: 2026-10-03 | O3: dummy-generator | P3: concept | Q3: 1 | T3: DUMMY
A4: c6103cd3-8773-554b-b652-da20b2eb63bd | B4: BM-O4-01 | C4: ROL-015 | D4: ROL-011 | E4: IB-10 | G4: Voor de ambtelijke toets | H4: Excel of PDF | I4: Actueel en gecontroleerd door afzender | J4: Data komt laat of in een ander formaat | K4: ja | L4: 2026-10-03 | M4: dummy-generator | N4: 2026-10-03 | O4: dummy-generator | P4: concept | Q4: 1 | T4: DUMMY
A5: eaca765e-5620-584d-9f1e-f7b7f678e716 | B5: BM-O4-02 | C5: ROL-011 | D5: ROL-017 | E5: IB-14 | F5: BP-06 | G5: Voor de ambtelijke toets | H5: Excel of PDF | I5: Actueel en gecontroleerd door afzender | J5: Data komt laat of in een ander formaat | K5: ja | L5: 2026-10-03 | M5: dummy-generator | N5: 2026-10-03 | O5: dummy-generator | P5: concept | Q5: 1 | T5: DUMMY
A6: 6e66ea78-9bab-5e10-9827-82e4769754f9 | B6: BM-P3-01 | C6: ROL-004 | D6: ROL-002 | E6: IB-03 | F6: BP-01 | G6: Voor de ambtelijke toets | H6: Excel of PDF | I6: Actueel en gecontroleerd door afzender | J6: Data komt laat of in een ander formaat | K6: ja | L6: 2026-10-03 | M6: dummy-generator | N6: 2026-10-03 | O6: dummy-generator | P6: concept | Q6: 1 | T6: DUMMY
A7: 8e51af6b-2ab2-572d-a0a1-b54037d4882c | B7: BM-P2-01 | C7: ROL-006 | D7: ROL-003 | E7: IB-04 | G7: Voor de ambtelijke toets | H7: Excel of PDF | I7: Actueel en gecontroleerd door afzender | J7: Data komt laat of in een ander formaat | K7: ja | L7: 2026-10-03 | M7: dummy-generator | N7: 2026-10-03 | O7: dummy-generator | P7: concept | Q7: 1 | T7: DUMMY
A8: c54af4b7-72bd-5d3c-a6b9-7023b5156d42 | B8: BM-P2-01 | C8: ROL-003 | D8: ROL-008 | E8: IB-02 | F8: BP-01 | G8: Voor de ambtelijke toets | H8: Excel of PDF | I8: Actueel en gecontroleerd door afzender | J8: Data komt laat of in een ander formaat | K8: ja | L8: 2026-10-03 | M8: dummy-generator | N8: 2026-10-03 | O8: dummy-generator | P8: concept | Q8: 1 | T8: DUMMY
A9: e47f3865-2c16-5cad-9dd4-3fcbbdc5ed9e | B9: BM-O5-01 | C9: ROL-005 | D9: ROL-013 | E9: IB-06 | F9: BP-12 | G9: Voor de ambtelijke toets | H9: Excel of PDF | I9: Actueel en gecontroleerd door afzender | J9: Data komt laat of in een ander formaat | K9: ja | L9: 2026-10-03 | M9: dummy-generator | N9: 2026-10-03 | O9: dummy-generator | P9: concept | Q9: 1 | T9: DUMMY
A10: 2d08d5cd-22c1-58d2-aee3-8ac6a6bbcc56 | B10: BM-O6-01 | C10: ROL-006 | D10: ROL-007 | E10: IB-07 | F10: BP-13 | G10: Voor de ambtelijke toets | H10: Excel of PDF | I10: Actueel en gecontroleerd door afzender | J10: Data komt laat of in een ander formaat | K10: ja | L10: 2026-10-03 | M10: dummy-generator | N10: 2026-10-03 | O10: dummy-generator | P10: concept | Q10: 1 | T10: DUMMY
A11: 9b01c507-397c-51a7-9876-860a1fcf3414 | B11: BM-P5-01 | C11: ROL-002 | D11: ROL-008 | E11: IB-15 | F11: BP-14 | G11: Voor de ambtelijke toets | H11: Excel of PDF | I11: Actueel en gecontroleerd door afzender | J11: Data komt laat of in een ander formaat | K11: ja | L11: 2026-10-03 | M11: dummy-generator | N11: 2026-10-03 | O11: dummy-generator | P11: concept | Q11: 1 | T11: DUMMY
A12: 63273341-e969-5a62-905d-bbaf6efe5c73 | B12: BM-P3-02 | C12: ROL-012 | D12: ROL-010 | E12: IB-08 | F12: BP-10 | G12: Voor de ambtelijke toets | H12: Excel of PDF | I12: Actueel en gecontroleerd door afzender | J12: Data komt laat of in een ander formaat | K12: ja | L12: 2026-10-03 | M12: dummy-generator | N12: 2026-10-03 | O12: dummy-generator | P12: concept | Q12: 1 | T12: DUMMY

Sheet instrument
A1: instrument_id | B1: instrument_code | C1: naam_officieel | D1: naam_kort | E1: korte_omschrijving | F1: uitgebreide_omschrijving | G1: primaire_instrumenttype_id | H1: doel | I1: centrale_gebruikersvraag | J1: benodigde_input | K1: beoogde_output | L1: gebruikstoelichting | M1: zelfstandig_bruikbaar | N1: complexiteitsniveau | O1: doorlooptijd_categorie | P1: digitale_vorm_id | Q1: officiele_url | R1: publicatiestatus_id | S1: inhoudelijke_status_id | T1: relevantie_v1 | U1: tonen_in_v1 | V1: reden_niet_tonen | W1: validation_status_id | X1: created_at | Y1: created_by | Z1: updated_at | AA1: updated_by | AB1: record_status | AC1: version_number | AD1: valid_from | AE1: valid_until | AF1: notes_internal
A2: 53917737-f299-5c2a-ad7f-0d6b4221a486 | B2: I-001 | C2: DUMAVA | D2: DUMAVA | E2: Subsidie verduurzaming maatschappelijk vastgoed: 20% bij 1-3 losse maatregelen, 30-40% bij integraal project; ook voor energieadvies en label; aanvragen vóór opdrachtverlening; niet voor wettelijk verplichte maatregelen; stapelbaar tot 100% | F2: Subsidie verduurzaming maatschappelijk vastgoed: 20% bij 1-3 losse maatregelen, 30-40% bij integraal project; ook voor energieadvies en label; aanvragen vóór opdrachtverlening; niet voor wettelijk verplichte maatregelen; stapelbaar tot 100% Dummy-uitbreiding voor het website-prototype; niet gecontroleerd. | G2: ITY-01 | H2: Helpt bij: investering voorbereiden | I2: Welke subsidies zijn beschikbaar? | J2: Projectomschrijving, kosten en eigenaargegevens | K2: Subsidiebeschikking of toekenning | L2: Dummy: lees eerst de bron en controleer actuele voorwaarden. | M2: ja | N2: basis | O2: maanden | P2: DV-01 | R2: PS-04 | S2: IS-01 | T2: hoog | U2: ja | W2: VS-02 | X2: 2026-10-02 | Y2: migratie catalogus v0.1 | Z2: 2026-10-02 | AA2: migratie catalogus v0.1 | AB2: concept | AC2: 1 | AF2: Volgorde van binnenkomst; niet met BOSA voor zelfde maatregel; 2026: budget 405 mln (70% integraal, apart plafond scholen), Wgr-lichamen toegelaten, netcongestie-uitzondering (voorbereid op aardgasvrij volstaat), IB/VPB-plichtig uitgesloten | Actualiteitsdatum v0.1: 2026-09 | DUMMY-aanvulling: benodigde_input, beoogde_output, centrale_gebruikersvraag, complexiteitsniveau, digitale_vorm_id, doel, doorlooptijd_categorie, gebruikstoelichting, publicatiestatus_id, relevantie_v1, tonen_in_v1, uitgebreide_omschrijving
A3: 818d28c2-d14a-5098-a016-bdc067bb47f0 | B3: I-002 | C3: ISDE zakelijk | D3: ISDE zakelijk | E3: Investeringssubsidie warmtepompen en zonneboilers voor zakelijke gebruikers en maatschappelijke instellingen | F3: Investeringssubsidie warmtepompen en zonneboilers voor zakelijke gebruikers en maatschappelijke instellingen Dummy-uitbreiding voor het website-prototype; niet gecontroleerd. | G3: ITY-01 | H3: Helpt bij: investering voorbereiden | I3: Welke subsidies zijn beschikbaar? | J3: Projectomschrijving, kosten en eigenaargegevens | K3: Subsidiebeschikking of toekenning | L3: Dummy: lees eerst de bron en controleer actuele voorwaarden. | M3: ja | N3: basis | O3: maanden | P3: DV-01 | R3: PS-02 | S3: IS-01 | T3: hoog | U3: ja | W3: VS-02 | X3: 2026-10-02 | Y3: migratie catalogus v0.1 | Z3: 2026-10-02 | AA3: migratie catalogus v0.1 | AB3: concept | AC3: 1 | AF3: Actualiteitsdatum v0.1: 2026-09 | DUMMY-aanvulling: benodigde_input, beoogde_output, centrale_gebruikersvraag, complexiteitsniveau, digitale_vorm_id, doel, doorlooptijd_categorie, gebruikstoelichting, publicatiestatus_id, relevantie_v1, tonen_in_v1, uitgebreide_omschrijving
A4: 40b3f423-9bf0-5393-a4a2-a031d3342a00 | B4: I-003 | C4: SDE++ | D4: SDE++ | E4: Exploitatiesubsidie grootschalige duurzame opwek (m.n. zon op dak) | F4: Exploitatiesubsidie grootschalige duurzame opwek (m.n. zon op dak) Dummy-uitbreiding voor het website-prototype; niet gecontroleerd. | G4: ITY-01 | H4: Helpt bij: investering voorbereiden | I4: Welke subsidies zijn beschikbaar? | J4: Projectomschrijving, kosten en eigenaargegevens | K4: Subsidiebeschikking of toekenning | L4: Dummy: lees eerst de bron en controleer actuele voorwaarden. | M4: nee | N4: gemiddeld | O4: maanden | P4: DV-01 | R4: PS-02 | S4: IS-01 | T4: hoog | U4: ja | W4: VS-02 | X4: 2026-10-02 | Y4: migratie catalogus v0.1 | Z4: 2026-10-02 | AA4: migratie catalogus v0.1 | AB4: concept | AC4: 1 | AF4: Netcongestie meewegen | Actualiteitsdatum v0.1: 2026-09 | DUMMY-aanvulling: benodigde_input, beoogde_output, centrale_gebruikersvraag, complexiteitsniveau, digitale_vorm_id, doel, doorlooptijd_categorie, gebruikstoelichting, publicatiestatus_id, relevantie_v1, tonen_in_v1, uitgebreide_omschrijving
A5: 231b26d3-de95-532a-b596-ea3518b8143c | B5: I-004 | C5: EIA / MIA-Vamil | D5: EIA / MIA-Vamil | E5: Fiscale aftrek energie- en milieu-investeringen; alleen bij winstbelastingplicht | F5: Fiscale aftrek energie- en milieu-investeringen; alleen bij winstbelastingplicht Dummy-uitbreiding voor het website-prototype; niet gecontroleerd. | G5: ITY-05 | H5: Helpt bij: investering voorbereiden | I5: Welke fiscale gevolgen zijn er? | J5: Investeringsgegevens en fiscale status | K5: Fiscaal voordeel in de aangifte | L5: Dummy: lees eerst de bron en controleer actuele voorwaarden. | M5: nee | N5: gemiddeld | O5: weken | P5: DV-01 | R5: PS-02 | S5: IS-01 | T5: middel | U5: ja | W5: VS-02 | X5: 2026-10-02 | Y5: migratie catalogus v0.1 | Z5: 2026-10-02 | AA5: migratie catalogus v0.1 | AB5: concept | AC5: 1 | AF5: Niet voor gemeenten/meeste stichtingen; wel exploitatie-BV's | Actualiteitsdatum v0.1: 2026-09 | DUMMY-aanvulling: benodigde_input, beoogde_output, centrale_gebruikersvraag, complexiteitsniveau, digitale_vorm_id, doel, doorlooptijd_categorie, gebruikstoelichting, publicatiestatus_id, relevantie_v1, tonen_in_v1, uitgebreide_omschrijving
A6: 727952b5-e058-5e2e-aa69-59cfda2bb5ed | B6: I-005 | C6: BOSA | D6: BOSA | E6: Subsidie bouw en onderhoud sportaccommodaties voor amateursport; verduurzaming bestaande accommodaties loopt via DUMAVA | F6: Subsidie bouw en onderhoud sportaccommodaties voor amateursport; verduurzaming bestaande accommodaties loopt via DUMAVA Dummy-uitbreiding voor het website-prototype; niet gecontroleerd. | G6: ITY-01 | H6: Helpt bij: investering voorbereiden | I6: Welke subsidies zijn beschikbaar? | J6: Projectomschrijving, kosten en eigenaargegevens | K6: Subsidiebeschikking of toekenning | L6: Dummy: lees eerst de bron en controleer actuele voorwaarden. | M6: ja | N6: basis | O6: maanden | P6: DV-01 | R6: PS-04 | S6: IS-01 | T6: middel | U6: ja | W6: VS-02 | X6: 2026-10-02 | Y6: migratie catalogus v0.1 | Z6: 2026-10-02 | AA6: migratie catalogus v0.1 | AB6: concept | AC6: 1 | AF6: Niet combineren met SPUK voor zelfde accommodatie | Actualiteitsdatum v0.1: 2026-09 | DUMMY-aanvulling: benodigde_input, beoogde_output, centrale_gebruikersvraag, complexiteitsniveau, digitale_vorm_id, doel, doorlooptijd_categorie, gebruikstoelichting, publicatiestatus_id, relevantie_v1, tonen_in_v1, uitgebreide_omschrijving
A7: e5b10513-764f-50b1-a4f5-82461c128590 | B7: I-006 | C7: SPUK stimulering sport | D7: SPUK stimulering sport | E7: Specifieke uitkering voor gemeentelijke sportbedrijven (bouw, onderhoud, exploitatie) | F7: Specifieke uitkering voor gemeentelijke sportbedrijven (bouw, onderhoud, exploitatie) Dummy-uitbreiding voor het website-prototype; niet gecontroleerd. | G7: ITY-01 | H7: Helpt bij: uitvoeringsprogramma opstellen | I7: Welke subsidies zijn beschikbaar? | J7: Projectomschrijving, kosten en eigenaargegevens | K7: Subsidiebeschikking of toekenning | L7: Dummy: lees eerst de bron en controleer actuele voorwaarden. | M7: ja | N7: basis | O7: maanden | P7: DV-01 | R7: PS-01 | S7: IS-02 | T7: middel | U7: ja | W7: VS-02 | X7: 2026-10-02 | Y7: migratie catalogus v0.1 | Z7: 2026-10-02 | AA7: migratie catalogus v0.1 | AB7: concept | AC7: 1 | AF7: Niet samen met BOSA voor zelfde accommodatie | Actualiteitsdatum v0.1: 2026-09 | DUMMY-aanvulling: benodigde_input, beoogde_output, centrale_gebruikersvraag, complexiteitsniveau, digitale_vorm_id, doel, doorlooptijd_categorie, gebruikstoelichting, publicatiestatus_id, relevantie_v1, tonen_in_v1, uitgebreide_omschrijving
A8: f5e9f9b9-aa10-58ea-b3ad-01cc9943eb4c | B8: I-007 | C8: SIM | D8: SIM | E8: Instandhoudingssubsidie rijksmonumenten | F8: Instandhoudingssubsidie rijksmonumenten Dummy-uitbreiding voor het website-prototype; niet gecontroleerd. | G8: ITY-01 | H8: Helpt bij: investering voorbereiden | I8: Welke subsidies zijn beschikbaar? | J8: Projectomschrijving, kosten en eigenaargegevens | K8: Subsidiebeschikking of toekenning | L8: Dummy: lees eerst de bron en controleer actuele voorwaarden. | M8: nee | N8: gemiddeld | O8: maanden | P8: DV-01 | R8: PS-02 | S8: IS-01 | T8: hoog | U8: ja | W8: VS-02 | X8: 2026-10-02 | Y8: migratie catalogus v0.1 | Z8: 2026-10-02 | AA8: migratie catalogus v0.1 | AB8: concept | AC8: 1 | AF8: Actualiteitsdatum v0.1: 2026-09 | DUMMY-aanvulling: benodigde_input, beoogde_output, centrale_gebruikersvraag, complexiteitsniveau, digitale_vorm_id, doel, doorlooptijd_categorie, gebruikstoelichting, publicatiestatus_id, relevantie_v1, tonen_in_v1, uitgebreide_omschrijving
A9: 4fa5861c-ba81-5bc2-902a-e95ec8b64e86 | B9: I-008 | C9: Provinciaal ontzorgingsprogramma | D9: Provinciaal ontzorgingsprogramma | E9: Kosteloos advies en begeleiding voor kleine maatschappelijk vastgoedeigenaren en gemeenten tot 50.000 inwoners; advies bruikbaar als onderlegger DUMAVA | F9: Kosteloos advies en begeleiding voor kleine maatschappelijk vastgoedeigenaren en gemeenten tot 50.000 inwoners; advies bruikbaar als onderlegger DUMAVA Dummy-uitbreiding voor het website-prototype; niet gecontroleerd. | G9: ITY-30 | H9: Helpt bij: strategie herijken | I9: Wat is de totale investeringsbehoefte? | J9: Intake en objectgegevens | K9: Advies of uitvoeringsondersteuning | L9: Dummy: lees eerst de bron en controleer actuele voorwaarden. | M9: ja | N9: specialistisch | O9: weken | P9: DV-12 | R9: PS-02 | S9: IS-01 | T9: hoog | U9: ja | W9: VS-02 | X9: 2026-10-02 | Y9: migratie catalogus v0.1 | Z9: 2026-10-02 | AA9: migratie catalogus v0.1 | AB9: concept | AC9: 1 | AF9: Actualiteitsdatum v0.1: 2026-09 | DUMMY-aanvulling: benodigde_input, beoogde_output, centrale_gebruikersvraag, complexiteitsniveau, digitale_vorm_id, doel, doorlooptijd_categorie, gebruikstoelichting, publicatiestatus_id, relevantie_v1, tonen_in_v1, uitgebreide_omschrijving
A10: ce057252-d645-5a30-9ed4-db7e0d19c3bc | B10: I-009 | C10: BNG reguliere financiering | D10: BNG reguliere financiering | E10: Leningen aan decentrale overheden en instellingen, gekoppeld aan SDG's 3, 4, 7 en 11 | F10: Leningen aan decentrale overheden en instellingen, gekoppeld aan SDG's 3, 4, 7 en 11 Dummy-uitbreiding voor het website-prototype; niet gecontroleerd. | G10: ITY-02 | H10: Helpt bij: uitvoeringsprogramma opstellen | I10: Welke financieringsconstructie past? | J10: Investeringsbedrag, kasstroom en zekerheden | K10: Financieringsaanbod | L10: Dummy: lees eerst de bron en controleer actuele voorwaarden. | M10: nee | N10: gemiddeld | O10: weken | P10: DV-01 | R10: PS-04 | S10: IS-01 | T10: hoog | U10: ja | W10: VS-02 | X10: 2026-10-02 | Y10: migratie catalogus v0.1 | Z10: 2026-10-02 | AA10: migratie catalogus v0.1 | AB10: concept | AC10: 1 | AF10: Actualiteitsdatum v0.1: 2026-09 | DUMMY-aanvulling: benodigde_input, beoogde_output, centrale_gebruikersvraag, complexiteitsniveau, digitale_vorm_id, doel, doorlooptijd_categorie, gebruikstoelichting, primaire_instrumenttype_id, publicatiestatus_id, relevantie_v1, tonen_in_v1, uitgebreide_omschrijving
A11: 1e7453cb-3224-5cdf-8983-7a9ee90539a4 | B11: I-010 | C11: BNG Duurzaamheidsfonds | D11: BNG Duurzaamheidsfonds | E11: Leningen aan zakelijke initiatiefnemers voor projecten die bijdragen aan gemeentelijke duurzaamheidsdoelen | F11: Leningen aan zakelijke initiatiefnemers voor projecten die bijdragen aan gemeentelijke duurzaamheidsdoelen Dummy-uitbreiding voor het website-prototype; niet gecontroleerd. | G11: ITY-02 | H11: Helpt bij: investering voorbereiden | I11: Welke financieringsconstructie past? | J11: Investeringsbedrag, kasstroom en zekerheden | K11: Financieringsaanbod | L11: Dummy: lees eerst de bron en controleer actuele voorwaarden. | M11: nee | N11: gemiddeld | O11: weken | P11: DV-01 | R11: PS-02 | S11: IS-01 | T11: middel | U11: ja | W11: VS-02 | X11: 2026-10-02 | Y11: migratie catalogus v0.1 | Z11: 2026-10-02 | AA11: migratie catalogus v0.1 | AB11: concept | AC11: 1 | AF11: Actualiteitsdatum v0.1: 2026-09 | DUMMY-aanvulling: benodigde_input, beoogde_output, centrale_gebruikersvraag, complexiteitsniveau, digitale_vorm_id, doel, doorlooptijd_categorie, gebruikstoelichting, primaire_instrumenttype_id, publicatiestatus_id, relevantie_v1, tonen_in_v1, uitgebreide_omschrijving
A12: 2f69cd32-7644-5cb8-b94c-9c1073af6913 | B12: I-011 | C12: BNG Maatschappelijk Vastgoed Scan | D12: BNG Maatschappelijk Vastgoed Scan | E12: Scan van gemeentelijk vastgoed: labels, maatregelen per gebouw, investering, terugverdientijd, CO2-reductie | F12: Scan van gemeentelijk vastgoed: labels, maatregelen per gebouw, investering, terugverdientijd, CO2-reductie Dummy-uitbreiding voor het website-prototype; niet gecontroleerd. | G12: ITY-15 | H12: Helpt bij: verduurzamingsopgave bepalen | I12: Welke subsidies zijn beschikbaar? | J12: Basisgegevens object | K12: Indicatief resultaat na invoer | L12: Dummy: lees eerst de bron en controleer actuele voorwaarden. | M12: nee | N12: gemiddeld | O12: direct | P12: DV-08 | R12: PS-01 | S12: IS-02 | T12: middel | U12: ja | W12: VS-02 | X12: 2026-10-02 | Y12: migratie catalogus v0.1 | Z12: 2026-10-02 | AA12: migratie catalogus v0.1 | AB12: concept | AC12: 1 | AF12: Actualiteitsdatum v0.1: 2026-09 | DUMMY-aanvulling: benodigde_input, beoogde_output, centrale_gebruikersvraag, complexiteitsniveau, digitale_vorm_id, doel, doorlooptijd_categorie, gebruikstoelichting, primaire_instrumenttype_id, publicatiestatus_id, relevantie_v1, tonen_in_v1, uitgebreide_omschrijving
A13: 7671e620-9ee5-5684-be49-fe448ee0cdf3 | B13: I-012 | C13: Waarborgfonds Sport (SWS) | D13: Waarborgfonds Sport (SWS) | E13: Borgstelling voor leningen van sportverenigingen | F13: Borgstelling voor leningen van sportverenigingen Dummy-uitbreiding voor het website-prototype; niet gecontroleerd. | G13: ITY-03 | H13: Helpt bij: investering voorbereiden | I13: Welke financieringsconstructie past? | J13: Financieringsaanvraag en jaarcijfers | K13: Borgstelling of garantie | L13: Dummy: lees eerst de bron en controleer actuele voorwaarden. | M13: ja | N13: basis | O13: weken | P13: DV-01 | R13: PS-02 | S13: IS-01 | T13: middel | U13: ja | W13: VS-02 | X13: 2026-10-02 | Y13: migratie catalogus v0.1 | Z13: 2026-10-02 | AA13: migratie catalogus v0.1 | AB13: concept | AC13: 1 | AF13: Actualiteitsdatum v0.1: 2026-09 | DUMMY-aanvulling: benodigde_input, beoogde_output, centrale_gebruikersvraag, complexiteitsniveau, digitale_vorm_id, doel, doorlooptijd_categorie, gebruikstoelichting, primaire_instrumenttype_id, publicatiestatus_id, relevantie_v1, tonen_in_v1, uitgebreide_omschrijving
... A21: a606340f-c817-5f52-9e24-2865a2862ac2 | B21: I-020 | C21: Reserve dekking kapitaallasten / voorziening groot onderhoud | D21: Reserve dekking kapitaallasten / voorziening groot onderhoud | E21: Keuze reserve vs voorziening; voeding en onttrekking via financiële verordening; voorziening vereist actueel beheerplan | F21: Keuze reserve vs voorziening; voeding en onttrekking via financiële verordening; voorziening vereist actueel beheerplan Dummy-uitbreiding voor het website-prototype; niet gecontroleerd. | G21: ITY-11 | H21: Helpt bij: portefeuille prioriteren | I21: Welke structurele lasten ontstaan? | J21: Boekwaarde, afschrijvingstermijn, begrotingsruimte | K21: Dekking in begroting of exploitatie | L21: Dummy: lees eerst de bron en controleer actuele voorwaarden. | M21: nee | N21: gemiddeld | O21: weken | P21: DV-04 | R21: PS-02 | S21: IS-01 | T21: hoog | U21: ja | W21: VS-02 | X21: 2026-10-02 | Y21: migratie catalogus v0.1 | Z21: 2026-10-02 | AA21: migratie catalogus v0.1 | AB21: concept | AC21: 1 | AF21: Voorbeeld Haarlemmermeer: reserve gevoed uit verkoopopbrengsten | Actualiteitsdatum v0.1: 2026-09 | DUMMY-aanvulling: benodigde_input, beoogde_output, centrale_gebruikersvraag, complexiteitsniveau, digitale_vorm_id, doel, doorlooptijd_categorie, gebruikstoelichting, publicatiestatus_id, relevantie_v1, tonen_in_v1, uitgebreide_omschrijving
A22: 0c9edc33-1044-5cc0-9033-578f03f54d54 | B22: I-021 | C22: Kostprijsdekkende huur (KPD) | D22: Kostprijsdekkende huur (KPD) | E22: Huur die alle eigenaarlasten dekt; varianten en ingroeipad; doorwerking naar subsidies sociaal domein (indexatiekloof) | F22: Huur die alle eigenaarlasten dekt; varianten en ingroeipad; doorwerking naar subsidies sociaal domein (indexatiekloof) Dummy-uitbreiding voor het website-prototype; niet gecontroleerd. | G22: ITY-11 | H22: Helpt bij: portefeuille prioriteren | I22: Welke structurele lasten ontstaan? | J22: Boekwaarde, afschrijvingstermijn, begrotingsruimte | K22: Dekking in begroting of exploitatie | L22: Dummy: lees eerst de bron en controleer actuele voorwaarden. | M22: nee | N22: gemiddeld | O22: weken | P22: DV-04 | R22: PS-01 | S22: IS-03 | T22: laag | U22: nee | V22: Dummy: instrument nog in ontwikkeling | W22: VS-02 | X22: 2026-10-02 | Y22: migratie catalogus v0.1 | Z22: 2026-10-02 | AA22: migratie catalogus v0.1 | AB22: concept | AC22: 1 | AF22: Prioritair hiaat projectplan | Actualiteitsdatum v0.1: 2026-09 | DUMMY-aanvulling: benodigde_input, beoogde_output, centrale_gebruikersvraag, complexiteitsniveau, digitale_vorm_id, doel, doorlooptijd_categorie, gebruikstoelichting, publicatiestatus_id, reden_niet_tonen, relevantie_v1, tonen_in_v1, uitgebreide_omschrijving
A23: 73a3f140-a5db-501d-98ac-500c907e0d89 | B23: I-022 | C23: Split naar shared incentive | D23: Split naar shared incentive | E23: Kosten en baten eigenaar-huurder gezamenlijk in kaart; langere huurperiode = lagere huurverhoging; allonges | F23: Kosten en baten eigenaar-huurder gezamenlijk in kaart; langere huurperiode = lagere huurverhoging; allonges Dummy-uitbreiding voor het website-prototype; niet gecontroleerd. | G23: ITY-11 | H23: Helpt bij: investering voorbereiden | I23: Welke structurele lasten ontstaan? | J23: Boekwaarde, afschrijvingstermijn, begrotingsruimte | K23: Dekking in begroting of exploitatie | L23: Dummy: lees eerst de bron en controleer actuele voorwaarden. | M23: ja | N23: basis | O23: weken | P23: DV-04 | R23: PS-02 | S23: IS-01 | T23: hoog | U23: ja | W23: VS-02 | X23: 2026-10-02 | Y23: migratie catalogus v0.1 | Z23: 2026-10-02 | AA23: migratie catalogus v0.1 | AB23: concept | AC23: 1 | AF23: Actualiteitsdatum v0.1: 2026-09 | DUMMY-aanvulling: benodigde_input, beoogde_output, centrale_gebruikersvraag, complexiteitsniveau, digitale_vorm_id, doel, doorlooptijd_categorie, gebruikstoelichting, publicatiestatus_id, relevantie_v1, tonen_in_v1, uitgebreide_omschrijving
A24: 5edc3fdd-bc8c-5532-85de-83a68ff78673 | B24: I-023 | C24: CO2-reductiemethode | D24: CO2-reductiemethode | E24: Investeringen onder 875 euro per vermeden ton CO2 gelden als maatschappelijk verantwoord; alternatief voor terugverdientijd | F24: Investeringen onder 875 euro per vermeden ton CO2 gelden als maatschappelijk verantwoord; alternatief voor terugverdientijd Dummy-uitbreiding voor het website-prototype; niet gecontroleerd. | G24: ITY-16 | H24: Helpt bij: portefeuille prioriteren | I24: Welke scenario’s zijn financieel vergelijkbaar? | J24: Varianten met kosten en effecten | K24: Onderbouwde keuze tussen varianten | L24: Dummy: lees eerst de bron en controleer actuele voorwaarden. | M24: ja | N24: basis | O24: dagen | P24: DV-04 | R24: PS-02 | S24: IS-01 | T24: hoog | U24: ja | W24: VS-02 | X24: 2026-10-02 | Y24: migratie catalogus v0.1 | Z24: 2026-10-02 | AA24: migratie catalogus v0.1 | AB24: concept | AC24: 1 | AF24: Actualiteitsdatum v0.1: 2026-09 | DUMMY-aanvulling: benodigde_input, beoogde_output, centrale_gebruikersvraag, complexiteitsniveau, digitale_vorm_id, doel, doorlooptijd_categorie, gebruikstoelichting, primaire_instrumenttype_id, publicatiestatus_id, relevantie_v1, tonen_in_v1, uitgebreide_omschrijving
A25: 4ee0562c-469d-571e-b3bc-01ad3eac023c | B25: I-024 | C25: MKBA / scenariovergelijking | D25: MKBA / scenariovergelijking | E25: Maatschappelijke kosten-batenanalyse of scenario's doorrekenen als besluitonderlegger | F25: Maatschappelijke kosten-batenanalyse of scenario's doorrekenen als besluitonderlegger Dummy-uitbreiding voor het website-prototype; niet gecontroleerd. | G25: ITY-16 | H25: Helpt bij: portefeuille prioriteren | I25: Welke scenario’s zijn financieel vergelijkbaar? | J25: Varianten met kosten en effecten | K25: Onderbouwde keuze tussen varianten | L25: Dummy: lees eerst de bron en controleer actuele voorwaarden. | M25: nee | N25: gemiddeld | O25: dagen | P25: DV-04 | R25: PS-01 | S25: IS-03 | T25: laag | U25: nee | V25: Dummy: instrument nog in ontwikkeling | W25: VS-02 | X25: 2026-10-02 | Y25: migratie catalogus v0.1 | Z25: 2026-10-02 | AA25: migratie catalogus v0.1 | AB25: concept | AC25: 1 | AF25: Route uitwerken | Actualiteitsdatum v0.1: 2026-09 | DUMMY-aanvulling: benodigde_input, beoogde_output, centrale_gebruikersvraag, complexiteitsniveau, digitale_vorm_id, doel, doorlooptijd_categorie, gebruikstoelichting, primaire_instrumenttype_id, publicatiestatus_id, reden_niet_tonen, relevantie_v1, tonen_in_v1, uitgebreide_omschrijving
A26: 5a2ae9cf-9a19-5df8-8b65-3fac7683c685 | B26: I-025 | C26: VNG Rekenmodel Verduurzaming MV 2.0 | D26: VNG Rekenmodel Verduurzaming MV 2.0 | E26: Doorrekening portefeuille: invoer m2 per functie, afschrijvingstermijnen, rente, vernieuwingsgraad, monumentaal %, circulariteitsopslag; output totale investering en opbouw kapitaallasten | F26: Doorrekening portefeuille: invoer m2 per functie, afschrijvingstermijnen, rente, vernieuwingsgraad, monumentaal %, circulariteitsopslag; output totale investering en opbouw kapitaallasten Dummy-uitbreiding voor het website-prototype; niet gecontroleerd. | G26: ITY-14 | H26: Helpt bij: portefeuille prioriteren | I26: Wat kost niets doen? | J26: Kosten, levensduur en exploitatiegegevens | K26: Doorrekening van varianten | L26: Dummy: lees eerst de bron en controleer actuele voorwaarden. | M26: ja | N26: basis | O26: dagen | P26: DV-03 | R26: PS-01 | S26: IS-02 | T26: middel | U26: ja | W26: VS-02 | X26: 2026-10-02 | Y26: migratie catalogus v0.1 | Z26: 2026-10-02 | AA26: migratie catalogus v0.1 | AB26: concept | AC26: 1 | AF26: Versie checken bij VNG | Actualiteitsdatum v0.1: 2026-09 | DUMMY-aanvulling: benodigde_input, beoogde_output, centrale_gebruikersvraag, complexiteitsniveau, digitale_vorm_id, doel, doorlooptijd_categorie, gebruikstoelichting, primaire_instrumenttype_id, publicatiestatus_id, relevantie_v1, tonen_in_v1, uitgebreide_omschrijving
A27: b94247f2-b259-5d1c-9ef6-6f659122fa5b | B27: I-026 | C27: RVO Wegwijzer financiering | D27: RVO Wegwijzer financiering | E27: Per type maatschappelijk vastgoed een stappenplan voor de financieringsroute en subsidies | F27: Per type maatschappelijk vastgoed een stappenplan voor de financieringsroute en subsidies Dummy-uitbreiding voor het website-prototype; niet gecontroleerd. | G27: ITY-24 | H27: Helpt bij: investering voorbereiden | I27: Wat kost niets doen? | J27: Geen | K27: Inzicht en werkwijze | L27: Dummy: lees eerst de bron en controleer actuele voorwaarden. | M27: ja | N27: basis | O27: direct | P27: DV-04 | R27: PS-02 | S27: IS-01 | T27: hoog | U27: ja | W27: VS-02 | X27: 2026-10-02 | Y27: migratie catalogus v0.1 | Z27: 2026-10-02 | AA27: migratie catalogus v0.1 | AB27: concept | AC27: 1 | AF27: Actualiteitsdatum v0.1: 2026-09 | DUMMY-aanvulling: benodigde_input, beoogde_output, centrale_gebruikersvraag, complexiteitsniveau, digitale_vorm_id, doel, doorlooptijd_categorie, gebruikstoelichting, primaire_instrumenttype_id, publicatiestatus_id, relevantie_v1, tonen_in_v1, uitgebreide_omschrijving
A28: 8031cb7f-7dd0-5d13-bd9c-9d2e6663670b | B28: I-027 | C28: RVO Subsidie- en financieringswijzer | D28: RVO Subsidie- en financieringswijzer | E28: Filtertool voor beschikbare regelingen per organisatie- en vastgoedtype | F28: Filtertool voor beschikbare regelingen per organisatie- en vastgoedtype Dummy-uitbreiding voor het website-prototype; niet gecontroleerd. | G28: ITY-15 | H28: Helpt bij: investering voorbereiden | I28: Welke subsidies zijn beschikbaar? | J28: Basisgegevens object | K28: Indicatief resultaat na invoer | L28: Dummy: lees eerst de bron en controleer actuele voorwaarden. | M28: ja | N28: basis | O28: direct | P28: DV-08 | R28: PS-02 | S28: IS-01 | T28: hoog | U28: ja | W28: VS-02 | X28: 2026-10-02 | Y28: migratie catalogus v0.1 | Z28: 2026-10-02 | AA28: migratie catalogus v0.1 | AB28: concept | AC28: 1 | AF28: Functioneel de dichtstbijzijnde bestaande 'kompas'-voorloper | Actualiteitsdatum v0.1: 2026-09 | DUMMY-aanvulling: benodigde_input, beoogde_output, centrale_gebruikersvraag, complexiteitsniveau, digitale_vorm_id, doel, doorlooptijd_categorie, gebruikstoelichting, primaire_instrumenttype_id, publicatiestatus_id, relevantie_v1, tonen_in_v1, uitgebreide_omschrijving
A29: 8d32aa9c-213e-55aa-ba33-65e835863920 | B29: I-028 | C29: Regeling Groenprojecten | D29: Regeling Groenprojecten | E29: Groenverklaring geeft rentekorting via groenbanken; fiscaal voordeel groen beleggen wordt afgebouwd richting 2027 | F29: Groenverklaring geeft rentekorting via groenbanken; fiscaal voordeel groen beleggen wordt afgebouwd richting 2027 Dummy-uitbreiding voor het website-prototype; niet gecontroleerd. | G29: ITY-02 | H29: Helpt bij: investering voorbereiden | I29: Welke financieringsconstructie past? | J29: Investeringsbedrag, kasstroom en zekerheden | K29: Financieringsaanbod | L29: Dummy: lees eerst de bron en controleer actuele voorwaarden. | M29: nee | N29: gemiddeld | O29: weken | P29: DV-01 | R29: PS-01 | S29: IS-02 | T29: middel | U29: ja | W29: VS-02 | X29: 2026-10-02 | Y29: migratie catalogus v0.1 | Z29: 2026-10-02 | AA29: migratie catalogus v0.1 | AB29: concept | AC29: 1 | AF29: Actualiteitsdatum v0.1: 2026-09 | DUMMY-aanvulling: benodigde_input, beoogde_output, centrale_gebruikersvraag, complexiteitsniveau, digitale_vorm_id, doel, doorlooptijd_categorie, gebruikstoelichting, primaire_instrumenttype_id, publicatiestatus_id, relevantie_v1, tonen_in_v1, uitgebreide_omschrijving
A30: 9e55809b-a0ec-5175-8e57-da2567157305 | B30: I-029 | C30: Paragraaf vastgoed / Meerjarenperspectief Vastgoed | D30: Paragraaf vastgoed / Meerjarenperspectief Vastgoed | E30: Transparante presentatie kosten, baten en beleidsbijdrage van vastgoed in begroting en jaarrekening; raadsinstrument | F30: Transparante presentatie kosten, baten en beleidsbijdrage van vastgoed in begroting en jaarrekening; raadsinstrument Dummy-uitbreiding voor het website-prototype; niet gecontroleerd. | G30: ITY-23 | H30: Helpt bij: prestaties monitoren | I30: Hoe landt de investering in begroting en MIP? | J30: Beleids- en portefeuillegegevens | K30: Ingevuld format | L30: Dummy: lees eerst de bron en controleer actuele voorwaarden. | M30: ja | N30: basis | O30: dagen | P30: DV-05 | R30: PS-04 | S30: IS-01 | T30: hoog | U30: ja | W30: VS-02 | X30: 2026-10-02 | Y30: migratie catalogus v0.1 | Z30: 2026-10-02 | AA30: migratie catalogus v0.1 | AB30: concept | AC30: 1 | AF30: Actualiteitsdatum v0.1: 2026-09 | DUMMY-aanvulling: benodigde_input, beoogde_output, centrale_gebruikersvraag, complexiteitsniveau, digitale_vorm_id, doel, doorlooptijd_categorie, gebruikstoelichting, primaire_instrumenttype_id, publicatiestatus_id, relevantie_v1, tonen_in_v1, uitgebreide_omschrijving
A31: 3701b66e-4173-5925-bc35-a5ffe5851e3c | B31: I-030 | C31: EED-rapportageplicht | D31: EED-rapportageplicht | E31: Jaarlijkse energierapportage + 4-jaarlijkse maatregelenrapportage; gefaseerd: >50.000 inw. 2025, 5.000-50.000 in 2027, <5.000 in 2030 | F31: Jaarlijkse energierapportage + 4-jaarlijkse maatregelenrapportage; gefaseerd: >50.000 inw. 2025, 5.000-50.000 in 2027, <5.000 in 2030 Dummy-uitbreiding voor het website-prototype; niet gecontroleerd. | G31: ITY-26 | H31: Helpt bij: prestaties monitoren | I31: Welke risico’s moeten worden meegenomen? | J31: Gebouwgegevens en energielabel | K31: Vastgestelde verplichting en deadline | L31: Dummy: lees eerst de bron en controleer actuele voorwaarden. | M31: nee | N31: gemiddeld | O31: direct | P31: DV-01 | R31: PS-02 | S31: IS-01 | T31: hoog | U31: ja | W31: VS-02 | X31: 2026-10-02 | Y31: migratie catalogus v0.1 | Z31: 2026-10-02 | AA31: migratie catalogus v0.1 | AB31: concept | AC31: 1 | AF31: Onderwijshuisvesting uitgezonderd | Actualiteitsdatum v0.1: 2026-09 | DUMMY-aanvulling: benodigde_input, beoogde_output, centrale_gebruikersvraag, complexiteitsniveau, digitale_vorm_id, doel, doorlooptijd_categorie, gebruikstoelichting, publicatiestatus_id, relevantie_v1, tonen_in_v1, uitgebreide_omschrijving
A32: 6562981b-1a29-5a8b-b3db-c987a08a3e2b | B32: I-031 | C32: BNG Maatschappelijk Vastgoedlening | D32: BNG Maatschappelijk Vastgoedlening | E32: Nieuwe lening (mei 2026) via BNG Duurzaamheidsfonds/SVn voor scholen, kleine zorg, sport, kerken e.a.: 50.000-1 mln, looptijd tot 20 jaar, tot 100% financiering zonder eigen inbreng; rentekorting 2,65% bij leningen tot 250.000 (rijkssubsidie 32,6 mln op 130 mln leningen) | F32: Nieuwe lening (mei 2026) via BNG Duurzaamheidsfonds/SVn voor scholen, kleine zorg, sport, kerken e.a.: 50.000-1 mln, looptijd tot 20 jaar, tot 100% financiering zonder eigen inbreng; rentekorting 2,65% bij leningen tot 250.000 (rijkssubsidie 32,6 mln op 130 mln leningen) Dummy-uitbreiding voor het website-prototype; niet gecontroleerd. | G32: ITY-02 | H32: Helpt bij: investering voorbereiden | I32: Welke financieringsconstructie past? | J32: Investeringsbedrag, kasstroom en zekerheden | K32: Financieringsaanbod | L32: Dummy: lees eerst de bron en controleer actuele voorwaarden. | M32: ja | N32: basis | O32: weken | P32: DV-01 | R32: PS-02 | S32: IS-01 | T32: middel | U32: ja | W32: VS-02 | X32: 2026-10-02 | Y32: migratie catalogus v0.1 | Z32: 2026-10-02 | AA32: migratie catalogus v0.1 | AB32: concept | AC32: 1 | AF32: Combineerbaar met DUMAVA; niet voor gemeenten; ook zonder subsidierelatie | Actualiteitsdatum v0.1: 2026-09 | DUMMY-aanvulling: benodigde_input, beoogde_output, centrale_gebruikersvraag, complexiteitsniveau, digitale_vorm_id, doel, doorlooptijd_categorie, gebruikstoelichting, primaire_instrumenttype_id, publicatiestatus_id, relevantie_v1, tonen_in_v1, uitgebreide_omschrijving
A33: 9707e8a4-adc5-5dec-806a-c57cc6ff4b65 | B33: I-032 | C33: Fonds Verduurzaming Maatschappelijk Vastgoed (Gelderland/SVn) | D33: Fonds Verduurzaming Maatschappelijk Vastgoed (Gelderland/SVn) | E33: Provinciale lening 10.000-250.000 voor energiebesparing en opwek, looptijd 15 jaar, rente 2%; energieadvies vereist vanaf 50.000; niet voor gemeenten en corporaties. Voorbeeld van provinciale MV-fondsen | F33: Provinciale lening 10.000-250.000 voor energiebesparing en opwek, looptijd 15 jaar, rente 2%; energieadvies vereist vanaf 50.000; niet voor gemeenten en corporaties. Voorbeeld van provinciale MV-fondsen Dummy-uitbreiding voor het website-prototype; niet gecontroleerd. | G33: ITY-02 | H33: Helpt bij: investering voorbereiden | I33: Welke financieringsconstructie past? | J33: Investeringsbedrag, kasstroom en zekerheden | K33: Financieringsaanbod | L33: Dummy: lees eerst de bron en controleer actuele voorwaarden. | M33: ja | N33: basis | O33: weken | P33: DV-01 | R33: PS-02 | S33: IS-01 | T33: middel | U33: ja | W33: VS-02 | X33: 2026-10-02 | Y33: migratie catalogus v0.1 | Z33: 2026-10-02 | AA33: migratie catalogus v0.1 | AB33: concept | AC33: 1 | AF33: Per provincie verschillend; check eigen provincie | Actualiteitsdatum v0.1: 2026-09 | DUMMY-aanvulling: benodigde_input, beoogde_output, centrale_gebruikersvraag, complexiteitsniveau, digitale_vorm_id, doel, doorlooptijd_categorie, gebruikstoelichting, primaire_instrumenttype_id, publicatiestatus_id, relevantie_v1, tonen_in_v1, uitgebreide_omschrijving
A34: 69daceb2-596d-55c4-8f68-59cffcb18fba | B34: I-033 | C34: Regionale energiefondsen (overzicht REFS) | D34: Regionale energiefondsen (overzicht REFS) | E34: Provinciale en regionale energiefondsen (o.a. Energiefonds Drenthe) financieren besparing en opwek, ook vastgoedprojecten; overzicht op refs.nu | F34: Provinciale en regionale energiefondsen (o.a. Energiefonds Drenthe) financieren besparing en opwek, ook vastgoedprojecten; overzicht op refs.nu Dummy-uitbreiding voor het website-prototype; niet gecontroleerd. | G34: ITY-02 | H34: Helpt bij: investering voorbereiden | I34: Welke financieringsconstructie past? | J34: Investeringsbedrag, kasstroom en zekerheden | K34: Financieringsaanbod | L34: Dummy: lees eerst de bron en controleer actuele voorwaarden. | M34: nee | N34: gemiddeld | O34: weken | P34: DV-01 | R34: PS-01 | S34: IS-02 | T34: middel | U34: ja | W34: VS-02 | X34: 2026-10-02 | Y34: migratie catalogus v0.1 | Z34: 2026-10-02 | AA34: migratie catalogus v0.1 | AB34: concept | AC34: 1 | AF34: Voorwaarden per fonds sterk verschillend | Actualiteitsdatum v0.1: 2026-09 | DUMMY-aanvulling: benodigde_input, beoogde_output, centrale_gebruikersvraag, complexiteitsniveau, digitale_vorm_id, doel, doorlooptijd_categorie, gebruikstoelichting, primaire_instrumenttype_id, publicatiestatus_id, relevantie_v1, tonen_in_v1, uitgebreide_omschrijving
A35: d7c25398-97bd-5d1e-ab2d-33c04cc5057a | B35: I-034 | C35: ELENA (EIB) | D35: ELENA (EIB) | E35: Europese projectontwikkelingssteun (ca. 90% van de ontwikkelkosten) voor het bundelen van grotere investeringsprogramma's energie-efficientie in gebouwen; geschikt voor gemeentelijke of regionale programma's | F35: Europese projectontwikkelingssteun (ca. 90% van de ontwikkelkosten) voor het bundelen van grotere investeringsprogramma's energie-efficientie in gebouwen; geschikt voor gemeentelijke of regionale programma's Dummy-uitbreiding voor het website-prototype; niet gecontroleerd. | G35: ITY-01 | H35: Helpt bij: portefeuille prioriteren | I35: Welke subsidies zijn beschikbaar? | J35: Projectomschrijving, kosten en eigenaargegevens | K35: Subsidiebeschikking of toekenning | L35: Dummy: lees eerst de bron en controleer actuele voorwaarden. | M35: nee | N35: gemiddeld | O35: maanden | P35: DV-01 | R35: PS-01 | S35: IS-02 | T35: middel | U35: ja | W35: VS-02 | X35: 2026-10-02 | Y35: migratie catalogus v0.1 | Z35: 2026-10-02 | AA35: migratie catalogus v0.1 | AB35: concept | AC35: 1 | AF35: Vereist schaal (bundeling); lange doorlooptijd | Actualiteitsdatum v0.1: 2026-09 | DUMMY-aanvulling: benodigde_input, beoogde_output, centrale_gebruikersvraag, complexiteitsniveau, digitale_vorm_id, doel, doorlooptijd_categorie, gebruikstoelichting, publicatiestatus_id, relevantie_v1, tonen_in_v1, uitgebreide_omschrijving
A36: 4fe1fbd7-b026-55f8-92a2-8f8b53f7b274 | B36: I-035 | C36: EU-subsidies (EFRO/JTF e.a.) | D36: EU-subsidies (EFRO/JTF e.a.) | E36: Europese fondsen waarmee duurzaamheidsprojecten gefinancierd kunnen worden; aanvraag via landsdelige managementautoriteiten; door VNG genoemd als aanvullende bron | F36: Europese fondsen waarmee duurzaamheidsprojecten gefinancierd kunnen worden; aanvraag via landsdelige managementautoriteiten; door VNG genoemd als aanvullende bron Dummy-uitbreiding voor het website-prototype; niet gecontroleerd. | G36: ITY-01 | H36: Helpt bij: uitvoeringsprogramma opstellen | I36: Welke subsidies zijn beschikbaar? | J36: Projectomschrijving, kosten en eigenaargegevens | K36: Subsidiebeschikking of toekenning | L36: Dummy: lees eerst de bron en controleer actuele voorwaarden. | M36: nee | N36: gemiddeld | O36: maanden | P36: DV-01 | R36: PS-01 | S36: IS-02 | T36: middel | U36: ja | W36: VS-02 | X36: 2026-10-02 | Y36: migratie catalogus v0.1 | Z36: 2026-10-02 | AA36: migratie catalogus v0.1 | AB36: concept | AC36: 1 | AF36: Openstellingen per landsdeel en periode | Actualiteitsdatum v0.1: 2026-09 | DUMMY-aanvulling: benodigde_input, beoogde_output, centrale_gebruikersvraag, complexiteitsniveau, digitale_vorm_id, doel, doorlooptijd_categorie, gebruikstoelichting, publicatiestatus_id, relevantie_v1, tonen_in_v1, uitgebreide_omschrijving
A37: 77945447-b3c0-58d2-9b40-48aa3a12137b | B37: I-036 | C37: Duurzaam Monumenten-Lening (Restauratiefonds) | D37: Duurzaam Monumenten-Lening (Restauratiefonds) | E37: Laagrentende lening van het Nationaal Restauratiefonds voor het verduurzamen van monumenten; combineerbaar met SIM en DUMAVA (monumenten) | F37: Laagrentende lening van het Nationaal Restauratiefonds voor het verduurzamen van monumenten; combineerbaar met SIM en DUMAVA (monumenten) Dummy-uitbreiding voor het website-prototype; niet gecontroleerd. | G37: ITY-02 | H37: Helpt bij: investering voorbereiden | I37: Welke financieringsconstructie past? | J37: Investeringsbedrag, kasstroom en zekerheden | K37: Financieringsaanbod | L37: Dummy: lees eerst de bron en controleer actuele voorwaarden. | M37: ja | N37: basis | O37: weken | P37: DV-01 | R37: PS-01 | S37: IS-02 | T37: middel | U37: ja | W37: VS-02 | X37: 2026-10-02 | Y37: migratie catalogus v0.1 | Z37: 2026-10-02 | AA37: migratie catalogus v0.1 | AB37: concept | AC37: 1 | AF37: Actualiteitsdatum v0.1: 2026-09 | DUMMY-aanvulling: benodigde_input, beoogde_output, centrale_gebruikersvraag, complexiteitsniveau, digitale_vorm_id, doel, doorlooptijd_categorie, gebruikstoelichting, primaire_instrumenttype_id, publicatiestatus_id, relevantie_v1, tonen_in_v1, uitgebreide_omschrijving
... A48: f6c6fb1f-f7a1-5d7a-b1fa-ee9cbb35fa65 | B48: I-047 | C48: DMJOP (duurzaam meerjarenonderhoudsplan) | D48: DMJOP (duurzaam meerjarenonderhoudsplan) | E48: Koppelt verduurzamingsmaatregelen aan natuurlijke onderhoudsmomenten en al gereserveerde onderhouds- en projectbudgetten; deel dekking uit toekomstige energiebesparing | F48: Koppelt verduurzamingsmaatregelen aan natuurlijke onderhoudsmomenten en al gereserveerde onderhouds- en projectbudgetten; deel dekking uit toekomstige energiebesparing Dummy-uitbreiding voor het website-prototype; niet gecontroleerd. | G48: ITY-23 | H48: Helpt bij: accommodatie vernieuwen | I48: Hoe landt de investering in begroting en MIP? | J48: Beleids- en portefeuillegegevens | K48: Ingevuld format | L48: Dummy: lees eerst de bron en controleer actuele voorwaarden. | M48: nee | N48: gemiddeld | O48: dagen | P48: DV-05 | R48: PS-02 | S48: IS-01 | T48: hoog | U48: ja | W48: VS-02 | X48: 2026-10-02 | Y48: migratie catalogus v0.1 | Z48: 2026-10-02 | AA48: migratie catalogus v0.1 | AB48: concept | AC48: 1 | AF48: Basis voor voorziening groot onderhoud (I-020) | Actualiteitsdatum v0.1: 2026-09 | DUMMY-aanvulling: benodigde_input, beoogde_output, centrale_gebruikersvraag, complexiteitsniveau, digitale_vorm_id, doel, doorlooptijd_categorie, gebruikstoelichting, primaire_instrumenttype_id, publicatiestatus_id, relevantie_v1, tonen_in_v1, uitgebreide_omschrijving
A49: e8ea5aa1-171d-52e2-aea9-c9fbb2d6e20b | B49: I-048 | C49: Intern revolverend verduurzamingsfonds | D49: Intern revolverend verduurzamingsfonds | E49: Gemeentelijk fonds waarin gerealiseerde energiebesparingen terugvloeien en opnieuw worden ingezet voor volgende verduurzamingsprojecten | F49: Gemeentelijk fonds waarin gerealiseerde energiebesparingen terugvloeien en opnieuw worden ingezet voor volgende verduurzamingsprojecten Dummy-uitbreiding voor het website-prototype; niet gecontroleerd. | G49: ITY-11 | H49: Helpt bij: portefeuille prioriteren | I49: Welke structurele lasten ontstaan? | J49: Boekwaarde, afschrijvingstermijn, begrotingsruimte | K49: Dekking in begroting of exploitatie | L49: Dummy: lees eerst de bron en controleer actuele voorwaarden. | M49: nee | N49: gemiddeld | O49: weken | P49: DV-04 | R49: PS-01 | S49: IS-03 | T49: laag | U49: nee | V49: Dummy: instrument nog in ontwikkeling | W49: VS-02 | X49: 2026-10-02 | Y49: migratie catalogus v0.1 | Z49: 2026-10-02 | AA49: migratie catalogus v0.1 | AB49: concept | AC49: 1 | AF49: Route en spelregels uitwerken (BBV) | Actualiteitsdatum v0.1: 2026-09 | DUMMY-aanvulling: benodigde_input, beoogde_output, centrale_gebruikersvraag, complexiteitsniveau, digitale_vorm_id, doel, doorlooptijd_categorie, gebruikstoelichting, publicatiestatus_id, reden_niet_tonen, relevantie_v1, tonen_in_v1, uitgebreide_omschrijving
A50: 57bd6d36-474b-527b-aecb-98b5fb724c46 | B50: I-049 | C50: Expertisecentrum Verduurzaming Zorg: regelingenoverzicht | D50: Expertisecentrum Verduurzaming Zorg: regelingenoverzicht | E50: Sectorloket zorg met actueel overzicht van subsidies, lokale regelingen en fondsen voor zorgvastgoed, incl. DUMAVA-uitleg | F50: Sectorloket zorg met actueel overzicht van subsidies, lokale regelingen en fondsen voor zorgvastgoed, incl. DUMAVA-uitleg Dummy-uitbreiding voor het website-prototype; niet gecontroleerd. | G50: ITY-24 | H50: Helpt bij: investering voorbereiden | I50: Wat kost niets doen? | J50: Geen | K50: Inzicht en werkwijze | L50: Dummy: lees eerst de bron en controleer actuele voorwaarden. | M50: ja | N50: basis | O50: direct | P50: DV-04 | R50: PS-04 | S50: IS-01 | T50: middel | U50: ja | W50: VS-02 | X50: 2026-10-02 | Y50: migratie catalogus v0.1 | Z50: 2026-10-02 | AA50: migratie catalogus v0.1 | AB50: concept | AC50: 1 | AF50: Actualiteitsdatum v0.1: 2026-09 | DUMMY-aanvulling: benodigde_input, beoogde_output, centrale_gebruikersvraag, complexiteitsniveau, digitale_vorm_id, doel, doorlooptijd_categorie, gebruikstoelichting, primaire_instrumenttype_id, publicatiestatus_id, relevantie_v1, tonen_in_v1, uitgebreide_omschrijving
A51: ff4bafcc-8aa6-52fe-8a81-82eef82e2b3f | B51: I-050 | C51: NPLW-database subsidies en regelingen | D51: NPLW-database subsidies en regelingen | E51: Database van het Nationaal Programma Lokale Warmtetransitie met financieringsregelingen (o.a. BNG Duurzaamheidsfonds) voor gemeenten en gebouweigenaren | F51: Database van het Nationaal Programma Lokale Warmtetransitie met financieringsregelingen (o.a. BNG Duurzaamheidsfonds) voor gemeenten en gebouweigenaren Dummy-uitbreiding voor het website-prototype; niet gecontroleerd. | G51: ITY-24 | H51: Helpt bij: uitvoeringsprogramma opstellen | I51: Wat kost niets doen? | J51: Geen | K51: Inzicht en werkwijze | L51: Dummy: lees eerst de bron en controleer actuele voorwaarden. | M51: ja | N51: basis | O51: direct | P51: DV-04 | R51: PS-02 | S51: IS-01 | T51: hoog | U51: ja | W51: VS-02 | X51: 2026-10-02 | Y51: migratie catalogus v0.1 | Z51: 2026-10-02 | AA51: migratie catalogus v0.1 | AB51: concept | AC51: 1 | AF51: Actualiteitsdatum v0.1: 2026-09 | DUMMY-aanvulling: benodigde_input, beoogde_output, centrale_gebruikersvraag, complexiteitsniveau, digitale_vorm_id, doel, doorlooptijd_categorie, gebruikstoelichting, primaire_instrumenttype_id, publicatiestatus_id, relevantie_v1, tonen_in_v1, uitgebreide_omschrijving
A52: 6e66d1d7-0362-5fbb-bd25-d67757b5b3f7 | B52: I-051 | C52: Fonds Nieuwe Doen rentekorting maatschappelijk vastgoed | D52: Fonds Nieuwe Doen rentekorting maatschappelijk vastgoed | E52: Rentekorting op leningen voor verduurzaming van maatschappelijk vastgoed in Groningen. | F52: Rentekorting op leningen voor verduurzaming van maatschappelijk vastgoed in Groningen. Dummy-uitbreiding voor het website-prototype; niet gecontroleerd. | G52: ITY-02 | H52: Helpt bij: investering voorbereiden | I52: Welke financieringsconstructie past? | J52: Investeringsbedrag, kasstroom en zekerheden | K52: Financieringsaanbod | L52: Dummy: lees eerst de bron en controleer actuele voorwaarden. | M52: nee | N52: gemiddeld | O52: weken | P52: DV-01 | Q52: https://www.provinciegroningen.nl/actueel/nieuws/nieuwsartikel/aantrekkelijke-rentekortingsregeling-voor-leningen-verduurzaming-maatschappelijk-vastgoed/ | R52: PS-02 | S52: IS-01 | T52: hoog | U52: ja | W52: VS-02 | X52: 2026-10-02 | Y52: migratie catalogus v0.1 | Z52: 2026-10-02 | AA52: migratie catalogus v0.1 | AB52: concept | AC52: 1 | AF52: Ook voor huurders die energiekosten dragen; lokale stapeling mogelijk | Actualiteitsdatum v0.1: 2026-09 | DUMMY-aanvulling: benodigde_input, beoogde_output, centrale_gebruikersvraag, complexiteitsniveau, digitale_vorm_id, doel, doorlooptijd_categorie, gebruikstoelichting, primaire_instrumenttype_id, publicatiestatus_id, relevantie_v1, tonen_in_v1, uitgebreide_omschrijving
A53: 6f6a8d40-0be7-5b02-800c-1847a867a116 | B53: I-052 | C53: Maatschappelijk Vastgoedlening Limburg | D53: Maatschappelijk Vastgoedlening Limburg | E53: Provinciale lening voor verduurzaming en combinatiewerken bij maatschappelijk vastgoed. | F53: Provinciale lening voor verduurzaming en combinatiewerken bij maatschappelijk vastgoed. Dummy-uitbreiding voor het website-prototype; niet gecontroleerd. | G53: ITY-02 | H53: Helpt bij: investering voorbereiden | I53: Welke financieringsconstructie past? | J53: Investeringsbedrag, kasstroom en zekerheden | K53: Financieringsaanbod | L53: Dummy: lees eerst de bron en controleer actuele voorwaarden. | M53: nee | N53: gemiddeld | O53: weken | P53: DV-01 | Q53: https://www.limburg.nl/actueel/nieuws/nieuwsberichten/2026/september/fonds-verduurzaming-maatschappelijk/ | R53: PS-02 | S53: IS-01 | T53: hoog | U53: ja | W53: VS-02 | X53: 2026-10-02 | Y53: migratie catalogus v0.1 | Z53: 2026-10-02 | AA53: migratie catalogus v0.1 | AB53: concept | AC53: 1 | AF53: Aansluiting op ontzorgingsprogramma Limburg Bespaart | Actualiteitsdatum v0.1: 2026-09 | DUMMY-aanvulling: benodigde_input, beoogde_output, centrale_gebruikersvraag, complexiteitsniveau, digitale_vorm_id, doel, doorlooptijd_categorie, gebruikstoelichting, primaire_instrumenttype_id, publicatiestatus_id, relevantie_v1, tonen_in_v1, uitgebreide_omschrijving
A54: be4fdf25-f998-5bf0-ab9d-e4de4b6741fb | B54: I-053 | C54: Stimuleringslening verduurzamen maatschappelijk vastgoed Hardenberg | D54: Stimuleringslening verduurzamen maatschappelijk vastgoed Hardenberg | E54: Lokale zakelijke SVn-lening voor maatschappelijke non-profitorganisaties. | F54: Lokale zakelijke SVn-lening voor maatschappelijke non-profitorganisaties. Dummy-uitbreiding voor het website-prototype; niet gecontroleerd. | G54: ITY-02 | H54: Helpt bij: investering voorbereiden | I54: Welke financieringsconstructie past? | J54: Investeringsbedrag, kasstroom en zekerheden | K54: Financieringsaanbod | L54: Dummy: lees eerst de bron en controleer actuele voorwaarden. | M54: nee | N54: gemiddeld | O54: weken | P54: DV-01 | Q54: https://lokaleregelgeving.overheid.nl/CVDR736141/ | R54: PS-04 | S54: IS-01 | T54: middel | U54: ja | W54: VS-02 | X54: 2026-10-02 | Y54: migratie catalogus v0.1 | Z54: 2026-10-02 | AA54: migratie catalogus v0.1 | AB54: concept | AC54: 1 | AF54: Voorbeeld van lokale aanvullende leenroute | Actualiteitsdatum v0.1: 2026-09 | DUMMY-aanvulling: benodigde_input, beoogde_output, centrale_gebruikersvraag, complexiteitsniveau, digitale_vorm_id, doel, doorlooptijd_categorie, gebruikstoelichting, primaire_instrumenttype_id, publicatiestatus_id, relevantie_v1, tonen_in_v1, uitgebreide_omschrijving
A55: 7c8b62fc-d0cc-5b2b-961b-b2feaf7f0dad | B55: I-054 | C55: Waarborgfonds voor de Zorgsector | D55: Waarborgfonds voor de Zorgsector | E55: Borging voor leningen van toegelaten zorginstellingen. | F55: Borging voor leningen van toegelaten zorginstellingen. Dummy-uitbreiding voor het website-prototype; niet gecontroleerd. | G55: ITY-03 | H55: Helpt bij: uitvoeringsprogramma opstellen | I55: Welke financieringsconstructie past? | J55: Financieringsaanvraag en jaarcijfers | K55: Borgstelling of garantie | L55: Dummy: lees eerst de bron en controleer actuele voorwaarden. | M55: nee | N55: gemiddeld | O55: weken | P55: DV-01 | Q55: https://www.wfz.nl/ | R55: PS-01 | S55: IS-02 | T55: middel | U55: ja | W55: VS-02 | X55: 2026-10-02 | Y55: migratie catalogus v0.1 | Z55: 2026-10-02 | AA55: migratie catalogus v0.1 | AB55: concept | AC55: 1 | AF55: Toelating en projectvoorwaarden per casus toetsen | Actualiteitsdatum v0.1: 2026-09 | DUMMY-aanvulling: benodigde_input, beoogde_output, centrale_gebruikersvraag, complexiteitsniveau, digitale_vorm_id, doel, doorlooptijd_categorie, gebruikstoelichting, primaire_instrumenttype_id, publicatiestatus_id, relevantie_v1, tonen_in_v1, uitgebreide_omschrijving
A56: 3332e115-7812-5247-abae-40350ad913e5 | B56: I-055 | C56: WarmteBoost werkboeken en routekaart | D56: WarmteBoost werkboeken en routekaart | E56: Werkboeken, begeleiding en Excel-routekaart voor verduurzaming van buurt- en dorpshuizen. | F56: Werkboeken, begeleiding en Excel-routekaart voor verduurzaming van buurt- en dorpshuizen. Dummy-uitbreiding voor het website-prototype; niet gecontroleerd. | G56: ITY-30 | H56: Helpt bij: object verduurzamen | I56: Wat is de totale investeringsbehoefte? | J56: Intake en objectgegevens | K56: Advies of uitvoeringsondersteuning | L56: Dummy: lees eerst de bron en controleer actuele voorwaarden. | M56: ja | N56: specialistisch | O56: weken | P56: DV-12 | Q56: https://www.lsabewoners.nl/buurtenergie/stap-voor-stap-verduurzamen-met-warmteboost-werkboeken/ | R56: PS-02 | S56: IS-01 | T56: middel | U56: ja | W56: VS-02 | X56: 2026-10-02 | Y56: migratie catalogus v0.1 | Z56: 2026-10-02 | AA56: migratie catalogus v0.1 | AB56: concept | AC56: 1 | AF56: Sociaal-vastgoed-specifieke uitvoeringsroute | Actualiteitsdatum v0.1: 2026-09 | DUMMY-aanvulling: benodigde_input, beoogde_output, centrale_gebruikersvraag, complexiteitsniveau, digitale_vorm_id, doel, doorlooptijd_categorie, gebruikstoelichting, publicatiestatus_id, relevantie_v1, tonen_in_v1, uitgebreide_omschrijving
A57: 53bc68e2-b091-5e3c-923c-42e506cb225f | B57: I-056 | C57: Subsidie verduurzaming dorpshuizen, buurthuizen en wijkcentra Noord-Holland | D57: Subsidie verduurzaming dorpshuizen, buurthuizen en wijkcentra Noord-Holland | E57: Provinciale subsidie voor verduurzaming van sociale ontmoetingsgebouwen. | F57: Provinciale subsidie voor verduurzaming van sociale ontmoetingsgebouwen. Dummy-uitbreiding voor het website-prototype; niet gecontroleerd. | G57: ITY-01 | H57: Helpt bij: investering voorbereiden | I57: Welke subsidies zijn beschikbaar? | J57: Projectomschrijving, kosten en eigenaargegevens | K57: Subsidiebeschikking of toekenning | L57: Dummy: lees eerst de bron en controleer actuele voorwaarden. | M57: ja | N57: basis | O57: maanden | P57: DV-01 | Q57: https://www.noord-holland.nl/Loket/Producten_en_Diensten/Producten_op_alfabet/V/Verduurzaming_dorpshuizen_buurthuizen_en_wijkcentra_subsidie | R57: PS-01 | S57: IS-02 | T57: middel | U57: ja | W57: VS-02 | X57: 2026-10-02 | Y57: migratie catalogus v0.1 | Z57: 2026-10-02 | AA57: migratie catalogus v0.1 | AB57: concept | AC57: 1 | AF57: Ronde en voorwaarden jaarlijks actualiseren | Actualiteitsdatum v0.1: 2026-09 | DUMMY-aanvulling: benodigde_input, beoogde_output, centrale_gebruikersvraag, complexiteitsniveau, digitale_vorm_id, doel, doorlooptijd_categorie, gebruikstoelichting, publicatiestatus_id, relevantie_v1, tonen_in_v1, uitgebreide_omschrijving
A58: 241f32f7-8385-50c6-9c25-48eed2f00884 | B58: I-057 | C58: Crowdfunding / community finance | D58: Crowdfunding / community finance | E58: Aanvullende financieringsroute via achterban of lokale gemeenschap. | F58: Aanvullende financieringsroute via achterban of lokale gemeenschap. Dummy-uitbreiding voor het website-prototype; niet gecontroleerd. | G58: ITY-02 | H58: Helpt bij: investering voorbereiden | I58: Welke financieringsconstructie past? | J58: Investeringsbedrag, kasstroom en zekerheden | K58: Financieringsaanbod | L58: Dummy: lees eerst de bron en controleer actuele voorwaarden. | M58: nee | N58: gemiddeld | O58: weken | P58: DV-01 | Q58: https://infographics.rvo.nl/financiele-wegwijzer/ | R58: PS-01 | S58: IS-02 | T58: middel | U58: ja | W58: VS-02 | X58: 2026-10-02 | Y58: migratie catalogus v0.1 | Z58: 2026-10-02 | AA58: migratie catalogus v0.1 | AB58: concept | AC58: 1 | AF58: Geen uniforme regeling; kosten, risico en voorwaarden verschillen | Actualiteitsdatum v0.1: 2026-09 | DUMMY-aanvulling: benodigde_input, beoogde_output, centrale_gebruikersvraag, complexiteitsniveau, digitale_vorm_id, doel, doorlooptijd_categorie, gebruikstoelichting, primaire_instrumenttype_id, publicatiestatus_id, relevantie_v1, tonen_in_v1, uitgebreide_omschrijving
A59: 82578548-5018-52ef-a533-d1a0c0658c77 | B59: I-058 | C59: Green lease / duurzaamheidsallonge | D59: Green lease / duurzaamheidsallonge | E59: Contractafspraken tussen eigenaar en huurder over maatregelen, kosten, baten en prestaties. | F59: Contractafspraken tussen eigenaar en huurder over maatregelen, kosten, baten en prestaties. Dummy-uitbreiding voor het website-prototype; niet gecontroleerd. | G59: ITY-12 | H59: Helpt bij: investering voorbereiden | I59: Welke financieringsconstructie past? | J59: Programma van eisen en risicoverdeling | K59: Contract met uitvoerder of financier | L59: Dummy: lees eerst de bron en controleer actuele voorwaarden. | M59: nee | N59: gemiddeld | O59: maanden | P59: DV-04 | Q59: https://www.rvo.nl/onderwerpen/verduurzaming-utiliteitsbouw/maatschappelijk-vastgoed/tools-aan-de-slag | R59: PS-02 | S59: IS-01 | T59: hoog | U59: ja | W59: VS-02 | X59: 2026-10-02 | Y59: migratie catalogus v0.1 | Z59: 2026-10-02 | AA59: migratie catalogus v0.1 | AB59: concept | AC59: 1 | AF59: Aanvullend op menukaart huurder-verhuurderafspraken | Actualiteitsdatum v0.1: 2026-09 | DUMMY-aanvulling: benodigde_input, beoogde_output, centrale_gebruikersvraag, complexiteitsniveau, digitale_vorm_id, doel, doorlooptijd_categorie, gebruikstoelichting, publicatiestatus_id, relevantie_v1, tonen_in_v1, uitgebreide_omschrijving
A60: 5e88bc9e-854d-536c-b371-5d69b93a4b6b | B60: I-059 | C60: Algemeenbelangbesluit en beleidshuur | D60: Algemeenbelangbesluit en beleidshuur | E60: Juridisch-bestuurlijke route om maatschappelijke verhuur onder kostprijs te motiveren binnen Wet Markt en Overheid. | F60: Juridisch-bestuurlijke route om maatschappelijke verhuur onder kostprijs te motiveren binnen Wet Markt en Overheid. Dummy-uitbreiding voor het website-prototype; niet gecontroleerd. | G60: ITY-11 | H60: Helpt bij: strategie herijken | I60: Welke structurele lasten ontstaan? | J60: Boekwaarde, afschrijvingstermijn, begrotingsruimte | K60: Dekking in begroting of exploitatie | L60: Dummy: lees eerst de bron en controleer actuele voorwaarden. | M60: nee | N60: gemiddeld | O60: weken | P60: DV-04 | Q60: https://bouwstenen.nl/huurprijsmethodiek | R60: PS-01 | S60: IS-02 | T60: middel | U60: ja | W60: VS-02 | X60: 2026-10-02 | Y60: migratie catalogus v0.1 | Z60: 2026-10-02 | AA60: migratie catalogus v0.1 | AB60: concept | AC60: 1 | AF60: Geen geldstroom, wel essentieel voor betaalbaarheid en subsidierelatie | Actualiteitsdatum v0.1: 2026-09 | DUMMY-aanvulling: benodigde_input, beoogde_output, centrale_gebruikersvraag, complexiteitsniveau, digitale_vorm_id, doel, doorlooptijd_categorie, gebruikstoelichting, publicatiestatus_id, relevantie_v1, tonen_in_v1, uitgebreide_omschrijving
A61: bfde6caa-cbfd-5b52-982a-40bdf9217390 | B61: I-060 | C61: Grond- en verkoopopbrengstenreserve | D61: Grond- en verkoopopbrengstenreserve | E61: Verkoopopbrengsten uit vastgoed of grond worden geoormerkt als dekking voor verduurzaming. | F61: Verkoopopbrengsten uit vastgoed of grond worden geoormerkt als dekking voor verduurzaming. Dummy-uitbreiding voor het website-prototype; niet gecontroleerd. | G61: ITY-11 | H61: Helpt bij: portefeuille prioriteren | I61: Welke structurele lasten ontstaan? | J61: Boekwaarde, afschrijvingstermijn, begrotingsruimte | K61: Dekking in begroting of exploitatie | L61: Dummy: lees eerst de bron en controleer actuele voorwaarden. | M61: nee | N61: gemiddeld | O61: weken | P61: DV-04 | Q61: https://bouwstenen.nl/handreiking-paragraaf-kapitaalgoederen | R61: PS-01 | S61: IS-03 | T61: laag | U61: nee | V61: Dummy: instrument nog in ontwikkeling | W61: VS-02 | X61: 2026-10-02 | Y61: migratie catalogus v0.1 | Z61: 2026-10-02 | AA61: migratie catalogus v0.1 | AB61: concept | AC61: 1 | AF61: Lokale beleidskeuze; geen landelijke standaard | Actualiteitsdatum v0.1: 2026-09 | DUMMY-aanvulling: benodigde_input, beoogde_output, centrale_gebruikersvraag, complexiteitsniveau, digitale_vorm_id, doel, doorlooptijd_categorie, gebruikstoelichting, publicatiestatus_id, reden_niet_tonen, relevantie_v1, tonen_in_v1, uitgebreide_omschrijving
A62: 168cdc68-0122-522e-ba88-ecc156067301 | B62: I-061 | C62: TCO-model onderwijshuisvesting | D62: TCO-model onderwijshuisvesting | E62: Rekenmodel voor bouw of renovatie, exploitatie en onderhoud over de levensduur. | F62: Rekenmodel voor bouw of renovatie, exploitatie en onderhoud over de levensduur. Dummy-uitbreiding voor het website-prototype; niet gecontroleerd. | G62: ITY-14 | H62: Helpt bij: portefeuille prioriteren | I62: Wat kost niets doen? | J62: Kosten, levensduur en exploitatiegegevens | K62: Doorrekening van varianten | L62: Dummy: lees eerst de bron en controleer actuele voorwaarden. | M62: nee | N62: gemiddeld | O62: dagen | P62: DV-03 | Q62: https://www.pohv.nl/kennis-tools/kennisbank/rekenmodel-total-cost-of-ownership-tco | R62: PS-01 | S62: IS-02 | T62: middel | U62: ja | W62: VS-02 | X62: 2026-10-02 | Y62: migratie catalogus v0.1 | Z62: 2026-10-02 | AA62: migratie catalogus v0.1 | AB62: concept | AC62: 1 | AF62: Blueprint voor gedeelde gemeente-schoolbestuur-businesscase | Actualiteitsdatum v0.1: 2026-09 | DUMMY-aanvulling: benodigde_input, beoogde_output, centrale_gebruikersvraag, complexiteitsniveau, digitale_vorm_id, doel, doorlooptijd_categorie, gebruikstoelichting, primaire_instrumenttype_id, publicatiestatus_id, relevantie_v1, tonen_in_v1, uitgebreide_omschrijving
A63: 5b64627d-4931-52ce-a916-15bfdb9a31a9 | B63: I-062 | C63: CO2-routekaart en rekentool zorg | D63: CO2-routekaart en rekentool zorg | E63: Portefeuille- en objecttool voor maatregelen, CO2, kosten en investeringen in zorgvastgoed. | F63: Portefeuille- en objecttool voor maatregelen, CO2, kosten en investeringen in zorgvastgoed. Dummy-uitbreiding voor het website-prototype; niet gecontroleerd. | G63: ITY-15 | H63: Helpt bij: portefeuille prioriteren | I63: Welke subsidies zijn beschikbaar? | J63: Basisgegevens object | K63: Indicatief resultaat na invoer | L63: Dummy: lees eerst de bron en controleer actuele voorwaarden. | M63: ja | N63: basis | O63: direct | P63: DV-08 | Q63: https://www.expertisecentrumverduurzamingzorg.nl/co2-routekaart/ | R63: PS-02 | S63: IS-01 | T63: hoog | U63: ja | W63: VS-02 | X63: 2026-10-02 | Y63: migratie catalogus v0.1 | Z63: 2026-10-02 | AA63: migratie catalogus v0.1 | AB63: concept | AC63: 1 | AF63: Sectorspecifiek voorbeeld voor het Kompas | Actualiteitsdatum v0.1: 2026-09 | DUMMY-aanvulling: benodigde_input, beoogde_output, centrale_gebruikersvraag, complexiteitsniveau, digitale_vorm_id, doel, doorlooptijd_categorie, gebruikstoelichting, primaire_instrumenttype_id, publicatiestatus_id, relevantie_v1, tonen_in_v1, uitgebreide_omschrijving
A64: 9e626dff-b0bd-5b92-b8d6-967dca0b7f1c | B64: I-063 | C64: Subsidiewijzer verduurzaming sportaccommodaties | D64: Subsidiewijzer verduurzaming sportaccommodaties | E64: Sectorale matcher voor subsidies voor verduurzaming van sportaccommodaties. | F64: Sectorale matcher voor subsidies voor verduurzaming van sportaccommodaties. Dummy-uitbreiding voor het website-prototype; niet gecontroleerd. | G64: ITY-15 | H64: Helpt bij: investering voorbereiden | I64: Welke subsidies zijn beschikbaar? | J64: Basisgegevens object | K64: Indicatief resultaat na invoer | L64: Dummy: lees eerst de bron en controleer actuele voorwaarden. | M64: ja | N64: basis | O64: direct | P64: DV-08 | Q64: https://www.kenniscentrumsportenbewegen.nl/producten/subsidiewijzer-verduurzaming-sportaccommodaties/ | R64: PS-02 | S64: IS-01 | T64: hoog | U64: ja | W64: VS-02 | X64: 2026-10-02 | Y64: migratie catalogus v0.1 | Z64: 2026-10-02 | AA64: migratie catalogus v0.1 | AB64: concept | AC64: 1 | AF64: Wijzer, geen geldstroom zelf | Actualiteitsdatum v0.1: 2026-09 | DUMMY-aanvulling: benodigde_input, beoogde_output, centrale_gebruikersvraag, complexiteitsniveau, digitale_vorm_id, doel, doorlooptijd_categorie, gebruikstoelichting, primaire_instrumenttype_id, publicatiestatus_id, relevantie_v1, tonen_in_v1, uitgebreide_omschrijving
A65: 54dce8b3-394b-584b-81f4-487978b05bae | B65: I-064 | C65: Museum Financieringswijzer | D65: Museum Financieringswijzer | E65: Sectorspecifieke wijzer voor subsidies en leningen voor musea. | F65: Sectorspecifieke wijzer voor subsidies en leningen voor musea. Dummy-uitbreiding voor het website-prototype; niet gecontroleerd. | G65: ITY-15 | H65: Helpt bij: investering voorbereiden | I65: Welke subsidies zijn beschikbaar? | J65: Basisgegevens object | K65: Indicatief resultaat na invoer | L65: Dummy: lees eerst de bron en controleer actuele voorwaarden. | M65: ja | N65: basis | O65: direct | P65: DV-08 | Q65: https://museumvereniging.nl/financieringswijzer/ | R65: PS-02 | S65: IS-01 | T65: middel | U65: ja | W65: VS-02 | X65: 2026-10-02 | Y65: migratie catalogus v0.1 | Z65: 2026-10-02 | AA65: migratie catalogus v0.1 | AB65: concept | AC65: 1 | AF65: Sectorspecifieke financiële navigatie | Actualiteitsdatum v0.1: 2026-09 | DUMMY-aanvulling: benodigde_input, beoogde_output, centrale_gebruikersvraag, complexiteitsniveau, digitale_vorm_id, doel, doorlooptijd_categorie, gebruikstoelichting, primaire_instrumenttype_id, publicatiestatus_id, relevantie_v1, tonen_in_v1, uitgebreide_omschrijving
A66: 7fd46f3d-8244-53a0-ba66-39f3204ce81f | B66: I-065 | C66: Functiecombinatie en hogere bezettingsgraad | D66: Functiecombinatie en hogere bezettingsgraad | E66: Verbeter de exploitatie door delen, functiemenging, herprogrammeren en reduceren van vierkante meters. | F66: Verbeter de exploitatie door delen, functiemenging, herprogrammeren en reduceren van vierkante meters. Dummy-uitbreiding voor het website-prototype; niet gecontroleerd. | G66: ITY-11 | H66: Helpt bij: portefeuille prioriteren | I66: Welke structurele lasten ontstaan? | J66: Boekwaarde, afschrijvingstermijn, begrotingsruimte | K66: Dekking in begroting of exploitatie | L66: Dummy: lees eerst de bron en controleer actuele voorwaarden. | M66: nee | N66: gemiddeld | O66: weken | P66: DV-04 | Q66: https://bouwstenen.nl/beter-benutten-van-ruimte | R66: PS-04 | S66: IS-01 | T66: hoog | U66: ja | W66: VS-02 | X66: 2026-10-02 | Y66: migratie catalogus v0.1 | Z66: 2026-10-02 | AA66: migratie catalogus v0.1 | AB66: concept | AC66: 1 | AF66: Voorzieningenbeleid is randvoorwaarde | Actualiteitsdatum v0.1: 2026-09 | DUMMY-aanvulling: benodigde_input, beoogde_output, centrale_gebruikersvraag, complexiteitsniveau, digitale_vorm_id, doel, doorlooptijd_categorie, gebruikstoelichting, publicatiestatus_id, relevantie_v1, tonen_in_v1, uitgebreide_omschrijving
